Workbook

Sheet I 2024
A1: Resultado | B1: 45292 | C1: 45323 | D1: 45352 | E1: 45383 | F1: 45413 | G1: 45444 | H1: 45474 | I1: 45505 | J1: 45536 | K1: 45566 | L1: 45597 | M1: 45627 | N1: Total
A2: Resultado | N2: Total
A3: Receita operacional bruta | B3: 450429 | C3: 0 | D3: 0 | E3: 0 | F3: 0 | G3: 0 | H3: 0 | I3: 0 | J3: 0 | K3: 0 | L3: 0 | M3: 0 | N3: 450429
A4: [-] 10 - Receita | B4: 450429 | C4: 0 | D4: 0 | E4: 0 | F4: 0 | G4: 0 | H4: 0 | I4: 0 | J4: 0 | K4: 0 | L4: 0 | M4: 0 | N4: 450429
A5: 10.01 - Receita com produto | B5: 449858 | C5: 0 | D5: 0 | E5: 0 | F5: 0 | G5: 0 | H5: 0 | I5: 0 | J5: 0 | K5: 0 | L5: 0 | M5: 0 | N5: 449858
A6: 10.03 - Outras Receitas | B6: 571 | C6: 0 | D6: 0 | E6: 0 | F6: 0 | G6: 0 | H6: 0 | I6: 0 | J6: 0 | K6: 0 | L6: 0 | M6: 0 | N6: 571
A7: Custos de venda | B7: -11749 | C7: 0 | D7: 0 | E7: 0 | F7: 0 | G7: 0 | H7: 0 | I7: 0 | J7: 0 | K7: 0 | L7: 0 | M7: 0 | N7: -11749
A8: [-] 20 - Impostos sobre a receita | B8: -11749 | C8: 0 | D8: 0 | E8: 0 | F8: 0 | G8: 0 | H8: 0 | I8: 0 | J8: 0 | K8: 0 | L8: 0 | M8: 0 | N8: -11749
A9: 20.04 - ICMS - ST | B9: -11749 | C9: 0 | D9: 0 | E9: 0 | F9: 0 | G9: 0 | H9: 0 | I9: 0 | J9: 0 | K9: 0 | L9: 0 | M9: 0 | N9: -11749
A10: 21 - Crédito de impostos | B10: 0 | C10: 0 | D10: 0 | E10: 0 | F10: 0 | G10: 0 | H10: 0 | I10: 0 | J10: 0 | K10: 0 | L10: 0 | M10: 0 | N10: 0
A11: 22 - Repasse aos distribuidores | B11: 0 | C11: 0 | D11: 0 | E11: 0 | F11: 0 | G11: 0 | H11: 0 | I11: 0 | J11: 0 | K11: 0 | L11: 0 | M11: 0 | N11: 0
A12: 55 - Devolução de Terceiros | B12: 0 | C12: 0 | D12: 0 | E12: 0 | F12: 0 | G12: 0 | H12: 0 | I12: 0 | J12: 0 | K12: 0 | L12: 0 | M12: 0 | N12: 0
A13: ( = ) Receita operacional líquida | B13: 438680 | C13: 0 | D13: 0 | E13: 0 | F13: 0 | G13: 0 | H13: 0 | I13: 0 | J13: 0 | K13: 0 | L13: 0 | M13: 0 | N13: 438680
A14: Receita operacional líquida ( % ) | B14: 0.97 | C14: % | D14: % | E14: % | F14: % | G14: % | H14: % | I14: % | J14: % | K14: % | L14: % | M14: % | N14: 0.97
A15: Custos Operacionais Variáveis | B15: -269834 | C15: 0 | D15: 0 | E15: 0 | F15: 0 | G15: 0 | H15: 0 | I15: 0 | J15: 0 | K15: 0 | L15: 0 | M15: 0 | N15: -269834
A16: [-] 29 - Despesas com Pessoal - Operacional | B16: -25339 | C16: 0 | D16: 0 | E16: 0 | F16: 0 | G16: 0 | H16: 0 | I16: 0 | J16: 0 | K16: 0 | L16: 0 | M16: 0 | N16: -25339
A17: 29.01 - Operacional - Salário líquido | B17: -6816 | C17: 0 | D17: 0 | E17: 0 | F17: 0 | G17: 0 | H17: 0 | I17: 0 | J17: 0 | K17: 0 | L17: 0 | M17: 0 | N17: -6816
A18: 29.02 - Operacional - 13o salário | B18: -159 | C18: 0 | D18: 0 | E18: 0 | F18: 0 | G18: 0 | H18: 0 | I18: 0 | J18: 0 | K18: 0 | L18: 0 | M18: 0 | N18: -159
A19: 29.06 - Operacional - INSS | B19: -15675 | C19: 0 | D19: 0 | E19: 0 | F19: 0 | G19: 0 | H19: 0 | I19: 0 | J19: 0 | K19: 0 | L19: 0 | M19: 0 | N19: -15675
A20: 29.17 - Operacional - Refeitório | B20: -782 | C20: 0 | D20: 0 | E20: 0 | F20: 0 | G20: 0 | H20: 0 | I20: 0 | J20: 0 | K20: 0 | L20: 0 | M20: 0 | N20: -782
A21: 29.19 - Operacional - Horas Extras | B21: -1907 | C21: 0 | D21: 0 | E21: 0 | F21: 0 | G21: 0 | H21: 0 | I21: 0 | J21: 0 | K21: 0 | L21: 0 | M21: 0 | N21: -1907
A22: [-] 30 - Insumos de Produção | B22: -237263 | C22: 0 | D22: 0 | E22: 0 | F22: 0 | G22: 0 | H22: 0 | I22: 0 | J22: 0 | K22: 0 | L22: 0 | M22: 0 | N22: -237263
A23: 30.01 - Matérias primas | B23: -138506 | C23: 0 | D23: 0 | E23: 0 | F23: 0 | G23: 0 | H23: 0 | I23: 0 | J23: 0 | K23: 0 | L23: 0 | M23: 0 | N23: -138506
A24: 30.02 - Embalagens | B24: -98757 | C24: 0 | D24: 0 | E24: 0 | F24: 0 | G24: 0 | H24: 0 | I24: 0 | J24: 0 | K24: 0 | L24: 0 | M24: 0 | N24: -98757
A25: [-] 33 - Custos Indiretos de Fabricação | B25: -7232 | C25: 0 | D25: 0 | E25: 0 | F25: 0 | G25: 0 | H25: 0 | I25: 0 | J25: 0 | K25: 0 | L25: 0 | M25: 0 | N25: -7232
A26: 33.01 - Energia | B26: -596 | C26: 0 | D26: 0 | E26: 0 | F26: 0 | G26: 0 | H26: 0 | I26: 0 | J26: 0 | K26: 0 | L26: 0 | M26: 0 | N26: -596
... A33: ( = ) Resultado Bruto | B33: 168846 | C33: 0 | D33: 0 | E33: 0 | F33: 0 | G33: 0 | H33: 0 | I33: 0 | J33: 0 | K33: 0 | L33: 0 | M33: 0 | N33: 168846
A34: Resultado Bruto ( % ) | B34: 0.37 | C34: % | D34: % | E34: % | F34: % | G34: % | H34: % | I34: % | J34: % | K34: % | L34: % | M34: % | N34: 0.37
A35: Despesas Operacionais | Administração | B35: -2619 | C35: 0 | D35: 0 | E35: 0 | F35: 0 | G35: 0 | H35: 0 | I35: 0 | J35: 0 | K35: 0 | L35: 0 | M35: 0 | N35: -2619
A36: [-] 41 - Despesas com Pessoal - Administração | B36: -847 | C36: 0 | D36: 0 | E36: 0 | F36: 0 | G36: 0 | H36: 0 | I36: 0 | J36: 0 | K36: 0 | L36: 0 | M36: 0 | N36: -847
A37: 41.07 - Administrativo - FGTS | B37: -847 | C37: 0 | D37: 0 | E37: 0 | F37: 0 | G37: 0 | H37: 0 | I37: 0 | J37: 0 | K37: 0 | L37: 0 | M37: 0 | N37: -847
A38: [-] 42 - Infra-estrutura Administrativa | B38: -99 | C38: 0 | D38: 0 | E38: 0 | F38: 0 | G38: 0 | H38: 0 | I38: 0 | J38: 0 | K38: 0 | L38: 0 | M38: 0 | N38: -99
A39: 42.03 - Internet | B39: -99 | C39: 0 | D39: 0 | E39: 0 | F39: 0 | G39: 0 | H39: 0 | I39: 0 | J39: 0 | K39: 0 | L39: 0 | M39: 0 | N39: -99
A40: [-] 43 - Serviços de apoio à operação | B40: -1673 | C40: 0 | D40: 0 | E40: 0 | F40: 0 | G40: 0 | H40: 0 | I40: 0 | J40: 0 | K40: 0 | L40: 0 | M40: 0 | N40: -1673
A41: 43.10 - Softwares de gestão | B41: -1566 | C41: 0 | D41: 0 | E41: 0 | F41: 0 | G41: 0 | H41: 0 | I41: 0 | J41: 0 | K41: 0 | L41: 0 | M41: 0 | N41: -1566
A42: 43.12 - Tarifas | B42: -107 | C42: 0 | D42: 0 | E42: 0 | F42: 0 | G42: 0 | H42: 0 | I42: 0 | J42: 0 | K42: 0 | L42: 0 | M42: 0 | N42: -107
A43: 44 - Transporte próprio da Administração | B43: 0 | C43: 0 | D43: 0 | E43: 0 | F43: 0 | G43: 0 | H43: 0 | I43: 0 | J43: 0 | K43: 0 | L43: 0 | M43: 0 | N43: 0
A44: 45 - Despesas administrativas | B44: 0 | C44: 0 | D44: 0 | E44: 0 | F44: 0 | G44: 0 | H44: 0 | I44: 0 | J44: 0 | K44: 0 | L44: 0 | M44: 0 | N44: 0
A45: 46 - Manutenção Administrativa | B45: 0 | C45: 0 | D45: 0 | E45: 0 | F45: 0 | G45: 0 | H45: 0 | I45: 0 | J45: 0 | K45: 0 | L45: 0 | M45: 0 | N45: 0
A46: 47 - Impostos | B46: 0 | C46: 0 | D46: 0 | E46: 0 | F46: 0 | G46: 0 | H46: 0 | I46: 0 | J46: 0 | K46: 0 | L46: 0 | M46: 0 | N46: 0
... A59: ( = ) Resultado Antes do Resultado Financeiro e dos Tributos (EBIT) | B59: 154682 | C59: 0 | D59: 0 | E59: 0 | F59: 0 | G59: 0 | H59: 0 | I59: 0 | J59: 0 | K59: 0 | L59: 0 | M59: 0 | N59: 154682
A60: Resultado Antes do Resultado Financeiro e dos Tributos (EBIT) ( % ) | B60: 0.34 | C60: % | D60: % | E60: % | F60: % | G60: % | H60: % | I60: % | J60: % | K60: % | L60: % | M60: % | N60: 0.34
A61: Resultado Financeiro | B61: 0 | C61: 0 | D61: 0 | E61: 0 | F61: 0 | G61: 0 | H61: 0 | I61: 0 | J61: 0 | K61: 0 | L61: 0 | M61: 0 | N61: 0
A62: 48 - Despesas financeiras | B62: 0 | C62: 0 | D62: 0 | E62: 0 | F62: 0 | G62: 0 | H62: 0 | I62: 0 | J62: 0 | K62: 0 | L62: 0 | M62: 0 | N62: 0
A63: ( = ) Resultado Antes dos Tributos sobre o Lucro (EBT) | B63: 154682 | C63: 0 | D63: 0 | E63: 0 | F63: 0 | G63: 0 | H63: 0 | I63: 0 | J63: 0 | K63: 0 | L63: 0 | M63: 0 | N63: 154682
A64: Resultado Antes dos Tributos sobre o Lucro (EBT) ( % ) | B64: 0.34 | C64: % | D64: % | E64: % | F64: % | G64: % | H64: % | I64: % | J64: % | K64: % | L64: % | M64: % | N64: 0.34
A65: Imposto de Renda e Contribuição Social sobre o Lucro | B65: 0 | C65: 0 | D65: 0 | E65: 0 | F65: 0 | G65: 0 | H65: 0 | I65: 0 | J65: 0 | K65: 0 | L65: 0 | M65: 0 | N65: 0
A66: 49 - Imposto de Renda e Contribuição Social sobre o Lucro | B66: 0 | C66: 0 | D66: 0 | E66: 0 | F66: 0 | G66: 0 | H66: 0 | I66: 0 | J66: 0 | K66: 0 | L66: 0 | M66: 0 | N66: 0
A67: ( = ) Lucro Líquido | B67: 154682 | C67: 0 | D67: 0 | E67: 0 | F67: 0 | G67: 0 | H67: 0 | I67: 0 | J67: 0 | K67: 0 | L67: 0 | M67: 0 | N67: 154682
A68: Lucro Líquido ( % ) | B68: 0.34 | C68: % | D68: % | E68: % | F68: % | G68: % | H68: % | I68: % | J68: % | K68: % | L68: % | M68: % | N68: 0.34
A69: Variações de caixa não operacionais | B69: -6669 | C69: 0 | D69: 0 | E69: 0 | F69: 0 | G69: 0 | H69: 0 | I69: 0 | J69: 0 | K69: 0 | L69: 0 | M69: 0 | N69: -6669
A70: [-] 50 - Atividades de investimento | B70: -5818 | C70: 0 | D70: 0 | E70: 0 | F70: 0 | G70: 0 | H70: 0 | I70: 0 | J70: 0 | K70: 0 | L70: 0 | M70: 0 | N70: -5818
A71: 50.02 - Compra de veículos | B71: -5818 | C71: 0 | D71: 0 | E71: 0 | F71: 0 | G71: 0 | H71: 0 | I71: 0 | J71: 0 | K71: 0 | L71: 0 | M71: 0 | N71: -5818
A72: [-] 51 - Atividades de financiamento | B72: -597 | C72: 0 | D72: 0 | E72: 0 | F72: 0 | G72: 0 | H72: 0 | I72: 0 | J72: 0 | K72: 0 | L72: 0 | M72: 0 | N72: -597
A73: 51.08 - Empréstimo a sócios | B73: -597 | C73: 0 | D73: 0 | E73: 0 | F73: 0 | G73: 0 | H73: 0 | I73: 0 | J73: 0 | K73: 0 | L73: 0 | M73: 0 | N73: -597
A74: 52 - Aplicações financeiras | B74: 0 | C74: 0 | D74: 0 | E74: 0 | F74: 0 | G74: 0 | H74: 0 | I74: 0 | J74: 0 | K74: 0 | L74: 0 | M74: 0 | N74: 0
A75: [-] 53 - Participações e Distribuições | B75: -254 | C75: 0 | D75: 0 | E75: 0 | F75: 0 | G75: 0 | H75: 0 | I75: 0 | J75: 0 | K75: 0 | L75: 0 | M75: 0 | N75: -254
A76: 53.02 - Distribuição de lucros e dividendos para sócios | B76: -254 | C76: 0 | D76: 0 | E76: 0 | F76: 0 | G76: 0 | H76: 0 | I76: 0 | J76: 0 | K76: 0 | L76: 0 | M76: 0 | N76: -254
A77: [-] 54 - Ajustes de saldo | B77: 0 | C77: 0 | D77: 0 | E77: 0 | F77: 0 | G77: 0 | H77: 0 | I77: 0 | J77: 0 | K77: 0 | L77: 0 | M77: 0 | N77: 0
A78: 54.05 - Transferência entre contas | B78: 0 | C78: 0 | D78: 0 | E78: 0 | F78: 0 | G78: 0 | H78: 0 | I78: 0 | J78: 0 | K78: 0 | L78: 0 | M78: 0 | N78: 0
A79: ( = ) Variação de caixa | B79: 148013 | C79: 0 | D79: 0 | E79: 0 | F79: 0 | G79: 0 | H79: 0 | I79: 0 | J79: 0 | K79: 0 | L79: 0 | M79: 0 | N79: 148013
A80: Variação de caixa ( % ) | B80: 0.32 | C80: % | D80: % | E80: % | F80: % | G80: % | H80: % | I80: % | J80: % | K80: % | L80: % | M80: % | N80: 0.32
A81: 43.09 - Segurança do trabalho | B81: 0 | C81: -140 | D81: -140 | E81: -74 | F81: 0 | G81: 0 | H81: 0 | I81: -750 | J81: 0 | K81: 0 | L81: 0 | M81: 0 | N81: -1104
A82: 43.10 - Softwares de gestão | B82: -5163 | C82: -5166 | D82: -846 | E82: -846 | F82: -846 | G82: -846 | H82: -846 | I82: -846 | J82: -846 | K82: -1566 | L82: 0 | M82: 0 | N82: -17817
A83: 43.11 - Medicina do Trabalho | B83: -5574 | C83: -895 | D83: -265 | E83: -1578 | F83: -717 | G83: -250 | H83: -1267 | I83: -1137 | J83: -345 | K83: 0 | L83: 0 | M83: 0 | N83: -12028
A84: 43.12 - Tarifas | B84: -494 | C84: -492 | D84: -636 | E84: -482 | F84: -488 | G84: -603 | H84: -473 | I84: -390 | J84: -347 | K84: -17 | L84: 0 | M84: 0 | N84: -4422
A85: [-] 44 - Transporte próprio da Administração | B85: 0 | C85: 0 | D85: 0 | E85: 0 | F85: -216 | G85: 0 | H85: 0 | I85: 0 | J85: 0 | K85: 0 | L85: 0 | M85: 0 | N85: -216
A86: 44.01 - Administração - Combustível | B86: 0 | C86: 0 | D86: 0 | E86: 0 | F86: -216 | G86: 0 | H86: 0 | I86: 0 | J86: 0 | K86: 0 | L86: 0 | M86: 0 | N86: -216
A87: [-] 45 - Despesas administrativas | B87: -2336 | C87: -3443 | D87: -11199 | E87: -1892 | F87: -2450 | G87: -2763 | H87: -1153 | I87: -2639 | J87: -3673 | K87: 0 | L87: 0 | M87: 0 | N87: -31548
A88: 45.01 - Materiais de escritório | B88: -627 | C88: -65 | D88: -6053 | E88: -18 | F88: -124 | G88: -296 | H88: 0 | I88: -450 | J88: -52 | K88: 0 | L88: 0 | M88: 0 | N88: -7685
A89: 45.03 - Materiais de informática | B89: 0 | C89: 0 | D89: -639 | E89: 0 | F89: 0 | G89: -345 | H89: 0 | I89: 0 | J89: -80 | K89: 0 | L89: 0 | M89: 0 | N89: -1064
A90: 45.06 - Cartório | B90: 0 | C90: 0 | D90: 0 | E90: -18 | F90: -177 | G90: 0 | H90: -13 | I90: 0 | J90: 0 | K90: 0 | L90: 0 | M90: 0 | N90: -208
A91: 45.07 - Taxas | B91: -191 | C91: -909 | D91: -3737 | E91: -126 | F91: -80 | G91: -92 | H91: -85 | I91: -76 | J91: -88 | K91: 0 | L91: 0 | M91: 0 | N91: -5384
A92: 45.08 - Outras despesas administrativas | B92: -432 | C92: -116 | D92: -350 | E92: -133 | F92: -473 | G92: -86 | H92: -58 | I92: -1021 | J92: -1189 | K92: 0 | L92: 0 | M92: 0 | N92: -3858
... A149: ( = ) Resultado Antes do Resultado Financeiro e dos Tributos (EBIT) | B149: 102243 | C149: 36780 | D149: 294560 | E149: 226449 | F149: 282460 | G149: 313076 | H149: 254958 | I149: 366459 | J149: 231437 | K149: 240803 | L149: 0 | M149: 0 | N149: 2349225
A150: Resultado Antes do Resultado Financeiro e dos Tributos (EBIT) ( % ) | B150: 0.08 | C150: 0.03 | D150: 0.23 | E150: 0.19 | F150: 0.21 | G150: 0.23 | H150: 0.19 | I150: 0.24 | J150: 0.18 | K150: 0.88 | L150: % | M150: % | N150: 0.2
A151: Resultado Financeiro | B151: 0 | C151: 0 | D151: 0 | E151: -605 | F151: 0 | G151: 0 | H151: 0 | I151: 0 | J151: 0 | K151: 0 | L151: 0 | M151: 0 | N151: -605
A152: [-] 48 - Despesas financeiras | B152: 0 | C152: 0 | D152: 0 | E152: -605 | F152: 0 | G152: 0 | H152: 0 | I152: 0 | J152: 0 | K152: 0 | L152: 0 | M152: 0 | N152: -605
A153: 48.01 - Juros pagos | B153: 0 | C153: 0 | D153: 0 | E153: -605 | F153: 0 | G153: 0 | H153: 0 | I153: 0 | J153: 0 | K153: 0 | L153: 0 | M153: 0 | N153: -605
A154: ( = ) Resultado Antes dos Tributos sobre o Lucro (EBT) | B154: 102243 | C154: 36780 | D154: 294560 | E154: 225844 | F154: 282460 | G154: 313076 | H154: 254958 | I154: 366459 | J154: 231437 | K154: 240803 | L154: 0 | M154: 0 | N154: 2348620
A155: Resultado Antes dos Tributos sobre o Lucro (EBT) ( % ) | B155: 0.08 | C155: 0.03 | D155: 0.23 | E155: 0.19 | F155: 0.21 | G155: 0.23 | H155: 0.19 | I155: 0.24 | J155: 0.18 | K155: 0.88 | L155: % | M155: % | N155: 0.2
A156: Imposto de Renda e Contribuição Social sobre o Lucro | B156: -91757 | C156: 0 | D156: 0 | E156: -94127 | F156: 0 | G156: 0 | H156: -102366 | I156: 0 | J156: 0 | K156: 0 | L156: 0 | M156: 0 | N156: -288250
A157: [-] 49 - Imposto de Renda e Contribuição Social sobre o Lucro | B157: -91757 | C157: 0 | D157: 0 | E157: -94127 | F157: 0 | G157: 0 | H157: -102366 | I157: 0 | J157: 0 | K157: 0 | L157: 0 | M157: 0 | N157: -288250
A158: 49.01 - IRPJ | B158: -57479 | C158: 0 | D158: 0 | E158: -59018 | F158: 0 | G158: 0 | H158: -64368 | I158: 0 | J158: 0 | K158: 0 | L158: 0 | M158: 0 | N158: -180865
A159: 49.02 - CSLL | B159: -34278 | C159: 0 | D159: 0 | E159: -35109 | F159: 0 | G159: 0 | H159: -37998 | I159: 0 | J159: 0 | K159: 0 | L159: 0 | M159: 0 | N159: -107385
A160: ( = ) Lucro Líquido | B160: 10486 | C160: 36780 | D160: 294560 | E160: 131717 | F160: 282460 | G160: 313076 | H160: 152592 | I160: 366459 | J160: 231437 | K160: 240803 | L160: 0 | M160: 0 | N160: 2060370
A161: Lucro Líquido ( % ) | B161: 0 | C161: 0.03 | D161: 0.23 | E161: 0.11 | F161: 0.21 | G161: 0.23 | H161: 0.11 | I161: 0.24 | J161: 0.18 | K161: 0.88 | L161: % | M161: % | N161: 0.17
A162: Variações de caixa não operacionais | B162: -59882 | C162: -58065 | D162: -125141 | E162: -63351 | F162: -112543 | G162: -96700 | H162: -97947 | I162: -93070 | J162: -90342 | K162: -5818 | L162: 0 | M162: 0 | N162: -802859
A163: [-] 50 - Atividades de investimento | B163: -16118 | C163: -13498 | D163: -32354 | E163: -18791 | F163: -41851 | G163: -51419 | H163: -52357 | I163: -52081 | J163: -33809 | K163: -5818 | L163: 0 | M163: 0 | N163: -318096
A164: 50.01 - Compra de máquinas e equipamentos | B164: -7500 | C164: -7500 | D164: -7500 | E164: -9873 | F164: -11310 | G164: -3035 | H164: -17796 | I164: -4917 | J164: -2139 | K164: 0 | L164: 0 | M164: 0 | N164: -71570
A165: 50.02 - Compra de veículos | B165: -5818 | C165: -5818 | D165: -5818 | E165: -5818 | F165: -5818 | G165: -5818 | H165: -5818 | I165: -5818 | J165: -5818 | K165: -5818 | L165: 0 | M165: 0 | N165: -58180
A166: 50.03 - Compra de mobiliário | B166: 0 | C166: 0 | D166: -689 | E166: 0 | F166: 0 | G166: -2600 | H166: 0 | I166: 0 | J166: 0 | K166: 0 | L166: 0 | M166: 0 | N166: -3289
A167: 50.04 - Investimentos em infra-estrutura | B167: -2800 | C167: -180 | D167: -18347 | E167: -3100 | F167: -24723 | G167: -39966 | H167: -28743 | I167: -41346 | J167: -25852 | K167: 0 | L167: 0 | M167: 0 | N167: -185057
A168: [-] 51 - Atividades de financiamento | B168: -5455 | C168: -6155 | D168: -35081 | E168: -5455 | F168: -18805 | G168: -2389 | H168: -6050 | I168: -9944 | J168: -6954 | K168: 0 | L168: 0 | M168: 0 | N168: -96288
A169: 51.02 - Pagamento de empréstimo | B169: -6155 | C169: -6155 | D169: -6155 | E169: -6155 | F169: -6155 | G169: -3089 | H169: 0 | I169: 0 | J169: 0 | K169: 0 | L169: 0 | M169: 0 | N169: -33864
A170: 51.07 - Recebimento de empréstimos a colaboradores | B170: 700 | C170: 0 | D170: 1400 | E170: 700 | F170: 700 | G170: 700 | H170: 700 | I170: 700 | J170: 0 | K170: 0 | L170: 0 | M170: 0 | N170: 5600
A171: 51.08 - Empréstimo a sócios | B171: 0 | C171: 0 | D171: -30326 | E171: 0 | F171: -13350 | G171: 0 | H171: -6750 | I171: -10644 | J171: -6954 | K171: 0 | L171: 0 | M171: 0 | N171: -68024
A172: [-] 52 - Aplicações financeiras | B172: -6026 | C172: -6026 | D172: -6026 | E172: -6016 | F172: -6316 | G172: -6306 | H172: -6306 | I172: -6306 | J172: -6306 | K172: 0 | L172: 0 | M172: 0 | N172: -55634
A173: 52.01 - Investimento em aplicações financeiras | B173: -6026 | C173: -6026 | D173: -6026 | E173: -6016 | F173: -6316 | G173: -6306 | H173: -6306 | I173: -6306 | J173: -6306 | K173: 0 | L173: 0 | M173: 0 | N173: -55634
... A178: ( = ) Variação de caixa | B178: -49396 | C178: -21285 | D178: 169419 | E178: 68366 | F178: 169917 | G178: 216376 | H178: 54645 | I178: 273389 | J178: 141095 | K178: 234985 | L178: 0 | M178: 0 | N178: 1257511
...

Sheet PL.C
B3: Classf. | C3: Nome da conta | D3: Tipo | E3: Natureza | F3: Grupo de conta | G3: Função no controle de reembolso de despesas | H3: Ativo
B4: 10 | C4: Receita | D4: Sintética | E4: --- | F4: Receita operacional bruta | G4: --- | H4: sim
B5: 10.01 | C5: Receita com produto | D5: Analítica | E5: Entrada | F5: Receita operacional bruta | G5: --- | H5: sim
B6: 10.02 | C6: Receita com serviço | D6: Analítica | E6: Entrada | F6: Receita operacional bruta | G6: --- | H6: sim
B7: 10.03 | C7: Outras Receitas | D7: Analítica | E7: Entrada | F7: Receita operacional bruta | G7: Nenhuma | H7: sim
B8: 10.04 | C8: Estorno de Produto | D8: Analítica | E8: Saída | F8: Receita operacional bruta | G8: Nenhuma | H8: sim
B9: 10.06 | C9: Devolução de produto | D9: Analítica | E9: Saída | F9: Receita operacional bruta | G9: Nenhuma | H9: sim
B10: 10.07 | C10: Adiantamento de despesas de cliente | D10: Analítica | E10: Saída | F10: Receita operacional bruta | G10: Nenhuma | H10: sim
B11: 10.08 | C11: Devolução de Recebimento | D11: Analítica | E11: Saída | F11: Receita operacional bruta | G11: Nenhuma | H11: sim
B12: 20 | C12: Impostos sobre a receita | D12: Sintética | E12: --- | F12: Custos de venda | G12: --- | H12: sim
B13: 20.01 | C13: ICMS | D13: Analítica | E13: Saída | F13: Custos de venda | G13: --- | H13: sim
B14: 20.04 | C14: ICMS - ST | D14: Analítica | E14: Saída | F14: Custos de venda | G14: Nenhuma | H14: sim
B15: 20.05 | C15: DIFAL | D15: Analítica | E15: Saída | F15: Custos de venda | G15: Nenhuma | H15: sim
B16: 21 | C16: Crédito de impostos | D16: Sintética | E16: --- | F16: Custos de venda | G16: --- | H16: sim
B17: 21.01 | C17: ICMS | D17: Analítica | E17: Entrada | F17: Custos de venda | G17: --- | H17: sim
B18: 21.02 | C18: IPI | D18: Analítica | E18: Entrada | F18: Custos de venda | G18: --- | H18: sim
B19: 21.03 | C19: ISS | D19: Analítica | E19: Entrada | F19: Custos de venda | G19: --- | H19: sim
B20: 22 | C20: Repasse aos distribuidores | D20: Sintética | E20: --- | F20: Custos de venda | G20: Nenhuma | H20: sim
B21: 22.01 | C21: Repasse Distribuidores | D21: Analítica | E21: Saída | F21: Custos de venda | G21: Nenhuma | H21: sim
B22: 29 | C22: Despesas com Pessoal - Operacional | D22: Sintética | E22: --- | F22: Custos Operacionais Variáveis | G22: Nenhuma | H22: sim
B23: 29.01 | C23: Operacional - Salário líquido | D23: Analítica | E23: Saída | F23: Custos Operacionais Variáveis | G23: --- | H23: sim
B24: 29.02 | C24: Operacional - 13o salário | D24: Analítica | E24: Saída | F24: Custos Operacionais Variáveis | G24: --- | H24: sim
B25: 29.03 | C25: Operacional - Férias | D25: Analítica | E25: Saída | F25: Custos Operacionais Variáveis | G25: --- | H25: sim
B26: 29.04 | C26: Operacional - Rescisão | D26: Analítica | E26: Saída | F26: Custos Operacionais Variáveis | G26: --- | H26: sim
B27: 29.05 | C27: Operacional - Multa rescisória | D27: Analítica | E27: Saída | F27: Custos Operacionais Variáveis | G27: --- | H27: sim
B28: 29.06 | C28: Operacional - INSS | D28: Analítica | E28: Saída | F28: Custos Operacionais Variáveis | G28: --- | H28: sim
B29: 29.07 | C29: Operacional - FGTS | D29: Analítica | E29: Saída | F29: Custos Operacionais Variáveis | G29: --- | H29: sim
B30: 29.08 | C30: Operacional - IRRF | D30: Analítica | E30: Saída | F30: Custos Operacionais Variáveis | G30: --- | H30: sim
B31: 29.09 | C31: Operacional - Vale refeição | D31: Analítica | E31: Saída | F31: Custos Operacionais Variáveis | G31: --- | H31: sim
B32: 29.10 | C32: Operacional - Vale alimentação | D32: Analítica | E32: Saída | F32: Custos Operacionais Variáveis | G32: --- | H32: sim
B33: 29.11 | C33: Operacional - Vale transporte | D33: Analítica | E33: Saída | F33: Custos Operacionais Variáveis | G33: --- | H33: sim
B34: 29.12 | C34: Operacional - Plano de saúde | D34: Analítica | E34: Saída | F34: Custos Operacionais Variáveis | G34: --- | H34: sim
... B41: 29.19 | C41: Operacional - Horas Extras | D41: Analítica | E41: Saída | F41: Custos Operacionais Variáveis | G41: Nenhuma | H41: sim
B42: 30 | C42: Insumos de Produção | D42: Sintética | E42: --- | F42: Custos Operacionais Variáveis | G42: --- | H42: sim
B43: 30.01 | C43: Matérias primas | D43: Analítica | E43: Saída | F43: Custos Operacionais Variáveis | G43: --- | H43: sim
B44: 30.02 | C44: Embalagens | D44: Analítica | E44: Saída | F44: Custos Operacionais Variáveis | G44: --- | H44: sim
B45: 31 | C45: Materiais de consumo operacionais | D45: Sintética | E45: --- | F45: Custos Operacionais Fixos | G45: Nenhuma | H45: sim
B46: 31.02 | C46: Produtos de higiene | D46: Analítica | E46: Saída | F46: Custos Operacionais Fixos | G46: Nenhuma | H46: sim
B47: 31.04 | C47: Equipamentos de Proteção Individual | D47: Analítica | E47: Saída | F47: Custos Operacionais Fixos | G47: Nenhuma | H47: sim
B48: 31.05 | C48: Uniformes | D48: Analítica | E48: Saída | F48: Custos Operacionais Fixos | G48: Nenhuma | H48: sim
B49: 31.06 | C49: Materiais de Limpeza | D49: Analítica | E49: Saída | F49: Custos Operacionais Fixos | G49: Nenhuma | H49: sim
B50: 32 | C50: Serviços de industrialização | D50: Sintética | E50: --- | F50: Custos Operacionais Fixos | G50: Nenhuma | H50: sim
B51: 32.01 | C51: Locação de Máquinas e Equipamentos | D51: Analítica | E51: Saída | F51: Custos Operacionais Fixos | G51: Nenhuma | H51: sim
B52: 33 | C52: Custos Indiretos de Fabricação | D52: Sintética | E52: --- | F52: Custos Operacionais Variáveis | G52: --- | H52: sim
B53: 33.01 | C53: Energia | D53: Analítica | E53: Saída | F53: Custos Operacionais Variáveis | G53: --- | H53: sim
B54: 33.02 | C54: Gás | D54: Analítica | E54: Saída | F54: Custos Operacionais Variáveis | G54: --- | H54: sim
B55: 33.03 | C55: Agua | D55: Analítica | E55: Saída | F55: Custos Operacionais Variáveis | G55: --- | H55: sim
B56: 33.04 | C56: Consumíveis de Produção | D56: Analítica | E56: Saída | F56: Custos Operacionais Variáveis | G56: Nenhuma | H56: sim
B57: 33.05 | C57: Outros custos fabris | D57: Analítica | E57: Saída | F57: Custos Operacionais Variáveis | G57: Nenhuma | H57: sim
B58: 34 | C58: Manutenção | D58: Sintética | E58: --- | F58: Custos Operacionais Fixos | G58: Nenhuma | H58: sim
B59: 34.01 | C59: Manutenção de ar condicionado | D59: Analítica | E59: Saída | F59: Custos Operacionais Fixos | G59: Nenhuma | H59: sim
B60: 34.04 | C60: Manutenção de infra-estrutura | D60: Analítica | E60: Saída | F60: Custos Operacionais Fixos | G60: Nenhuma | H60: sim
B61: 34.05 | C61: Manutenção de máquinas | D61: Analítica | E61: Saída | F61: Custos Operacionais Fixos | G61: Nenhuma | H61: sim
B62: 34.06 | C62: Manutenção de ferramentas | D62: Analítica | E62: Saída | F62: Custos Operacionais Fixos | G62: Nenhuma | H62: sim
B63: 34.07 | C63: Calibração de instrumentos | D63: Analítica | E63: Saída | F63: Custos Operacionais Fixos | G63: Nenhuma | H63: sim
B64: 35.02 | C64: Comercial - Comissão de vendedores direto | D64: Analítica | E64: Saída | F64: Despesas Operacionais | Vendas e Comercialização | G64: Nenhuma | H64: sim
B65: 36 | C65: Despesas com Pessoal - Comercial | D65: Sintética | E65: --- | F65: Despesas Operacionais | Vendas e Comercialização | G65: Nenhuma | H65: sim
B66: 36.01 | C66: Comercial - Salário líquido | D66: Analítica | E66: Saída | F66: Despesas Operacionais | Vendas e Comercialização | G66: Nenhuma | H66: sim
B67: 36.02 | C67: Comercial - 13o salário | D67: Analítica | E67: Saída | F67: Despesas Operacionais | Vendas e Comercialização | G67: Nenhuma | H67: sim
B68: 36.03 | C68: Comercial - Férias | D68: Analítica | E68: Saída | F68: Despesas Operacionais | Vendas e Comercialização | G68: Nenhuma | H68: sim
B69: 36.04 | C69: Comercial - Rescisão | D69: Analítica | E69: Saída | F69: Despesas Operacionais | Vendas e Comercialização | G69: Nenhuma | H69: sim
B70: 36.05 | C70: Comercial - Multa rescisória | D70: Analítica | E70: Saída | F70: Despesas Operacionais | Vendas e Comercialização | G70: Nenhuma | H70: sim
B71: 36.06 | C71: Comercial - INSS | D71: Analítica | E71: Saída | F71: Despesas Operacionais | Vendas e Comercialização | G71: Nenhuma | H71: sim
B72: 36.07 | C72: Comercial - FGTS | D72: Analítica | E72: Saída | F72: Despesas Operacionais | Vendas e Comercialização | G72: Nenhuma | H72: sim
B73: 36.08 | C73: Comercial - IRRF | D73: Analítica | E73: Saída | F73: Despesas Operacionais | Vendas e Comercialização | G73: Nenhuma | H73: sim
B74: 36.09 | C74: Comercial - Vale refeição | D74: Analítica | E74: Saída | F74: Despesas Operacionais | Vendas e Comercialização | G74: Nenhuma | H74: sim
B75: 36.10 | C75: Comercial - Vale alimentação | D75: Analítica | E75: Saída | F75: Despesas Operacionais | Vendas e Comercialização | G75: Nenhuma | H75: sim
B76: 36.11 | C76: Comercial - Vale transporte | D76: Analítica | E76: Saída | F76: Despesas Operacionais | Vendas e Comercialização | G76: Nenhuma | H76: sim
B77: 36.12 | C77: Comercial - Plano de saúde | D77: Analítica | E77: Saída | F77: Despesas Operacionais | Vendas e Comercialização | G77: Nenhuma | H77: sim
... B82: 36.17 | C82: Comercial - Adiantamento de Salário | D82: Analítica | E82: Saída | F82: Despesas Operacionais | Vendas e Comercialização | G82: Nenhuma | H82: sim
B83: 37 | C83: Despesas com Transporte - Comercial | D83: Sintética | E83: --- | F83: Despesas Operacionais | Vendas e Comercialização | G83: Nenhuma | H83: sim
B84: 37.01 | C84: Comercial - Combustível | D84: Analítica | E84: Saída | F84: Despesas Operacionais | Vendas e Comercialização | G84: Nenhuma | H84: sim
B85: 37.02 | C85: Comercial -Manutenção | D85: Analítica | E85: Saída | F85: Despesas Operacionais | Vendas e Comercialização | G85: Nenhuma | H85: sim
B86: 37.03 | C86: Comercial -IPVA | D86: Analítica | E86: Saída | F86: Despesas Operacionais | Vendas e Comercialização | G86: Nenhuma | H86: sim
B87: 37.04 | C87: Comercial -Seguro | D87: Analítica | E87: Saída | F87: Despesas Operacionais | Vendas e Comercialização | G87: Nenhuma | H87: sim
B88: 37.05 | C88: Comercial -Estacionamento | D88: Analítica | E88: Saída | F88: Despesas Operacionais | Vendas e Comercialização | G88: Nenhuma | H88: sim
B89: 37.06 | C89: Comercial -Multas | D89: Analítica | E89: Saída | F89: Despesas Operacionais | Vendas e Comercialização | G89: Nenhuma | H89: sim
B90: 37.07 | C90: Comercial -Pedágio | D90: Analítica | E90: Saída | F90: Despesas Operacionais | Vendas e Comercialização | G90: Nenhuma | H90: sim
B91: 38 | C91: Marketing e vendas | D91: Sintética | E91: --- | F91: Despesas Operacionais | Vendas e Comercialização | G91: Nenhuma | H91: sim
B92: 38.01 | C92: Desenvolvimento e manutenção do site | D92: Analítica | E92: Saída | F92: Despesas Operacionais | Vendas e Comercialização | G92: Nenhuma | H92: sim
B93: 38.02 | C93: Mídias Sociais | D93: Analítica | E93: Saída | F93: Despesas Operacionais | Vendas e Comercialização | G93: Nenhuma | H93: sim
B94: 38.03 | C94: Viagens de negócio | D94: Analítica | E94: Saída | F94: Despesas Operacionais | Vendas e Comercialização | G94: Nenhuma | H94: sim
B95: 38.04 | C95: Brindes corporativos | D95: Analítica | E95: Saída | F95: Despesas Operacionais | Vendas e Comercialização | G95: Nenhuma | H95: sim
B96: 38.05 | C96: Participação em eventos | D96: Analítica | E96: Saída | F96: Despesas Operacionais | Vendas e Comercialização | G96: Nenhuma | H96: sim
B97: 38.06 | C97: Gráfica | D97: Analítica | E97: Saída | F97: Despesas Operacionais | Vendas e Comercialização | G97: Nenhuma | H97: sim
B98: 38.07 | C98: Agência de Publicidade e Propaganda | D98: Analítica | E98: Saída | F98: Despesas Operacionais | Vendas e Comercialização | G98: Nenhuma | H98: sim
B99: 38.08 | C99: Bonificação / Ajuda de Custo | D99: Analítica | E99: Saída | F99: Despesas Operacionais | Vendas e Comercialização | G99: Nenhuma | H99: sim
B100: 38.09 | C100: Promotor de Vendas | D100: Analítica | E100: Saída | F100: Despesas Operacionais | Vendas e Comercialização | G100: Nenhuma | H100: sim
B101: 39 | C101: Despesas com Pessoal - Logística | D101: Sintética | E101: --- | F101: Despesas Operacionais | Logística de Vendas | G101: Nenhuma | H101: sim
B102: 39.01 | C102: Logística - Salário líquido | D102: Analítica | E102: Saída | F102: Despesas Operacionais | Logística de Vendas | G102: Nenhuma | H102: sim
B103: 39.02 | C103: Logística - 13o salário | D103: Analítica | E103: Saída | F103: Despesas Operacionais | Logística de Vendas | G103: Nenhuma | H103: sim
B104: 39.03 | C104: Logística - Férias | D104: Analítica | E104: Saída | F104: Despesas Operacionais | Logística de Vendas | G104: Nenhuma | H104: sim
B105: 39.04 | C105: Logística - Rescisão | D105: Analítica | E105: Saída | F105: Despesas Operacionais | Logística de Vendas | G105: Nenhuma | H105: sim
B106: 39.05 | C106: Logística - Multa rescisória | D106: Analítica | E106: Saída | F106: Despesas Operacionais | Logística de Vendas | G106: Nenhuma | H106: sim
B107: 39.06 | C107: Logística - INSS | D107: Analítica | E107: Saída | F107: Despesas Operacionais | Logística de Vendas | G107: Nenhuma | H107: sim
B108: 39.07 | C108: Logística - FGTS | D108: Analítica | E108: Saída | F108: Despesas Operacionais | Logística de Vendas | G108: Nenhuma | H108: sim
B109: 39.08 | C109: Logística - IRRF | D109: Analítica | E109: Saída | F109: Despesas Operacionais | Logística de Vendas | G109: Nenhuma | H109: sim
B110: 39.09 | C110: Logística - Vale refeição | D110: Analítica | E110: Saída | F110: Despesas Operacionais | Logística de Vendas | G110: Nenhuma | H110: sim
B111: 39.10 | C111: Logística - Vale alimentação | D111: Analítica | E111: Saída | F111: Despesas Operacionais | Logística de Vendas | G111: Nenhuma | H111: sim
B112: 39.11 | C112: Logística - Vale transporte | D112: Analítica | E112: Saída | F112: Despesas Operacionais | Logística de Vendas | G112: Nenhuma | H112: sim
...

Sheet I
A1: colar na célula A2 | B1: 45658 | C1: 45689 | D1: 45717 | E1: 45748 | F1: 45778 | G1: 45809 | H1: 45839 | I1: 45870 | J1: 45901 | K1: 45931 | L1: 45962 | M1: 45992 | N1: Total
A2: Receita operacional bruta | B2: 1385199 | C2: 1267113 | D2: 1314151 | E2: 1590579 | F2: 1497226 | G2: 1483637 | H2: 1883540 | I2: 1534163 | J2: 1652451 | K2: 1528370 | L2: 1348686 | M2: 1782991 | N2: 18268112
A3: [-] 10 - Receita | B3: 1385199 | C3: 1267113 | D3: 1314151 | E3: 1590579 | F3: 1497226 | G3: 1483637 | H3: 1883540 | I3: 1534163 | J3: 1652451 | K3: 1528370 | L3: 1348686 | M3: 1782991 | N3: 18268112
A4: 10.01 - Receita com produto | B4: 1379860 | C4: 1267464 | D4: 1314099 | E4: 1583657 | F4: 1498153 | G4: 1477480 | H4: 1883211 | I4: 1532324 | J4: 1649142 | K4: 1528791 | L4: 1348698 | M4: 1781131 | N4: 18244016
A5: 10.02 - Receita com serviço | B5: 0 | C5: 0 | D5: 0 | E5: 0 | F5: 0 | G5: 0 | H5: 0 | I5: 0 | J5: 85 | K5: 0 | L5: 0 | M5: 0 | N5: 85
A6: 10.03 - Outras Receitas | B6: 6982 | C6: 4142 | D6: 362 | E6: 7275 | F6: 0 | G6: 6264 | H6: 2807 | I6: 2053 | J6: 3353 | K6: 0 | L6: 0 | M6: 3540 | N6: 36782
A7: 10.06 - Devolução de produto | B7: -1643 | C7: -4493 | D7: -310 | E7: -353 | F7: -927 | G7: -107 | H7: -133 | I7: -168 | J7: -130 | K7: -114 | L7: -12 | M7: -1680 | N7: -10075
A8: 10.08 - Devolução de Recebimento | B8: 0 | C8: 0 | D8: 0 | E8: 0 | F8: 0 | G8: 0 | H8: -2343 | I8: -45 | J8: 0 | K8: -306 | L8: 0 | M8: 0 | N8: -2695
A9: Custos de venda | B9: -76353 | C9: -61825 | D9: -84284 | E9: -86087 | F9: -94571 | G9: -80879 | H9: -102307 | I9: -101456 | J9: -91951 | K9: -81174 | L9: -103162 | M9: -105589 | N9: -1069643
A10: [-] 20 - Impostos sobre a receita | B10: -76593 | C10: -58280 | D10: -82822 | E10: -84256 | F10: -92783 | G10: -80722 | H10: -100812 | I10: -100525 | J10: -89559 | K10: -81174 | L10: -101070 | M10: -105589 | N10: -1054190
A11: 20.01 - ICMS | B11: -20159 | C11: -25180 | D11: -29078 | E11: -23991 | F11: -29468 | G11: -14431 | H11: -31227 | I11: -35068 | J11: -27813 | K11: -22114 | L11: -38319 | M11: -36335 | N11: -333189
A12: 20.04 - ICMS - ST | B12: -56433 | C12: -33100 | D12: -53743 | E12: -60264 | F12: -63315 | G12: -66290 | H12: -69584 | I12: -65456 | J12: -61745 | K12: -59060 | L12: -62750 | M12: -69254 | N12: -721001
A13: 21 - Crédito de impostos | B13: 0 | C13: 0 | D13: 0 | E13: 0 | F13: 0 | G13: 0 | H13: 0 | I13: 0 | J13: 0 | K13: 0 | L13: 0 | M13: 0 | N13: 0
... A180: Variação de caixa ( % ) | B180: -0.04 | C180: -0.12 | D180: 0.09 | E180: 0.13 | F180: 0.15 | G180: 0.03 | H180: 0.15 | I180: 0.31 | J180: 0.09 | K180: 0.04 | L180: 0.1 | M180: 0.13 | N180: 0.09

Sheet D
B2: 44562 | C2: 44593 | D2: 44621 | E2: 44652 | F2: 44682 | G2: 44713 | H2: 44743 | I2: 44774 | J2: 44805 | K2: 44835 | L2: 44866 | M2: 44896 | P2: 45658 | Q2: 45689 | R2: 45717 | S2: 45748 | T2: 45778 | U2: 45809 | V2: 45839 | W2: 45870 | X2: 45901 | Y2: 45931 | Z2: 45962 | AA2: 45992
A3: =IFERROR((IF(((IFERROR((FIND(".",I!A1)),0))>1),(MID(I!A1,((FIND(".",I!A1))-2),5)),(MID(I!A1,((FIND(" - ",I!A1))-2),2)))),"-") | B3: =IFERROR(IF($A3="-","null",I!B1),"null") | C3: =IFERROR(IF($A3="-","null",I!C1),"null") | D3: =IFERROR(IF($A3="-","null",I!D1),"null") | E3: =IFERROR(IF($A3="-","null",I!E1),"null") | F3: =IFERROR(IF($A3="-","null",I!F1),"null") | G3: =IFERROR(IF($A3="-","null",I!G1),"null") | H3: =IFERROR(IF($A3="-","null",I!H1),"null") | I3: =IFERROR(IF($A3="-","null",I!I1),"null") | ... M3: =IFERROR(IF($A3="-","null",I!M1),"null") | O3: 10.01 | P3: =SUMIFS(B:B,$A:$A,$O3) | Q3: =SUMIFS(C:C,$A:$A,$O3) | R3: =SUMIFS(D:D,$A:$A,$O3) | S3: =SUMIFS(E:E,$A:$A,$O3) | T3: =SUMIFS(F:F,$A:$A,$O3) | U3: =SUMIFS(G:G,$A:$A,$O3) | V3: =SUMIFS(H:H,$A:$A,$O3) | W3: =SUMIFS(I:I,$A:$A,$O3) | X3: =SUMIFS(J:J,$A:$A,$O3) | Y3: =SUMIFS(K:K,$A:$A,$O3) | Z3: =SUMIFS(L:L,$A:$A,$O3) | AA3: =SUMIFS(M:M,$A:$A,$O3)
A4: =IFERROR((IF(((IFERROR((FIND(".",I!A2)),0))>1),(MID(I!A2,((FIND(".",I!A2))-2),5)),(MID(I!A2,((FIND(" - ",I!A2))-2),2)))),"-") | B4: =IFERROR(IF($A4="-","null",I!B2),"null") | C4: =IFERROR(IF($A4="-","null",I!C2),"null") | D4: =IFERROR(IF($A4="-","null",I!D2),"null") | E4: =IFERROR(IF($A4="-","null",I!E2),"null") | F4: =IFERROR(IF($A4="-","null",I!F2),"null") | G4: =IFERROR(IF($A4="-","null",I!G2),"null") | H4: =IFERROR(IF($A4="-","null",I!H2),"null") | I4: =IFERROR(IF($A4="-","null",I!I2),"null") | ... M4: =IFERROR(IF($A4="-","null",I!M2),"null") | O4: 10.02 | P4: =SUMIFS(B:B,$A:$A,$O4) | Q4: =SUMIFS(C:C,$A:$A,$O4) | R4: =SUMIFS(D:D,$A:$A,$O4) | S4: =SUMIFS(E:E,$A:$A,$O4) | T4: =SUMIFS(F:F,$A:$A,$O4) | U4: =SUMIFS(G:G,$A:$A,$O4) | V4: =SUMIFS(H:H,$A:$A,$O4) | W4: =SUMIFS(I:I,$A:$A,$O4) | X4: =SUMIFS(J:J,$A:$A,$O4) | Y4: =SUMIFS(K:K,$A:$A,$O4) | Z4: =SUMIFS(L:L,$A:$A,$O4) | AA4: =SUMIFS(M:M,$A:$A,$O4)
A5: =IFERROR((IF(((IFERROR((FIND(".",I!A3)),0))>1),(MID(I!A3,((FIND(".",I!A3))-2),5)),(MID(I!A3,((FIND(" - ",I!A3))-2),2)))),"-") | B5: =IFERROR(IF($A5="-","null",I!B3),"null") | C5: =IFERROR(IF($A5="-","null",I!C3),"null") | D5: =IFERROR(IF($A5="-","null",I!D3),"null") | E5: =IFERROR(IF($A5="-","null",I!E3),"null") | F5: =IFERROR(IF($A5="-","null",I!F3),"null") | G5: =IFERROR(IF($A5="-","null",I!G3),"null") | H5: =IFERROR(IF($A5="-","null",I!H3),"null") | I5: =IFERROR(IF($A5="-","null",I!I3),"null") | ... M5: =IFERROR(IF($A5="-","null",I!M3),"null") | O5: 10.03 | P5: =SUMIFS(B:B,$A:$A,$O5) | Q5: =SUMIFS(C:C,$A:$A,$O5) | R5: =SUMIFS(D:D,$A:$A,$O5) | S5: =SUMIFS(E:E,$A:$A,$O5) | T5: =SUMIFS(F:F,$A:$A,$O5) | U5: =SUMIFS(G:G,$A:$A,$O5) | V5: =SUMIFS(H:H,$A:$A,$O5) | W5: =SUMIFS(I:I,$A:$A,$O5) | X5: =SUMIFS(J:J,$A:$A,$O5) | Y5: =SUMIFS(K:K,$A:$A,$O5) | Z5: =SUMIFS(L:L,$A:$A,$O5) | AA5: =SUMIFS(M:M,$A:$A,$O5)
A6: =IFERROR((IF(((IFERROR((FIND(".",I!A4)),0))>1),(MID(I!A4,((FIND(".",I!A4))-2),5)),(MID(I!A4,((FIND(" - ",I!A4))-2),2)))),"-") | B6: =IFERROR(IF($A6="-","null",I!B4),"null") | C6: =IFERROR(IF($A6="-","null",I!C4),"null") | D6: =IFERROR(IF($A6="-","null",I!D4),"null") | E6: =IFERROR(IF($A6="-","null",I!E4),"null") | F6: =IFERROR(IF($A6="-","null",I!F4),"null") | G6: =IFERROR(IF($A6="-","null",I!G4),"null") | H6: =IFERROR(IF($A6="-","null",I!H4),"null") | I6: =IFERROR(IF($A6="-","null",I!I4),"null") | ... M6: =IFERROR(IF($A6="-","null",I!M4),"null") | O6: 10.04 | P6: =SUMIFS(B:B,$A:$A,$O6) | Q6: =SUMIFS(C:C,$A:$A,$O6) | R6: =SUMIFS(D:D,$A:$A,$O6) | S6: =SUMIFS(E:E,$A:$A,$O6) | T6: =SUMIFS(F:F,$A:$A,$O6) | U6: =SUMIFS(G:G,$A:$A,$O6) | V6: =SUMIFS(H:H,$A:$A,$O6) | W6: =SUMIFS(I:I,$A:$A,$O6) | X6: =SUMIFS(J:J,$A:$A,$O6) | Y6: =SUMIFS(K:K,$A:$A,$O6) | Z6: =SUMIFS(L:L,$A:$A,$O6) | AA6: =SUMIFS(M:M,$A:$A,$O6)
A7: =IFERROR((IF(((IFERROR((FIND(".",I!A5)),0))>1),(MID(I!A5,((FIND(".",I!A5))-2),5)),(MID(I!A5,((FIND(" - ",I!A5))-2),2)))),"-") | B7: =IFERROR(IF($A7="-","null",I!B5),"null") | C7: =IFERROR(IF($A7="-","null",I!C5),"null") | D7: =IFERROR(IF($A7="-","null",I!D5),"null") | E7: =IFERROR(IF($A7="-","null",I!E5),"null") | F7: =IFERROR(IF($A7="-","null",I!F5),"null") | G7: =IFERROR(IF($A7="-","null",I!G5),"null") | H7: =IFERROR(IF($A7="-","null",I!H5),"null") | I7: =IFERROR(IF($A7="-","null",I!I5),"null") | ... M7: =IFERROR(IF($A7="-","null",I!M5),"null") | O7: 10.06 | P7: =SUMIFS(B:B,$A:$A,$O7) | Q7: =SUMIFS(C:C,$A:$A,$O7) | R7: =SUMIFS(D:D,$A:$A,$O7) | S7: =SUMIFS(E:E,$A:$A,$O7) | T7: =SUMIFS(F:F,$A:$A,$O7) | U7: =SUMIFS(G:G,$A:$A,$O7) | V7: =SUMIFS(H:H,$A:$A,$O7) | W7: =SUMIFS(I:I,$A:$A,$O7) | X7: =SUMIFS(J:J,$A:$A,$O7) | Y7: =SUMIFS(K:K,$A:$A,$O7) | Z7: =SUMIFS(L:L,$A:$A,$O7) | AA7: =SUMIFS(M:M,$A:$A,$O7)
A8: =IFERROR((IF(((IFERROR((FIND(".",I!A6)),0))>1),(MID(I!A6,((FIND(".",I!A6))-2),5)),(MID(I!A6,((FIND(" - ",I!A6))-2),2)))),"-") | B8: =IFERROR(IF($A8="-","null",I!B6),"null") | C8: =IFERROR(IF($A8="-","null",I!C6),"null") | D8: =IFERROR(IF($A8="-","null",I!D6),"null") | E8: =IFERROR(IF($A8="-","null",I!E6),"null") | F8: =IFERROR(IF($A8="-","null",I!F6),"null") | G8: =IFERROR(IF($A8="-","null",I!G6),"null") | H8: =IFERROR(IF($A8="-","null",I!H6),"null") | I8: =IFERROR(IF($A8="-","null",I!I6),"null") | ... M8: =IFERROR(IF($A8="-","null",I!M6),"null") | O8: 10.07 | P8: =SUMIFS(B:B,$A:$A,$O8) | Q8: =SUMIFS(C:C,$A:$A,$O8) | R8: =SUMIFS(D:D,$A:$A,$O8) | S8: =SUMIFS(E:E,$A:$A,$O8) | T8: =SUMIFS(F:F,$A:$A,$O8) | U8: =SUMIFS(G:G,$A:$A,$O8) | V8: =SUMIFS(H:H,$A:$A,$O8) | W8: =SUMIFS(I:I,$A:$A,$O8) | X8: =SUMIFS(J:J,$A:$A,$O8) | Y8: =SUMIFS(K:K,$A:$A,$O8) | Z8: =SUMIFS(L:L,$A:$A,$O8) | AA8: =SUMIFS(M:M,$A:$A,$O8)
A9: =IFERROR((IF(((IFERROR((FIND(".",I!A7)),0))>1),(MID(I!A7,((FIND(".",I!A7))-2),5)),(MID(I!A7,((FIND(" - ",I!A7))-2),2)))),"-") | B9: =IFERROR(IF($A9="-","null",I!B7),"null") | C9: =IFERROR(IF($A9="-","null",I!C7),"null") | D9: =IFERROR(IF($A9="-","null",I!D7),"null") | E9: =IFERROR(IF($A9="-","null",I!E7),"null") | F9: =IFERROR(IF($A9="-","null",I!F7),"null") | G9: =IFERROR(IF($A9="-","null",I!G7),"null") | H9: =IFERROR(IF($A9="-","null",I!H7),"null") | I9: =IFERROR(IF($A9="-","null",I!I7),"null") | ... M9: =IFERROR(IF($A9="-","null",I!M7),"null") | O9: 10.08 | P9: =SUMIFS(B:B,$A:$A,$O9) | Q9: =SUMIFS(C:C,$A:$A,$O9) | R9: =SUMIFS(D:D,$A:$A,$O9) | S9: =SUMIFS(E:E,$A:$A,$O9) | T9: =SUMIFS(F:F,$A:$A,$O9) | U9: =SUMIFS(G:G,$A:$A,$O9) | V9: =SUMIFS(H:H,$A:$A,$O9) | W9: =SUMIFS(I:I,$A:$A,$O9) | X9: =SUMIFS(J:J,$A:$A,$O9) | Y9: =SUMIFS(K:K,$A:$A,$O9) | Z9: =SUMIFS(L:L,$A:$A,$O9) | AA9: =SUMIFS(M:M,$A:$A,$O9)
A10: =IFERROR((IF(((IFERROR((FIND(".",I!A8)),0))>1),(MID(I!A8,((FIND(".",I!A8))-2),5)),(MID(I!A8,((FIND(" - ",I!A8))-2),2)))),"-") | B10: =IFERROR(IF($A10="-","null",I!B8),"null") | C10: =IFERROR(IF($A10="-","null",I!C8),"null") | D10: =IFERROR(IF($A10="-","null",I!D8),"null") | E10: =IFERROR(IF($A10="-","null",I!E8),"null") | F10: =IFERROR(IF($A10="-","null",I!F8),"null") | G10: =IFERROR(IF($A10="-","null",I!G8),"null") | H10: =IFERROR(IF($A10="-","null",I!H8),"null") | I10: =IFERROR(IF($A10="-","null",I!I8),"null") | ... M10: =IFERROR(IF($A10="-","null",I!M8),"null") | O10: 20.01 | P10: =SUMIFS(B:B,$A:$A,$O10) | Q10: =SUMIFS(C:C,$A:$A,$O10) | R10: =SUMIFS(D:D,$A:$A,$O10) | S10: =SUMIFS(E:E,$A:$A,$O10) | T10: =SUMIFS(F:F,$A:$A,$O10) | U10: =SUMIFS(G:G,$A:$A,$O10) | V10: =SUMIFS(H:H,$A:$A,$O10) | W10: =SUMIFS(I:I,$A:$A,$O10) | X10: =SUMIFS(J:J,$A:$A,$O10) | Y10: =SUMIFS(K:K,$A:$A,$O10) | Z10: =SUMIFS(L:L,$A:$A,$O10) | AA10: =SUMIFS(M:M,$A:$A,$O10)
A11: =IFERROR((IF(((IFERROR((FIND(".",I!A9)),0))>1),(MID(I!A9,((FIND(".",I!A9))-2),5)),(MID(I!A9,((FIND(" - ",I!A9))-2),2)))),"-") | B11: =IFERROR(IF($A11="-","null",I!B9),"null") | C11: =IFERROR(IF($A11="-","null",I!C9),"null") | D11: =IFERROR(IF($A11="-","null",I!D9),"null") | E11: =IFERROR(IF($A11="-","null",I!E9),"null") | F11: =IFERROR(IF($A11="-","null",I!F9),"null") | G11: =IFERROR(IF($A11="-","null",I!G9),"null") | H11: =IFERROR(IF($A11="-","null",I!H9),"null") | I11: =IFERROR(IF($A11="-","null",I!I9),"null") | ... M11: =IFERROR(IF($A11="-","null",I!M9),"null") | O11: 20.04 | P11: =SUMIFS(B:B,$A:$A,$O11) | Q11: =SUMIFS(C:C,$A:$A,$O11) | R11: =SUMIFS(D:D,$A:$A,$O11) | S11: =SUMIFS(E:E,$A:$A,$O11) | T11: =SUMIFS(F:F,$A:$A,$O11) | U11: =SUMIFS(G:G,$A:$A,$O11) | V11: =SUMIFS(H:H,$A:$A,$O11) | W11: =SUMIFS(I:I,$A:$A,$O11) | X11: =SUMIFS(J:J,$A:$A,$O11) | Y11: =SUMIFS(K:K,$A:$A,$O11) | Z11: =SUMIFS(L:L,$A:$A,$O11) | AA11: =SUMIFS(M:M,$A:$A,$O11)
A12: =IFERROR((IF(((IFERROR((FIND(".",I!A10)),0))>1),(MID(I!A10,((FIND(".",I!A10))-2),5)),(MID(I!A10,((FIND(" - ",I!A10))-2),2)))),"-") | B12: =IFERROR(IF($A12="-","null",I!B10),"null") | C12: =IFERROR(IF($A12="-","null",I!C10),"null") | D12: =IFERROR(IF($A12="-","null",I!D10),"null") | E12: =IFERROR(IF($A12="-","null",I!E10),"null") | F12: =IFERROR(IF($A12="-","null",I!F10),"null") | G12: =IFERROR(IF($A12="-","null",I!G10),"null") | H12: =IFERROR(IF($A12="-","null",I!H10),"null") | I12: =IFERROR(IF($A12="-","null",I!I10),"null") | ... M12: =IFERROR(IF($A12="-","null",I!M10),"null") | O12: 20.05 | P12: =SUMIFS(B:B,$A:$A,$O12) | Q12: =SUMIFS(C:C,$A:$A,$O12) | R12: =SUMIFS(D:D,$A:$A,$O12) | S12: =SUMIFS(E:E,$A:$A,$O12) | T12: =SUMIFS(F:F,$A:$A,$O12) | U12: =SUMIFS(G:G,$A:$A,$O12) | V12: =SUMIFS(H:H,$A:$A,$O12) | W12: =SUMIFS(I:I,$A:$A,$O12) | X12: =SUMIFS(J:J,$A:$A,$O12) | Y12: =SUMIFS(K:K,$A:$A,$O12) | Z12: =SUMIFS(L:L,$A:$A,$O12) | AA12: =SUMIFS(M:M,$A:$A,$O12)
A13: =IFERROR((IF(((IFERROR((FIND(".",I!A11)),0))>1),(MID(I!A11,((FIND(".",I!A11))-2),5)),(MID(I!A11,((FIND(" - ",I!A11))-2),2)))),"-") | B13: =IFERROR(IF($A13="-","null",I!B11),"null") | C13: =IFERROR(IF($A13="-","null",I!C11),"null") | D13: =IFERROR(IF($A13="-","null",I!D11),"null") | E13: =IFERROR(IF($A13="-","null",I!E11),"null") | F13: =IFERROR(IF($A13="-","null",I!F11),"null") | G13: =IFERROR(IF($A13="-","null",I!G11),"null") | H13: =IFERROR(IF($A13="-","null",I!H11),"null") | I13: =IFERROR(IF($A13="-","null",I!I11),"null") | ... M13: =IFERROR(IF($A13="-","null",I!M11),"null") | O13: 21.01 | P13: =SUMIFS(B:B,$A:$A,$O13) | Q13: =SUMIFS(C:C,$A:$A,$O13) | R13: =SUMIFS(D:D,$A:$A,$O13) | S13: =SUMIFS(E:E,$A:$A,$O13) | T13: =SUMIFS(F:F,$A:$A,$O13) | U13: =SUMIFS(G:G,$A:$A,$O13) | V13: =SUMIFS(H:H,$A:$A,$O13) | W13: =SUMIFS(I:I,$A:$A,$O13) | X13: =SUMIFS(J:J,$A:$A,$O13) | Y13: =SUMIFS(K:K,$A:$A,$O13) | Z13: =SUMIFS(L:L,$A:$A,$O13) | AA13: =SUMIFS(M:M,$A:$A,$O13)
A14: =IFERROR((IF(((IFERROR((FIND(".",I!A12)),0))>1),(MID(I!A12,((FIND(".",I!A12))-2),5)),(MID(I!A12,((FIND(" - ",I!A12))-2),2)))),"-") | B14: =IFERROR(IF($A14="-","null",I!B12),"null") | C14: =IFERROR(IF($A14="-","null",I!C12),"null") | D14: =IFERROR(IF($A14="-","null",I!D12),"null") | E14: =IFERROR(IF($A14="-","null",I!E12),"null") | F14: =IFERROR(IF($A14="-","null",I!F12),"null") | G14: =IFERROR(IF($A14="-","null",I!G12),"null") | H14: =IFERROR(IF($A14="-","null",I!H12),"null") | I14: =IFERROR(IF($A14="-","null",I!I12),"null") | ... M14: =IFERROR(IF($A14="-","null",I!M12),"null") | O14: 21.02 | P14: =SUMIFS(B:B,$A:$A,$O14) | Q14: =SUMIFS(C:C,$A:$A,$O14) | R14: =SUMIFS(D:D,$A:$A,$O14) | S14: =SUMIFS(E:E,$A:$A,$O14) | T14: =SUMIFS(F:F,$A:$A,$O14) | U14: =SUMIFS(G:G,$A:$A,$O14) | V14: =SUMIFS(H:H,$A:$A,$O14) | W14: =SUMIFS(I:I,$A:$A,$O14) | X14: =SUMIFS(J:J,$A:$A,$O14) | Y14: =SUMIFS(K:K,$A:$A,$O14) | Z14: =SUMIFS(L:L,$A:$A,$O14) | AA14: =SUMIFS(M:M,$A:$A,$O14)
... A175: =IFERROR((IF(((IFERROR((FIND(".",I!A173)),0))>1),(MID(I!A173,((FIND(".",I!A173))-2),5)),(MID(I!A173,((FIND(" - ",I!A173))-2),2)))),"-") | B175: =IFERROR(IF($A175="-","null",I!B173),"null") | C175: =IFERROR(IF($A175="-","null",I!C173),"null") | D175: =IFERROR(IF($A175="-","null",I!D173),"null") | E175: =IFERROR(IF($A175="-","null",I!E173),"null") | F175: =IFERROR(IF($A175="-","null",I!F173),"null") | G175: =IFERROR(IF($A175="-","null",I!G173),"null") | H175: =IFERROR(IF($A175="-","null",I!H173),"null") | I175: =IFERROR(IF($A175="-","null",I!I173),"null") | ... M175: =IFERROR(IF($A175="-","null",I!M173),"null") | O175: 50.02 | P175: =SUMIFS(B:B,$A:$A,$O175) | Q175: =SUMIFS(C:C,$A:$A,$O175) | R175: =SUMIFS(D:D,$A:$A,$O175) | S175: =SUMIFS(E:E,$A:$A,$O175) | T175: =SUMIFS(F:F,$A:$A,$O175) | U175: =SUMIFS(G:G,$A:$A,$O175) | V175: =SUMIFS(H:H,$A:$A,$O175) | W175: =SUMIFS(I:I,$A:$A,$O175) | X175: =SUMIFS(J:J,$A:$A,$O175) | Y175: =SUMIFS(K:K,$A:$A,$O175) | Z175: =SUMIFS(L:L,$A:$A,$O175) | AA175: =SUMIFS(M:M,$A:$A,$O175)
A176: =IFERROR((IF(((IFERROR((FIND(".",I!#REF!)),0))>1),(MID(I!#REF!,((FIND(".",I!#REF!))-2),5)),(MID(I!#REF!,((FIND(" - ",I!#REF!))-2),2)))),"-") | B176: =IFERROR(IF($A176="-","null",I!#REF!),"null") | C176: =IFERROR(IF($A176="-","null",I!#REF!),"null") | D176: =IFERROR(IF($A176="-","null",I!#REF!),"null") | E176: =IFERROR(IF($A176="-","null",I!#REF!),"null") | F176: =IFERROR(IF($A176="-","null",I!#REF!),"null") | G176: =IFERROR(IF($A176="-","null",I!#REF!),"null") | H176: =IFERROR(IF($A176="-","null",I!#REF!),"null") | I176: =IFERROR(IF($A176="-","null",I!#REF!),"null") | ... M176: =IFERROR(IF($A176="-","null",I!#REF!),"null") | O176: 50.03 | P176: =SUMIFS(B:B,$A:$A,$O176) | Q176: =SUMIFS(C:C,$A:$A,$O176) | R176: =SUMIFS(D:D,$A:$A,$O176) | S176: =SUMIFS(E:E,$A:$A,$O176) | T176: =SUMIFS(F:F,$A:$A,$O176) | U176: =SUMIFS(G:G,$A:$A,$O176) | V176: =SUMIFS(H:H,$A:$A,$O176) | W176: =SUMIFS(I:I,$A:$A,$O176) | X176: =SUMIFS(J:J,$A:$A,$O176) | Y176: =SUMIFS(K:K,$A:$A,$O176) | Z176: =SUMIFS(L:L,$A:$A,$O176) | AA176: =SUMIFS(M:M,$A:$A,$O176)
A177: =IFERROR((IF(((IFERROR((FIND(".",I!#REF!)),0))>1),(MID(I!#REF!,((FIND(".",I!#REF!))-2),5)),(MID(I!#REF!,((FIND(" - ",I!#REF!))-2),2)))),"-") | B177: =IFERROR(IF($A177="-","null",I!#REF!),"null") | C177: =IFERROR(IF($A177="-","null",I!#REF!),"null") | D177: =IFERROR(IF($A177="-","null",I!#REF!),"null") | E177: =IFERROR(IF($A177="-","null",I!#REF!),"null") | F177: =IFERROR(IF($A177="-","null",I!#REF!),"null") | G177: =IFERROR(IF($A177="-","null",I!#REF!),"null") | H177: =IFERROR(IF($A177="-","null",I!#REF!),"null") | I177: =IFERROR(IF($A177="-","null",I!#REF!),"null") | ... M177: =IFERROR(IF($A177="-","null",I!#REF!),"null") | O177: 50.04 | P177: =SUMIFS(B:B,$A:$A,$O177) | Q177: =SUMIFS(C:C,$A:$A,$O177) | R177: =SUMIFS(D:D,$A:$A,$O177) | S177: =SUMIFS(E:E,$A:$A,$O177) | T177: =SUMIFS(F:F,$A:$A,$O177) | U177: =SUMIFS(G:G,$A:$A,$O177) | V177: =SUMIFS(H:H,$A:$A,$O177) | W177: =SUMIFS(I:I,$A:$A,$O177) | X177: =SUMIFS(J:J,$A:$A,$O177) | Y177: =SUMIFS(K:K,$A:$A,$O177) | Z177: =SUMIFS(L:L,$A:$A,$O177) | AA177: =SUMIFS(M:M,$A:$A,$O177)
A178: =IFERROR((IF(((IFERROR((FIND(".",I!#REF!)),0))>1),(MID(I!#REF!,((FIND(".",I!#REF!))-2),5)),(MID(I!#REF!,((FIND(" - ",I!#REF!))-2),2)))),"-") | B178: =IFERROR(IF($A178="-","null",I!#REF!),"null") | C178: =IFERROR(IF($A178="-","null",I!#REF!),"null") | D178: =IFERROR(IF($A178="-","null",I!#REF!),"null") | E178: =IFERROR(IF($A178="-","null",I!#REF!),"null") | F178: =IFERROR(IF($A178="-","null",I!#REF!),"null") | G178: =IFERROR(IF($A178="-","null",I!#REF!),"null") | H178: =IFERROR(IF($A178="-","null",I!#REF!),"null") | I178: =IFERROR(IF($A178="-","null",I!#REF!),"null") | ... M178: =IFERROR(IF($A178="-","null",I!#REF!),"null") | O178: 50.05 | P178: =SUMIFS(B:B,$A:$A,$O178) | Q178: =SUMIFS(C:C,$A:$A,$O178) | R178: =SUMIFS(D:D,$A:$A,$O178) | S178: =SUMIFS(E:E,$A:$A,$O178) | T178: =SUMIFS(F:F,$A:$A,$O178) | U178: =SUMIFS(G:G,$A:$A,$O178) | V178: =SUMIFS(H:H,$A:$A,$O178) | W178: =SUMIFS(I:I,$A:$A,$O178) | X178: =SUMIFS(J:J,$A:$A,$O178) | Y178: =SUMIFS(K:K,$A:$A,$O178) | Z178: =SUMIFS(L:L,$A:$A,$O178) | AA178: =SUMIFS(M:M,$A:$A,$O178)
A179: =IFERROR((IF(((IFERROR((FIND(".",I!#REF!)),0))>1),(MID(I!#REF!,((FIND(".",I!#REF!))-2),5)),(MID(I!#REF!,((FIND(" - ",I!#REF!))-2),2)))),"-") | B179: =IFERROR(IF($A179="-","null",I!#REF!),"null") | C179: =IFERROR(IF($A179="-","null",I!#REF!),"null") | D179: =IFERROR(IF($A179="-","null",I!#REF!),"null") | E179: =IFERROR(IF($A179="-","null",I!#REF!),"null") | F179: =IFERROR(IF($A179="-","null",I!#REF!),"null") | G179: =IFERROR(IF($A179="-","null",I!#REF!),"null") | H179: =IFERROR(IF($A179="-","null",I!#REF!),"null") | I179: =IFERROR(IF($A179="-","null",I!#REF!),"null") | ... M179: =IFERROR(IF($A179="-","null",I!#REF!),"null") | O179: 50.06 | P179: =SUMIFS(B:B,$A:$A,$O179) | Q179: =SUMIFS(C:C,$A:$A,$O179) | R179: =SUMIFS(D:D,$A:$A,$O179) | S179: =SUMIFS(E:E,$A:$A,$O179) | T179: =SUMIFS(F:F,$A:$A,$O179) | U179: =SUMIFS(G:G,$A:$A,$O179) | V179: =SUMIFS(H:H,$A:$A,$O179) | W179: =SUMIFS(I:I,$A:$A,$O179) | X179: =SUMIFS(J:J,$A:$A,$O179) | Y179: =SUMIFS(K:K,$A:$A,$O179) | Z179: =SUMIFS(L:L,$A:$A,$O179) | AA179: =SUMIFS(M:M,$A:$A,$O179)
A180: =IFERROR((IF(((IFERROR((FIND(".",I!#REF!)),0))>1),(MID(I!#REF!,((FIND(".",I!#REF!))-2),5)),(MID(I!#REF!,((FIND(" - ",I!#REF!))-2),2)))),"-") | B180: =IFERROR(IF($A180="-","null",I!#REF!),"null") | C180: =IFERROR(IF($A180="-","null",I!#REF!),"null") | D180: =IFERROR(IF($A180="-","null",I!#REF!),"null") | E180: =IFERROR(IF($A180="-","null",I!#REF!),"null") | F180: =IFERROR(IF($A180="-","null",I!#REF!),"null") | G180: =IFERROR(IF($A180="-","null",I!#REF!),"null") | H180: =IFERROR(IF($A180="-","null",I!#REF!),"null") | I180: =IFERROR(IF($A180="-","null",I!#REF!),"null") | ... M180: =IFERROR(IF($A180="-","null",I!#REF!),"null") | O180: 51.01 | P180: =SUMIFS(B:B,$A:$A,$O180) | Q180: =SUMIFS(C:C,$A:$A,$O180) | R180: =SUMIFS(D:D,$A:$A,$O180) | S180: =SUMIFS(E:E,$A:$A,$O180) | T180: =SUMIFS(F:F,$A:$A,$O180) | U180: =SUMIFS(G:G,$A:$A,$O180) | V180: =SUMIFS(H:H,$A:$A,$O180) | W180: =SUMIFS(I:I,$A:$A,$O180) | X180: =SUMIFS(J:J,$A:$A,$O180) | Y180: =SUMIFS(K:K,$A:$A,$O180) | Z180: =SUMIFS(L:L,$A:$A,$O180) | AA180: =SUMIFS(M:M,$A:$A,$O180)
A181: =IFERROR((IF(((IFERROR((FIND(".",I!#REF!)),0))>1),(MID(I!#REF!,((FIND(".",I!#REF!))-2),5)),(MID(I!#REF!,((FIND(" - ",I!#REF!))-2),2)))),"-") | B181: =IFERROR(IF($A181="-","null",I!#REF!),"null") | C181: =IFERROR(IF($A181="-","null",I!#REF!),"null") | D181: =IFERROR(IF($A181="-","null",I!#REF!),"null") | E181: =IFERROR(IF($A181="-","null",I!#REF!),"null") | F181: =IFERROR(IF($A181="-","null",I!#REF!),"null") | G181: =IFERROR(IF($A181="-","null",I!#REF!),"null") | H181: =IFERROR(IF($A181="-","null",I!#REF!),"null") | I181: =IFERROR(IF($A181="-","null",I!#REF!),"null") | ... M181: =IFERROR(IF($A181="-","null",I!#REF!),"null") | O181: 51.02 | P181: =SUMIFS(B:B,$A:$A,$O181) | Q181: =SUMIFS(C:C,$A:$A,$O181) | R181: =SUMIFS(D:D,$A:$A,$O181) | S181: =SUMIFS(E:E,$A:$A,$O181) | T181: =SUMIFS(F:F,$A:$A,$O181) | U181: =SUMIFS(G:G,$A:$A,$O181) | V181: =SUMIFS(H:H,$A:$A,$O181) | W181: =SUMIFS(I:I,$A:$A,$O181) | X181: =SUMIFS(J:J,$A:$A,$O181) | Y181: =SUMIFS(K:K,$A:$A,$O181) | Z181: =SUMIFS(L:L,$A:$A,$O181) | AA181: =SUMIFS(M:M,$A:$A,$O181)
A182: =IFERROR((IF(((IFERROR((FIND(".",I!#REF!)),0))>1),(MID(I!#REF!,((FIND(".",I!#REF!))-2),5)),(MID(I!#REF!,((FIND(" - ",I!#REF!))-2),2)))),"-") | B182: =IFERROR(IF($A182="-","null",I!#REF!),"null") | C182: =IFERROR(IF($A182="-","null",I!#REF!),"null") | D182: =IFERROR(IF($A182="-","null",I!#REF!),"null") | E182: =IFERROR(IF($A182="-","null",I!#REF!),"null") | F182: =IFERROR(IF($A182="-","null",I!#REF!),"null") | G182: =IFERROR(IF($A182="-","null",I!#REF!),"null") | H182: =IFERROR(IF($A182="-","null",I!#REF!),"null") | I182: =IFERROR(IF($A182="-","null",I!#REF!),"null") | ... M182: =IFERROR(IF($A182="-","null",I!#REF!),"null") | O182: 51.03 | P182: =SUMIFS(B:B,$A:$A,$O182) | Q182: =SUMIFS(C:C,$A:$A,$O182) | R182: =SUMIFS(D:D,$A:$A,$O182) | S182: =SUMIFS(E:E,$A:$A,$O182) | T182: =SUMIFS(F:F,$A:$A,$O182) | U182: =SUMIFS(G:G,$A:$A,$O182) | V182: =SUMIFS(H:H,$A:$A,$O182) | W182: =SUMIFS(I:I,$A:$A,$O182) | X182: =SUMIFS(J:J,$A:$A,$O182) | Y182: =SUMIFS(K:K,$A:$A,$O182) | Z182: =SUMIFS(L:L,$A:$A,$O182) | AA182: =SUMIFS(M:M,$A:$A,$O182)
A183: =IFERROR((IF(((IFERROR((FIND(".",I!#REF!)),0))>1),(MID(I!#REF!,((FIND(".",I!#REF!))-2),5)),(MID(I!#REF!,((FIND(" - ",I!#REF!))-2),2)))),"-") | B183: =IFERROR(IF($A183="-","null",I!#REF!),"null") | C183: =IFERROR(IF($A183="-","null",I!#REF!),"null") | D183: =IFERROR(IF($A183="-","null",I!#REF!),"null") | E183: =IFERROR(IF($A183="-","null",I!#REF!),"null") | F183: =IFERROR(IF($A183="-","null",I!#REF!),"null") | G183: =IFERROR(IF($A183="-","null",I!#REF!),"null") | H183: =IFERROR(IF($A183="-","null",I!#REF!),"null") | I183: =IFERROR(IF($A183="-","null",I!#REF!),"null") | ... M183: =IFERROR(IF($A183="-","null",I!#REF!),"null") | O183: 51.04 | P183: =SUMIFS(B:B,$A:$A,$O183) | Q183: =SUMIFS(C:C,$A:$A,$O183) | R183: =SUMIFS(D:D,$A:$A,$O183) | S183: =SUMIFS(E:E,$A:$A,$O183) | T183: =SUMIFS(F:F,$A:$A,$O183) | U183: =SUMIFS(G:G,$A:$A,$O183) | V183: =SUMIFS(H:H,$A:$A,$O183) | W183: =SUMIFS(I:I,$A:$A,$O183) | X183: =SUMIFS(J:J,$A:$A,$O183) | Y183: =SUMIFS(K:K,$A:$A,$O183) | Z183: =SUMIFS(L:L,$A:$A,$O183) | AA183: =SUMIFS(M:M,$A:$A,$O183)
A184: =IFERROR((IF(((IFERROR((FIND(".",I!#REF!)),0))>1),(MID(I!#REF!,((FIND(".",I!#REF!))-2),5)),(MID(I!#REF!,((FIND(" - ",I!#REF!))-2),2)))),"-") | B184: =IFERROR(IF($A184="-","null",I!#REF!),"null") | C184: =IFERROR(IF($A184="-","null",I!#REF!),"null") | D184: =IFERROR(IF($A184="-","null",I!#REF!),"null") | E184: =IFERROR(IF($A184="-","null",I!#REF!),"null") | F184: =IFERROR(IF($A184="-","null",I!#REF!),"null") | G184: =IFERROR(IF($A184="-","null",I!#REF!),"null") | H184: =IFERROR(IF($A184="-","null",I!#REF!),"null") | I184: =IFERROR(IF($A184="-","null",I!#REF!),"null") | ... M184: =IFERROR(IF($A184="-","null",I!#REF!),"null") | O184: 51.05 | P184: =SUMIFS(B:B,$A:$A,$O184) | Q184: =SUMIFS(C:C,$A:$A,$O184) | R184: =SUMIFS(D:D,$A:$A,$O184) | S184: =SUMIFS(E:E,$A:$A,$O184) | T184: =SUMIFS(F:F,$A:$A,$O184) | U184: =SUMIFS(G:G,$A:$A,$O184) | V184: =SUMIFS(H:H,$A:$A,$O184) | W184: =SUMIFS(I:I,$A:$A,$O184) | X184: =SUMIFS(J:J,$A:$A,$O184) | Y184: =SUMIFS(K:K,$A:$A,$O184) | Z184: =SUMIFS(L:L,$A:$A,$O184) | AA184: =SUMIFS(M:M,$A:$A,$O184)
A185: =IFERROR((IF(((IFERROR((FIND(".",I!#REF!)),0))>1),(MID(I!#REF!,((FIND(".",I!#REF!))-2),5)),(MID(I!#REF!,((FIND(" - ",I!#REF!))-2),2)))),"-") | B185: =IFERROR(IF($A185="-","null",I!#REF!),"null") | C185: =IFERROR(IF($A185="-","null",I!#REF!),"null") | D185: =IFERROR(IF($A185="-","null",I!#REF!),"null") | E185: =IFERROR(IF($A185="-","null",I!#REF!),"null") | F185: =IFERROR(IF($A185="-","null",I!#REF!),"null") | G185: =IFERROR(IF($A185="-","null",I!#REF!),"null") | H185: =IFERROR(IF($A185="-","null",I!#REF!),"null") | I185: =IFERROR(IF($A185="-","null",I!#REF!),"null") | ... M185: =IFERROR(IF($A185="-","null",I!#REF!),"null") | O185: 51.06 | P185: =SUMIFS(B:B,$A:$A,$O185) | Q185: =SUMIFS(C:C,$A:$A,$O185) | R185: =SUMIFS(D:D,$A:$A,$O185) | S185: =SUMIFS(E:E,$A:$A,$O185) | T185: =SUMIFS(F:F,$A:$A,$O185) | U185: =SUMIFS(G:G,$A:$A,$O185) | V185: =SUMIFS(H:H,$A:$A,$O185) | W185: =SUMIFS(I:I,$A:$A,$O185) | X185: =SUMIFS(J:J,$A:$A,$O185) | Y185: =SUMIFS(K:K,$A:$A,$O185) | Z185: =SUMIFS(L:L,$A:$A,$O185) | AA185: =SUMIFS(M:M,$A:$A,$O185)
A186: =IFERROR((IF(((IFERROR((FIND(".",I!#REF!)),0))>1),(MID(I!#REF!,((FIND(".",I!#REF!))-2),5)),(MID(I!#REF!,((FIND(" - ",I!#REF!))-2),2)))),"-") | B186: =IFERROR(IF($A186="-","null",I!#REF!),"null") | C186: =IFERROR(IF($A186="-","null",I!#REF!),"null") | D186: =IFERROR(IF($A186="-","null",I!#REF!),"null") | E186: =IFERROR(IF($A186="-","null",I!#REF!),"null") | F186: =IFERROR(IF($A186="-","null",I!#REF!),"null") | G186: =IFERROR(IF($A186="-","null",I!#REF!),"null") | H186: =IFERROR(IF($A186="-","null",I!#REF!),"null") | I186: =IFERROR(IF($A186="-","null",I!#REF!),"null") | ... M186: =IFERROR(IF($A186="-","null",I!#REF!),"null") | O186: 51.07 | P186: =SUMIFS(B:B,$A:$A,$O186) | Q186: =SUMIFS(C:C,$A:$A,$O186) | R186: =SUMIFS(D:D,$A:$A,$O186) | S186: =SUMIFS(E:E,$A:$A,$O186) | T186: =SUMIFS(F:F,$A:$A,$O186) | U186: =SUMIFS(G:G,$A:$A,$O186) | V186: =SUMIFS(H:H,$A:$A,$O186) | W186: =SUMIFS(I:I,$A:$A,$O186) | X186: =SUMIFS(J:J,$A:$A,$O186) | Y186: =SUMIFS(K:K,$A:$A,$O186) | Z186: =SUMIFS(L:L,$A:$A,$O186) | AA186: =SUMIFS(M:M,$A:$A,$O186)
A187: =IFERROR((IF(((IFERROR((FIND(".",I!#REF!)),0))>1),(MID(I!#REF!,((FIND(".",I!#REF!))-2),5)),(MID(I!#REF!,((FIND(" - ",I!#REF!))-2),2)))),"-") | B187: =IFERROR(IF($A187="-","null",I!#REF!),"null") | C187: =IFERROR(IF($A187="-","null",I!#REF!),"null") | D187: =IFERROR(IF($A187="-","null",I!#REF!),"null") | E187: =IFERROR(IF($A187="-","null",I!#REF!),"null") | F187: =IFERROR(IF($A187="-","null",I!#REF!),"null") | G187: =IFERROR(IF($A187="-","null",I!#REF!),"null") | H187: =IFERROR(IF($A187="-","null",I!#REF!),"null") | I187: =IFERROR(IF($A187="-","null",I!#REF!),"null") | ... M187: =IFERROR(IF($A187="-","null",I!#REF!),"null") | O187: 51.08 | P187: =SUMIFS(B:B,$A:$A,$O187) | Q187: =SUMIFS(C:C,$A:$A,$O187) | R187: =SUMIFS(D:D,$A:$A,$O187) | S187: =SUMIFS(E:E,$A:$A,$O187) | T187: =SUMIFS(F:F,$A:$A,$O187) | U187: =SUMIFS(G:G,$A:$A,$O187) | V187: =SUMIFS(H:H,$A:$A,$O187) | W187: =SUMIFS(I:I,$A:$A,$O187) | X187: =SUMIFS(J:J,$A:$A,$O187) | Y187: =SUMIFS(K:K,$A:$A,$O187) | Z187: =SUMIFS(L:L,$A:$A,$O187) | AA187: =SUMIFS(M:M,$A:$A,$O187)
... A189: =IFERROR((IF(((IFERROR((FIND(".",I!#REF!)),0))>1),(MID(I!#REF!,((FIND(".",I!#REF!))-2),5)),(MID(I!#REF!,((FIND(" - ",I!#REF!))-2),2)))),"-") | B189: =IFERROR(IF($A189="-","null",I!#REF!),"null") | C189: =IFERROR(IF($A189="-","null",I!#REF!),"null") | D189: =IFERROR(IF($A189="-","null",I!#REF!),"null") | E189: =IFERROR(IF($A189="-","null",I!#REF!),"null") | F189: =IFERROR(IF($A189="-","null",I!#REF!),"null") | G189: =IFERROR(IF($A189="-","null",I!#REF!),"null") | H189: =IFERROR(IF($A189="-","null",I!#REF!),"null") | I189: =IFERROR(IF($A189="-","null",I!#REF!),"null") | ... M189: =IFERROR(IF($A189="-","null",I!#REF!),"null") | O189: 52.02 | P189: =SUMIFS(B:B,$A:$A,$O189) | Q189: =SUMIFS(C:C,$A:$A,$O189) | R189: =SUMIFS(D:D,$A:$A,$O189) | S189: =SUMIFS(E:E,$A:$A,$O189) | T189: =SUMIFS(F:F,$A:$A,$O189) | U189: =SUMIFS(G:G,$A:$A,$O189) | V189: =SUMIFS(H:H,$A:$A,$O189) | W189: =SUMIFS(I:I,$A:$A,$O189) | X189: =SUMIFS(J:J,$A:$A,$O189) | Y189: =SUMIFS(K:K,$A:$A,$O189) | Z189: =SUMIFS(L:L,$A:$A,$O189) | AA189: =SUMIFS(M:M,$A:$A,$O189)
A190: =IFERROR((IF(((IFERROR((FIND(".",I!A174)),0))>1),(MID(I!A174,((FIND(".",I!A174))-2),5)),(MID(I!A174,((FIND(" - ",I!A174))-2),2)))),"-") | B190: =IFERROR(IF($A190="-","null",I!B174),"null") | C190: =IFERROR(IF($A190="-","null",I!C174),"null") | D190: =IFERROR(IF($A190="-","null",I!D174),"null") | E190: =IFERROR(IF($A190="-","null",I!E174),"null") | F190: =IFERROR(IF($A190="-","null",I!F174),"null") | G190: =IFERROR(IF($A190="-","null",I!G174),"null") | H190: =IFERROR(IF($A190="-","null",I!H174),"null") | I190: =IFERROR(IF($A190="-","null",I!I174),"null") | ... M190: =IFERROR(IF($A190="-","null",I!M174),"null") | O190: 52.03 | P190: =SUMIFS(B:B,$A:$A,$O190) | Q190: =SUMIFS(C:C,$A:$A,$O190) | R190: =SUMIFS(D:D,$A:$A,$O190) | S190: =SUMIFS(E:E,$A:$A,$O190) | T190: =SUMIFS(F:F,$A:$A,$O190) | U190: =SUMIFS(G:G,$A:$A,$O190) | V190: =SUMIFS(H:H,$A:$A,$O190) | W190: =SUMIFS(I:I,$A:$A,$O190) | X190: =SUMIFS(J:J,$A:$A,$O190) | Y190: =SUMIFS(K:K,$A:$A,$O190) | Z190: =SUMIFS(L:L,$A:$A,$O190) | AA190: =SUMIFS(M:M,$A:$A,$O190)
A191: =IFERROR((IF(((IFERROR((FIND(".",I!A175)),0))>1),(MID(I!A175,((FIND(".",I!A175))-2),5)),(MID(I!A175,((FIND(" - ",I!A175))-2),2)))),"-") | B191: =IFERROR(IF($A191="-","null",I!B175),"null") | C191: =IFERROR(IF($A191="-","null",I!C175),"null") | D191: =IFERROR(IF($A191="-","null",I!D175),"null") | E191: =IFERROR(IF($A191="-","null",I!E175),"null") | F191: =IFERROR(IF($A191="-","null",I!F175),"null") | G191: =IFERROR(IF($A191="-","null",I!G175),"null") | H191: =IFERROR(IF($A191="-","null",I!H175),"null") | I191: =IFERROR(IF($A191="-","null",I!I175),"null") | ... M191: =IFERROR(IF($A191="-","null",I!M175),"null") | O191: 52.04 | P191: =SUMIFS(B:B,$A:$A,$O191) | Q191: =SUMIFS(C:C,$A:$A,$O191) | R191: =SUMIFS(D:D,$A:$A,$O191) | S191: =SUMIFS(E:E,$A:$A,$O191) | T191: =SUMIFS(F:F,$A:$A,$O191) | U191: =SUMIFS(G:G,$A:$A,$O191) | V191: =SUMIFS(H:H,$A:$A,$O191) | W191: =SUMIFS(I:I,$A:$A,$O191) | X191: =SUMIFS(J:J,$A:$A,$O191) | Y191: =SUMIFS(K:K,$A:$A,$O191) | Z191: =SUMIFS(L:L,$A:$A,$O191) | AA191: =SUMIFS(M:M,$A:$A,$O191)
A192: =IFERROR((IF(((IFERROR((FIND(".",I!A176)),0))>1),(MID(I!A176,((FIND(".",I!A176))-2),5)),(MID(I!A176,((FIND(" - ",I!A176))-2),2)))),"-") | B192: =IFERROR(IF($A192="-","null",I!B176),"null") | C192: =IFERROR(IF($A192="-","null",I!C176),"null") | D192: =IFERROR(IF($A192="-","null",I!D176),"null") | E192: =IFERROR(IF($A192="-","null",I!E176),"null") | F192: =IFERROR(IF($A192="-","null",I!F176),"null") | G192: =IFERROR(IF($A192="-","null",I!G176),"null") | H192: =IFERROR(IF($A192="-","null",I!H176),"null") | I192: =IFERROR(IF($A192="-","null",I!I176),"null") | ... M192: =IFERROR(IF($A192="-","null",I!M176),"null") | O192: 53.01 | P192: =SUMIFS(B:B,$A:$A,$O192) | Q192: =SUMIFS(C:C,$A:$A,$O192) | R192: =SUMIFS(D:D,$A:$A,$O192) | S192: =SUMIFS(E:E,$A:$A,$O192) | T192: =SUMIFS(F:F,$A:$A,$O192) | U192: =SUMIFS(G:G,$A:$A,$O192) | V192: =SUMIFS(H:H,$A:$A,$O192) | W192: =SUMIFS(I:I,$A:$A,$O192) | X192: =SUMIFS(J:J,$A:$A,$O192) | Y192: =SUMIFS(K:K,$A:$A,$O192) | Z192: =SUMIFS(L:L,$A:$A,$O192) | AA192: =SUMIFS(M:M,$A:$A,$O192)
A193: =IFERROR((IF(((IFERROR((FIND(".",I!A177)),0))>1),(MID(I!A177,((FIND(".",I!A177))-2),5)),(MID(I!A177,((FIND(" - ",I!A177))-2),2)))),"-") | B193: =IFERROR(IF($A193="-","null",I!B177),"null") | C193: =IFERROR(IF($A193="-","null",I!C177),"null") | D193: =IFERROR(IF($A193="-","null",I!D177),"null") | E193: =IFERROR(IF($A193="-","null",I!E177),"null") | F193: =IFERROR(IF($A193="-","null",I!F177),"null") | G193: =IFERROR(IF($A193="-","null",I!G177),"null") | H193: =IFERROR(IF($A193="-","null",I!H177),"null") | I193: =IFERROR(IF($A193="-","null",I!I177),"null") | ... M193: =IFERROR(IF($A193="-","null",I!M177),"null") | O193: 53.02 | P193: =SUMIFS(B:B,$A:$A,$O193) | Q193: =SUMIFS(C:C,$A:$A,$O193) | R193: =SUMIFS(D:D,$A:$A,$O193) | S193: =SUMIFS(E:E,$A:$A,$O193) | T193: =SUMIFS(F:F,$A:$A,$O193) | U193: =SUMIFS(G:G,$A:$A,$O193) | V193: =SUMIFS(H:H,$A:$A,$O193) | W193: =SUMIFS(I:I,$A:$A,$O193) | X193: =SUMIFS(J:J,$A:$A,$O193) | Y193: =SUMIFS(K:K,$A:$A,$O193) | Z193: =SUMIFS(L:L,$A:$A,$O193) | AA193: =SUMIFS(M:M,$A:$A,$O193)
A194: =IFERROR((IF(((IFERROR((FIND(".",I!A178)),0))>1),(MID(I!A178,((FIND(".",I!A178))-2),5)),(MID(I!A178,((FIND(" - ",I!A178))-2),2)))),"-") | B194: =IFERROR(IF($A194="-","null",I!B178),"null") | C194: =IFERROR(IF($A194="-","null",I!C178),"null") | D194: =IFERROR(IF($A194="-","null",I!D178),"null") | E194: =IFERROR(IF($A194="-","null",I!E178),"null") | F194: =IFERROR(IF($A194="-","null",I!F178),"null") | G194: =IFERROR(IF($A194="-","null",I!G178),"null") | H194: =IFERROR(IF($A194="-","null",I!H178),"null") | I194: =IFERROR(IF($A194="-","null",I!I178),"null") | ... M194: =IFERROR(IF($A194="-","null",I!M178),"null") | O194: 54.01 | P194: =SUMIFS(B:B,$A:$A,$O194) | Q194: =SUMIFS(C:C,$A:$A,$O194) | R194: =SUMIFS(D:D,$A:$A,$O194) | S194: =SUMIFS(E:E,$A:$A,$O194) | T194: =SUMIFS(F:F,$A:$A,$O194) | U194: =SUMIFS(G:G,$A:$A,$O194) | V194: =SUMIFS(H:H,$A:$A,$O194) | W194: =SUMIFS(I:I,$A:$A,$O194) | X194: =SUMIFS(J:J,$A:$A,$O194) | Y194: =SUMIFS(K:K,$A:$A,$O194) | Z194: =SUMIFS(L:L,$A:$A,$O194) | AA194: =SUMIFS(M:M,$A:$A,$O194)
A195: =IFERROR((IF(((IFERROR((FIND(".",I!A179)),0))>1),(MID(I!A179,((FIND(".",I!A179))-2),5)),(MID(I!A179,((FIND(" - ",I!A179))-2),2)))),"-") | B195: =IFERROR(IF($A195="-","null",I!B179),"null") | C195: =IFERROR(IF($A195="-","null",I!C179),"null") | D195: =IFERROR(IF($A195="-","null",I!D179),"null") | E195: =IFERROR(IF($A195="-","null",I!E179),"null") | F195: =IFERROR(IF($A195="-","null",I!F179),"null") | G195: =IFERROR(IF($A195="-","null",I!G179),"null") | H195: =IFERROR(IF($A195="-","null",I!H179),"null") | I195: =IFERROR(IF($A195="-","null",I!I179),"null") | ... M195: =IFERROR(IF($A195="-","null",I!M179),"null") | O195: 54.02 | P195: =SUMIFS(B:B,$A:$A,$O195) | Q195: =SUMIFS(C:C,$A:$A,$O195) | R195: =SUMIFS(D:D,$A:$A,$O195) | S195: =SUMIFS(E:E,$A:$A,$O195) | T195: =SUMIFS(F:F,$A:$A,$O195) | U195: =SUMIFS(G:G,$A:$A,$O195) | V195: =SUMIFS(H:H,$A:$A,$O195) | W195: =SUMIFS(I:I,$A:$A,$O195) | X195: =SUMIFS(J:J,$A:$A,$O195) | Y195: =SUMIFS(K:K,$A:$A,$O195) | Z195: =SUMIFS(L:L,$A:$A,$O195) | AA195: =SUMIFS(M:M,$A:$A,$O195)
A196: =IFERROR((IF(((IFERROR((FIND(".",I!A180)),0))>1),(MID(I!A180,((FIND(".",I!A180))-2),5)),(MID(I!A180,((FIND(" - ",I!A180))-2),2)))),"-") | B196: =IFERROR(IF($A196="-","null",I!B180),"null") | C196: =IFERROR(IF($A196="-","null",I!C180),"null") | D196: =IFERROR(IF($A196="-","null",I!D180),"null") | E196: =IFERROR(IF($A196="-","null",I!E180),"null") | F196: =IFERROR(IF($A196="-","null",I!F180),"null") | G196: =IFERROR(IF($A196="-","null",I!G180),"null") | H196: =IFERROR(IF($A196="-","null",I!H180),"null") | I196: =IFERROR(IF($A196="-","null",I!I180),"null") | ... M196: =IFERROR(IF($A196="-","null",I!M180),"null") | O196: 54.04 | P196: =SUMIFS(B:B,$A:$A,$O196) | Q196: =SUMIFS(C:C,$A:$A,$O196) | R196: =SUMIFS(D:D,$A:$A,$O196) | S196: =SUMIFS(E:E,$A:$A,$O196) | T196: =SUMIFS(F:F,$A:$A,$O196) | U196: =SUMIFS(G:G,$A:$A,$O196) | V196: =SUMIFS(H:H,$A:$A,$O196) | W196: =SUMIFS(I:I,$A:$A,$O196) | X196: =SUMIFS(J:J,$A:$A,$O196) | Y196: =SUMIFS(K:K,$A:$A,$O196) | Z196: =SUMIFS(L:L,$A:$A,$O196) | AA196: =SUMIFS(M:M,$A:$A,$O196)
A197: =IFERROR((IF(((IFERROR((FIND(".",I!A181)),0))>1),(MID(I!A181,((FIND(".",I!A181))-2),5)),(MID(I!A181,((FIND(" - ",I!A181))-2),2)))),"-") | B197: =IFERROR(IF($A197="-","null",I!B181),"null") | C197: =IFERROR(IF($A197="-","null",I!C181),"null") | D197: =IFERROR(IF($A197="-","null",I!D181),"null") | E197: =IFERROR(IF($A197="-","null",I!E181),"null") | F197: =IFERROR(IF($A197="-","null",I!F181),"null") | G197: =IFERROR(IF($A197="-","null",I!G181),"null") | H197: =IFERROR(IF($A197="-","null",I!H181),"null") | I197: =IFERROR(IF($A197="-","null",I!I181),"null") | ... M197: =IFERROR(IF($A197="-","null",I!M181),"null") | O197: 54.05 | P197: =SUMIFS(B:B,$A:$A,$O197) | Q197: =SUMIFS(C:C,$A:$A,$O197) | R197: =SUMIFS(D:D,$A:$A,$O197) | S197: =SUMIFS(E:E,$A:$A,$O197) | T197: =SUMIFS(F:F,$A:$A,$O197) | U197: =SUMIFS(G:G,$A:$A,$O197) | V197: =SUMIFS(H:H,$A:$A,$O197) | W197: =SUMIFS(I:I,$A:$A,$O197) | X197: =SUMIFS(J:J,$A:$A,$O197) | Y197: =SUMIFS(K:K,$A:$A,$O197) | Z197: =SUMIFS(L:L,$A:$A,$O197) | AA197: =SUMIFS(M:M,$A:$A,$O197)
A198: =IFERROR((IF(((IFERROR((FIND(".",I!A182)),0))>1),(MID(I!A182,((FIND(".",I!A182))-2),5)),(MID(I!A182,((FIND(" - ",I!A182))-2),2)))),"-") | B198: =IFERROR(IF($A198="-","null",I!B182),"null") | C198: =IFERROR(IF($A198="-","null",I!C182),"null") | D198: =IFERROR(IF($A198="-","null",I!D182),"null") | E198: =IFERROR(IF($A198="-","null",I!E182),"null") | F198: =IFERROR(IF($A198="-","null",I!F182),"null") | G198: =IFERROR(IF($A198="-","null",I!G182),"null") | H198: =IFERROR(IF($A198="-","null",I!H182),"null") | I198: =IFERROR(IF($A198="-","null",I!I182),"null") | ... M198: =IFERROR(IF($A198="-","null",I!M182),"null") | O198: 55.01 | P198: =SUMIFS(B:B,$A:$A,$O198) | Q198: =SUMIFS(C:C,$A:$A,$O198) | R198: =SUMIFS(D:D,$A:$A,$O198) | S198: =SUMIFS(E:E,$A:$A,$O198) | T198: =SUMIFS(F:F,$A:$A,$O198) | U198: =SUMIFS(G:G,$A:$A,$O198) | V198: =SUMIFS(H:H,$A:$A,$O198) | W198: =SUMIFS(I:I,$A:$A,$O198) | X198: =SUMIFS(J:J,$A:$A,$O198) | Y198: =SUMIFS(K:K,$A:$A,$O198) | Z198: =SUMIFS(L:L,$A:$A,$O198) | AA198: =SUMIFS(M:M,$A:$A,$O198)
A199: =IFERROR((IF(((IFERROR((FIND(".",I!A183)),0))>1),(MID(I!A183,((FIND(".",I!A183))-2),5)),(MID(I!A183,((FIND(" - ",I!A183))-2),2)))),"-") | B199: =IFERROR(IF($A199="-","null",I!B183),"null") | C199: =IFERROR(IF($A199="-","null",I!C183),"null") | D199: =IFERROR(IF($A199="-","null",I!D183),"null") | E199: =IFERROR(IF($A199="-","null",I!E183),"null") | F199: =IFERROR(IF($A199="-","null",I!F183),"null") | G199: =IFERROR(IF($A199="-","null",I!G183),"null") | H199: =IFERROR(IF($A199="-","null",I!H183),"null") | I199: =IFERROR(IF($A199="-","null",I!I183),"null") | ... M199: =IFERROR(IF($A199="-","null",I!M183),"null") | O199: 55.02 | P199: =SUMIFS(B:B,$A:$A,$O199) | Q199: =SUMIFS(C:C,$A:$A,$O199) | R199: =SUMIFS(D:D,$A:$A,$O199) | S199: =SUMIFS(E:E,$A:$A,$O199) | T199: =SUMIFS(F:F,$A:$A,$O199) | U199: =SUMIFS(G:G,$A:$A,$O199) | V199: =SUMIFS(H:H,$A:$A,$O199) | W199: =SUMIFS(I:I,$A:$A,$O199) | X199: =SUMIFS(J:J,$A:$A,$O199) | Y199: =SUMIFS(K:K,$A:$A,$O199) | Z199: =SUMIFS(L:L,$A:$A,$O199) | AA199: =SUMIFS(M:M,$A:$A,$O199)

Sheet BD
AI3: 9 | AJ3: 10 | AK3: 11 | AL3: 12 | AM3: 13 | AN3: 14 | AO3: 15 | AP3: 16 | AQ3: 17 | AR3: 18 | AS3: 19 | AT3: 20 | AV3: 9 | AW3: 10 | AX3: 11 | AY3: 12 | AZ3: 13 | BA3: 14 | BB3: 15 | BC3: 16 | BD3: 17 | BE3: 18 | BF3: 19 | BG3: 20
A4: Clasf. | B4: Nome da conta | C4: Tipo | D4: Natureza | E4: Grupo de conta | F4: Ativo | G4: Status | I4: 43831 | J4: 43862 | K4: 43891 | L4: 43922 | M4: 43952 | N4: 43983 | O4: 44013 | P4: 44044 | Q4: 44075 | R4: 44105 | S4: 44136 | T4: 44166 | V4: 44197 | W4: 44228 | X4: 44256 | Y4: 44287 | Z4: 44317 | AA4: 44348 | AB4: 44378 | AC4: 44409 | AD4: 44440 | AE4: 44470 | AF4: 44501 | AG4: 44531 | AI4: 44562 | AJ4: 44593 | AK4: 44621 | AL4: 44652 | AM4: 44682 | AN4: 44713 | AO4: 44743 | AP4: 44774 | AQ4: 44805 | AR4: 44835 | AS4: 44866 | AT4: 44896 | AV4: 44927 | AW4: 44958 | AX4: 44986 | AY4: 45017 | AZ4: 45047 | BA4: 45078 | BB4: 45108 | BC4: 45139 | BD4: 45170 | BE4: 45200 | BF4: 45231 | BG4: 45261 | BJ4: 45292 | BK4: 45323 | BL4: 45352 | BM4: 45383 | BN4: 45413 | BO4: 45444 | BP4: 45474 | BQ4: 45505 | BR4: 45536 | BS4: 45566 | BT4: 45597 | BU4: 45627 | BW4: jan/25 | BX4: fev/25 | BY4: mar/25 | BZ4: abr/25 | CA4: mai/25 | CB4: jun/25 | CC4: jul/25 | CD4: ago/25 | CE4: set/25 | CF4: out/25 | CG4: nov/25 | CH4: dez/25
A5: 10.01 | B5: Receita com produto | C5: Analítica | D5: Entrada | E5: =VLOOKUP($A5,PL.C!$B:$F,5,0) | F5: sim | G5: Budget | I5: 0 | J5: 36476 | K5: 42099 | L5: 1778806 | M5: 980903 | N5: 1146964 | O5: 1067595 | P5: 993317 | Q5: 1045459 | R5: 995263 | S5: 809964 | T5: 1083586 | V5: 920566 | W5: 847949 | X5: 1081182 | Y5: 971699 | Z5: 986935 | AA5: 1087558 | AB5: 1124216 | AC5: 1156838 | AD5: 1059419 | AE5: 993808 | AF5: 1098796 | AG5: 1075932 | AI5: 853337 | AJ5: 840528 | AK5: 1260369 | AL5: 1012027 | AM5: 1155106 | AN5: 1181187 | AO5: 1160671 | AP5: 1231074 | AQ5: 1117419 | AR5: 1131961 | AS5: 1242942 | AT5: 1217485 | AV5: 938670.7 | AW5: 924580.8 | AX5: 1386405.9 | AY5: 1113229.7 | AZ5: 1270616.6 | BA5: 1299305.7 | BB5: 1276738.1 | BC5: 1354181.4 | BD5: 1229160.9 | BE5: 1245157.1 | BF5: 1367236.2 | BG5: 1339233.5 | BJ5: 1307373.4 | BK5: 1255054.1 | BL5: 1396844.7 | BM5: 1286710.3 | BN5: 1455097.2 | BO5: 1561691.3 | BP5: 1459685.7 | BQ5: 1553959.8 | BR5: 1460685.5 | BS5: 1505911.7 | BT5: 1438646.5 | BU5: 1533462.2 | BW5: ='Hist. e Proj.'!AV62 | BX5: ='Hist. e Proj.'!AW62 | BY5: ='Hist. e Proj.'!AX62 | BZ5: ='Hist. e Proj.'!AY62 | CA5: ='Hist. e Proj.'!AZ62 | CB5: ='Hist. e Proj.'!BA62 | CC5: ='Hist. e Proj.'!BB62 | CD5: ='Hist. e Proj.'!BC62 | ... CH5: ='Hist. e Proj.'!BG62
A6: 10.02 | B6: Receita com serviço | C6: Analítica | D6: Entrada | E6: =VLOOKUP($A6,PL.C!$B:$F,5,0) | F6: sim | G6: Budget | I6: 0 | J6: 0 | K6: 0 | L6: 0 | M6: 0 | N6: 0 | O6: 0 | P6: 0 | Q6: 37 | R6: 0 | S6: 0 | T6: 0 | V6: 0 | W6: 0 | X6: 0 | Y6: 0 | Z6: 579 | AA6: 0 | AB6: 0 | AC6: 0 | AD6: 0 | AE6: 0 | AF6: 0 | AG6: 0 | AI6: 0 | AJ6: 0 | AK6: 0 | AL6: 0 | AM6: 0 | AN6: 0 | AO6: 0 | AP6: 0 | AQ6: 0 | AR6: 0 | AS6: 0 | AT6: 0 | AV6: 0 | AW6: 0 | AX6: 0 | AY6: 0 | AZ6: 0 | BA6: 0 | BB6: 0 | BC6: 0 | BD6: 0 | BE6: 0 | BF6: 0 | BG6: 0 | BI6: 1.05 | BJ6: 21 | BK6: 0 | BL6: 0 | BM6: 0 | BN6: 0 | BO6: 0 | BP6: 0 | BQ6: 0 | BR6: 0 | BS6: 0 | BT6: 0 | BU6: 0 | BW6: =_xlfn.XLOOKUP($A6,$A$203:$A$399,BJ$203:BJ$399,"Não Existe")*$BI6 | BX6: =_xlfn.SINGLE(_xlfn.XLOOKUP($A6,$A$203:$A$399,BK$203:BK$399,"Não Existe"))*$BI6 | BY6: =_xlfn.SINGLE(_xlfn.XLOOKUP($A6,$A$203:$A$399,BL$203:BL$399,"Não Existe"))*$BI6 | BZ6: =_xlfn.SINGLE(_xlfn.XLOOKUP($A6,$A$203:$A$399,BM$203:BM$399,"Não Existe"))*$BI6 | CA6: =_xlfn.SINGLE(_xlfn.XLOOKUP($A6,$A$203:$A$399,BN$203:BN$399,"Não Existe"))*$BI6 | CB6: =_xlfn.SINGLE(_xlfn.XLOOKUP($A6,$A$203:$A$399,BO$203:BO$399,"Não Existe"))*$BI6 | CC6: =_xlfn.SINGLE(_xlfn.XLOOKUP($A6,$A$203:$A$399,BP$203:BP$399,"Não Existe"))*$BI6 | CD6: =_xlfn.SINGLE(_xlfn.XLOOKUP($A6,$A$203:$A$399,BQ$203:BQ$399,"Não Existe"))*$BI6 | CE6: =_xlfn.SINGLE(_xlfn.XLOOKUP($A6,$A$203:$A$399,BR$203:BR$399,"Não Existe"))*$BI6 | ... CH6: =_xlfn.SINGLE(_xlfn.XLOOKUP($A6,$A$203:$A$399,BU$203:BU$399,"Não Existe"))*$BI6
A7: 10.03 | B7: Outras Receitas | C7: Analítica | D7: Entrada | E7: =VLOOKUP($A7,PL.C!$B:$F,5,0) | F7: sim | G7: Budget | I7: 0 | J7: 0 | K7: 0 | L7: 0 | M7: 0 | N7: 1109 | O7: 1458 | P7: 1835 | Q7: 2850 | R7: 762 | S7: 614 | T7: 2959 | V7: 4039 | W7: 1033 | X7: 1029 | Y7: 997 | Z7: 869 | AA7: 916 | AB7: 1657 | AC7: 764 | AD7: 783 | AE7: 1959 | AF7: 456 | AG7: 612 | AI7: 425 | AJ7: 10862 | AK7: 5968 | AL7: 1002 | AM7: 374 | AN7: 396 | AO7: 389 | AP7: 2848 | AQ7: 1126 | AR7: 6437 | AS7: 2605 | AT7: 3477 | AV7: 447.1 | AW7: 11426.824 | AX7: 6278.336 | AY7: 1054.104 | AZ7: 393.448 | BA7: 416.592 | BB7: 409.228 | BC7: 2996.096 | BD7: 1184.552 | BE7: 6771.724 | BF7: 2740.46 | BG7: 3657.804 | BI7: 1.05 | BJ7: 9691.5 | BK7: 1462.65 | BL7: 2131.5 | BM7: 1544.55 | BN7: 2871.75 | BO7: 1923.6 | BP7: 1386 | BQ7: 7108.5 | BR7: 4737.6 | BS7: 1832.25 | BT7: 0 | BU7: 2891.7 | BW7: =_xlfn.XLOOKUP($A7,$A$203:$A$399,BJ$203:BJ$399,"Não Existe")*$BI7 | BX7: =_xlfn.SINGLE(_xlfn.XLOOKUP($A7,$A$203:$A$399,BK$203:BK$399,"Não Existe"))*$BI7 | BY7: =_xlfn.SINGLE(_xlfn.XLOOKUP($A7,$A$203:$A$399,BL$203:BL$399,"Não Existe"))*$BI7 | BZ7: =_xlfn.SINGLE(_xlfn.XLOOKUP($A7,$A$203:$A$399,BM$203:BM$399,"Não Existe"))*$BI7 | CA7: =_xlfn.SINGLE(_xlfn.XLOOKUP($A7,$A$203:$A$399,BN$203:BN$399,"Não Existe"))*$BI7 | CB7: =_xlfn.SINGLE(_xlfn.XLOOKUP($A7,$A$203:$A$399,BO$203:BO$399,"Não Existe"))*$BI7 | CC7: =_xlfn.SINGLE(_xlfn.XLOOKUP($A7,$A$203:$A$399,BP$203:BP$399,"Não Existe"))*$BI7 | CD7: =_xlfn.SINGLE(_xlfn.XLOOKUP($A7,$A$203:$A$399,BQ$203:BQ$399,"Não Existe"))*$BI7 | CE7: =_xlfn.SINGLE(_xlfn.XLOOKUP($A7,$A$203:$A$399,BR$203:BR$399,"Não Existe"))*$BI7 | ... CH7: =_xlfn.SINGLE(_xlfn.XLOOKUP($A7,$A$203:$A$399,BU$203:BU$399,"Não Existe"))*$BI7
A8: 10.04 | B8: Estorno de Produtos | C8: Analítica | D8: Saída | E8: =VLOOKUP($A8,PL.C!$B:$F,5,0) | F8: sim | G8: Budget | I8: 0 | J8: 0 | K8: 0 | L8: 0 | M8: 0 | N8: 0 | O8: 0 | P8: 0 | Q8: -56 | R8: -10 | S8: 0 | T8: 0 | V8: 0 | W8: 0 | X8: 0 | Y8: 0 | Z8: 0 | AA8: 0 | AB8: 0 | AC8: 0 | AD8: 0 | AE8: 0 | AF8: -268 | AG8: -22 | AI8: 0 | AJ8: 0 | AK8: 0 | AL8: 0 | AM8: 0 | AN8: 0 | AO8: 0 | AP8: 0 | AQ8: 0 | AR8: 0 | AS8: 0 | AT8: 0 | AV8: 0 | AW8: 0 | AX8: 0 | AY8: 0 | AZ8: 0 | BA8: 0 | BB8: 0 | BC8: 0 | BD8: 0 | BE8: 0 | BF8: 0 | BG8: 0 | BI8: 1.05 | BJ8: 0 | BK8: 0 | BL8: 0 | BM8: 0 | BN8: 0 | BO8: 0 | BP8: 0 | BQ8: 0 | BR8: 0 | BS8: 0 | BT8: 0 | BU8: 0 | BW8: =_xlfn.XLOOKUP($A8,$A$203:$A$399,BJ$203:BJ$399,"Não Existe")*$BI8 | BX8: =_xlfn.SINGLE(_xlfn.XLOOKUP($A8,$A$203:$A$399,BK$203:BK$399,"Não Existe"))*$BI8 | BY8: =_xlfn.SINGLE(_xlfn.XLOOKUP($A8,$A$203:$A$399,BL$203:BL$399,"Não Existe"))*$BI8 | BZ8: =_xlfn.SINGLE(_xlfn.XLOOKUP($A8,$A$203:$A$399,BM$203:BM$399,"Não Existe"))*$BI8 | CA8: =_xlfn.SINGLE(_xlfn.XLOOKUP($A8,$A$203:$A$399,BN$203:BN$399,"Não Existe"))*$BI8 | CB8: =_xlfn.SINGLE(_xlfn.XLOOKUP($A8,$A$203:$A$399,BO$203:BO$399,"Não Existe"))*$BI8 | CC8: =_xlfn.SINGLE(_xlfn.XLOOKUP($A8,$A$203:$A$399,BP$203:BP$399,"Não Existe"))*$BI8 | CD8: =_xlfn.SINGLE(_xlfn.XLOOKUP($A8,$A$203:$A$399,BQ$203:BQ$399,"Não Existe"))*$BI8 | CE8: =_xlfn.SINGLE(_xlfn.XLOOKUP($A8,$A$203:$A$399,BR$203:BR$399,"Não Existe"))*$BI8 | ... CH8: =_xlfn.SINGLE(_xlfn.XLOOKUP($A8,$A$203:$A$399,BU$203:BU$399,"Não Existe"))*$BI8
A9: 10.06 | B9: Devolução de produto | C9: Analítica | D9: Saída | E9: =VLOOKUP($A9,PL.C!$B:$F,5,0) | F9: sim | G9: Budget | I9: 0 | J9: -666 | K9: 0 | L9: -224 | M9: 0 | N9: -47 | O9: -870 | P9: -298 | Q9: -139 | R9: -199 | S9: -60 | T9: -898 | V9: -515 | W9: -274 | X9: -440 | Y9: -1154 | Z9: -431 | AA9: -249 | AB9: -181 | AC9: -196 | AD9: -174 | AE9: -346 | AF9: -127 | AG9: -312 | AI9: -323 | AJ9: -589 | AK9: -207 | AL9: -64 | AM9: -446 | AN9: -136 | AO9: -407 | AP9: -530 | AQ9: -96 | AR9: -287 | AS9: -1700 | AT9: -353 | AV9: -339.796 | AW9: -619.628 | AX9: -217.764 | AY9: -67.328 | AZ9: -469.192 | BA9: -143.072 | BB9: -188.308 | BC9: -499.7 | BD9: -100.992 | BE9: -301.924 | BF9: -1788.4 | BG9: -371.356 | BI9: 1.05 | BJ9: -719.25 | BK9: -1050 | BL9: -1641.15 | BM9: -353.85 | BN9: -680.4 | BO9: -1729.35 | BP9: -417.9 | BQ9: -99.75 | BR9: -3006.15 | BS9: -192.15 | BT9: -753.9 | BU9: -2149.35 | BW9: =_xlfn.XLOOKUP($A9,$A$203:$A$399,BJ$203:BJ$399,"Não Existe")*$BI9 | BX9: =_xlfn.SINGLE(_xlfn.XLOOKUP($A9,$A$203:$A$399,BK$203:BK$399,"Não Existe"))*$BI9 | BY9: =_xlfn.SINGLE(_xlfn.XLOOKUP($A9,$A$203:$A$399,BL$203:BL$399,"Não Existe"))*$BI9 | BZ9: =_xlfn.SINGLE(_xlfn.XLOOKUP($A9,$A$203:$A$399,BM$203:BM$399,"Não Existe"))*$BI9 | CA9: =_xlfn.SINGLE(_xlfn.XLOOKUP($A9,$A$203:$A$399,BN$203:BN$399,"Não Existe"))*$BI9 | CB9: =_xlfn.SINGLE(_xlfn.XLOOKUP($A9,$A$203:$A$399,BO$203:BO$399,"Não Existe"))*$BI9 | CC9: =_xlfn.SINGLE(_xlfn.XLOOKUP($A9,$A$203:$A$399,BP$203:BP$399,"Não Existe"))*$BI9 | CD9: =_xlfn.SINGLE(_xlfn.XLOOKUP($A9,$A$203:$A$399,BQ$203:BQ$399,"Não Existe"))*$BI9 | CE9: =_xlfn.SINGLE(_xlfn.XLOOKUP($A9,$A$203:$A$399,BR$203:BR$399,"Não Existe"))*$BI9 | ... CH9: =_xlfn.SINGLE(_xlfn.XLOOKUP($A9,$A$203:$A$399,BU$203:BU$399,"Não Existe"))*$BI9
A10: 10.07 | B10: Adiantamento de despesas Clientes | C10: Analítica | D10: Saída | E10: Dedução da Receita | F10: sim | G10: Budget | I10: 0 | J10: 0 | K10: 0 | L10: 0 | M10: 0 | N10: 0 | O10: 0 | P10: -441 | Q10: 0 | R10: 0 | S10: 0 | T10: 0 | V10: 0 | W10: 0 | X10: 0 | Y10: 0 | Z10: 0 | AA10: 0 | AB10: 0 | AC10: 0 | AD10: 0 | AE10: 0 | AF10: 0 | AG10: 0 | AI10: 0 | AJ10: 0 | AK10: 0 | AL10: 0 | AM10: 0 | AN10: 0 | AO10: 0 | AP10: 0 | AQ10: 0 | AR10: 0 | AS10: 0 | AT10: 0 | AV10: 0 | AW10: 0 | AX10: 0 | AY10: 0 | AZ10: 0 | BA10: 0 | BB10: 0 | BC10: 0 | BD10: 0 | BE10: 0 | BF10: 0 | BG10: 0 | BI10: 1.05 | BJ10: 0 | BK10: 0 | BL10: 0 | BM10: 0 | BN10: 0 | BO10: 0 | BP10: 0 | BQ10: 0 | BR10: 0 | BS10: 0 | BT10: 0 | BU10: 0 | BW10: =_xlfn.SINGLE(_xlfn.XLOOKUP($A10,$A$203:$A$399,BJ$203:BJ$399,"Não Existe"))*$BI10 | BX10: =_xlfn.SINGLE(_xlfn.XLOOKUP($A10,$A$203:$A$399,BK$203:BK$399,"Não Existe"))*$BI10 | BY10: =_xlfn.SINGLE(_xlfn.XLOOKUP($A10,$A$203:$A$399,BL$203:BL$399,"Não Existe"))*$BI10 | BZ10: =_xlfn.SINGLE(_xlfn.XLOOKUP($A10,$A$203:$A$399,BM$203:BM$399,"Não Existe"))*$BI10 | CA10: =_xlfn.SINGLE(_xlfn.XLOOKUP($A10,$A$203:$A$399,BN$203:BN$399,"Não Existe"))*$BI10 | CB10: =_xlfn.SINGLE(_xlfn.XLOOKUP($A10,$A$203:$A$399,BO$203:BO$399,"Não Existe"))*$BI10 | CC10: =_xlfn.SINGLE(_xlfn.XLOOKUP($A10,$A$203:$A$399,BP$203:BP$399,"Não Existe"))*$BI10 | CD10: =_xlfn.SINGLE(_xlfn.XLOOKUP($A10,$A$203:$A$399,BQ$203:BQ$399,"Não Existe"))*$BI10 | ... CH10: =_xlfn.SINGLE(_xlfn.XLOOKUP($A10,$A$203:$A$399,BU$203:BU$399,"Não Existe"))*$BI10
A11: 10.08 | B11: Devolução de Recebimento | C11: Analítica | D11: Saída | E11: Dedução da Receita | F11: sim | G11: Budget | I11: 0 | J11: 0 | K11: 0 | L11: 0 | M11: 0 | N11: 0 | O11: 0 | P11: 0 | Q11: 0 | R11: 0 | S11: 0 | T11: 0 | V11: 0 | W11: 0 | X11: 0 | Y11: 0 | Z11: 0 | AA11: 0 | AB11: 0 | AC11: 0 | AD11: 0 | AE11: 0 | AF11: 0 | AG11: 0 | AI11: 0 | AJ11: 0 | AK11: -5708 | AL11: 0 | AM11: 0 | AN11: 0 | AO11: 0 | AP11: 0 | AQ11: 0 | AR11: 0 | AS11: -43 | AT11: 0 | AV11: 0 | AW11: 0 | AX11: -6004.816 | AY11: 0 | AZ11: 0 | BA11: 0 | BB11: -239.856 | BC11: -56.808 | BD11: 0 | BE11: 0 | BF11: -45.236 | BG11: 0 | BI11: 1.05 | BJ11: 0 | BK11: -846.3 | BL11: 0 | BM11: 0 | BN11: 0 | BO11: 0 | BP11: 0 | BQ11: 0 | BR11: 0 | BS11: -37.8 | BT11: 0 | BU11: -1863.75 | BW11: =_xlfn.SINGLE(_xlfn.XLOOKUP($A11,$A$203:$A$399,BJ$203:BJ$399,"Não Existe"))*$BI11 | BX11: =_xlfn.SINGLE(_xlfn.XLOOKUP($A11,$A$203:$A$399,BK$203:BK$399,"Não Existe"))*$BI11 | BY11: =_xlfn.SINGLE(_xlfn.XLOOKUP($A11,$A$203:$A$399,BL$203:BL$399,"Não Existe"))*$BI11 | BZ11: =_xlfn.SINGLE(_xlfn.XLOOKUP($A11,$A$203:$A$399,BM$203:BM$399,"Não Existe"))*$BI11 | CA11: =_xlfn.SINGLE(_xlfn.XLOOKUP($A11,$A$203:$A$399,BN$203:BN$399,"Não Existe"))*$BI11 | CB11: =_xlfn.SINGLE(_xlfn.XLOOKUP($A11,$A$203:$A$399,BO$203:BO$399,"Não Existe"))*$BI11 | CC11: =_xlfn.SINGLE(_xlfn.XLOOKUP($A11,$A$203:$A$399,BP$203:BP$399,"Não Existe"))*$BI11 | CD11: =_xlfn.SINGLE(_xlfn.XLOOKUP($A11,$A$203:$A$399,BQ$203:BQ$399,"Não Existe"))*$BI11 | ... CH11: =_xlfn.SINGLE(_xlfn.XLOOKUP($A11,$A$203:$A$399,BU$203:BU$399,"Não Existe"))*$BI11
A12: 20.01 | B12: ICMS | C12: Analítica | D12: Saída | E12: =VLOOKUP($A12,PL.C!$B:$F,5,0) | F12: sim | G12: Budget | I12: 0 | J12: 0 | K12: 0 | L12: -17145 | M12: -40272 | N12: -11766 | O12: -25370 | P12: -35444 | Q12: -23590 | R12: -13045 | S12: -24365 | T12: -13572 | V12: 0 | W12: -96 | X12: -96 | Y12: -112 | Z12: -13864 | AA12: -21137 | AB12: -26746 | AC12: -1262 | AD12: -14899 | AE12: -18945 | AF12: -16601 | AG12: 0 | AI12: -3105 | AJ12: -10384 | AK12: -28789 | AL12: 0 | AM12: -13909 | AN12: -13163 | AO12: -22284 | AP12: -8500 | AQ12: -17373 | AR12: -23021 | AS12: -8071 | AT12: -22326 | AV12: -16896.073 | AW12: -16642.454 | AX12: -24955.306 | AY12: -20038.135 | AZ12: -22871.099 | BA12: -23387.503 | BB12: -22981.286 | BC12: -24375.265 | BD12: -22124.896 | BE12: -22412.828 | BF12: -24610.252 | BG12: -24106.203 | BI12: 1.05 | BJ12: 0 | BK12: 0 | BL12: -10924.2 | BM12: -17547.6 | BN12: -14997.15 | BO12: -12255.6 | BP12: -17153.85 | BQ12: -28227.15 | BR12: -18285.75 | BS12: -21949.2 | BT12: -30508.8 | BU12: -10021.2 | BW12: =_xlfn.SINGLE(_xlfn.XLOOKUP($A12,$A$203:$A$399,BJ$203:BJ$399,"Não Existe"))*$BI12 | BX12: =_xlfn.SINGLE(_xlfn.XLOOKUP($A12,$A$203:$A$399,BK$203:BK$399,"Não Existe"))*$BI12 | BY12: =_xlfn.SINGLE(_xlfn.XLOOKUP($A12,$A$203:$A$399,BL$203:BL$399,"Não Existe"))*$BI12 | BZ12: =_xlfn.SINGLE(_xlfn.XLOOKUP($A12,$A$203:$A$399,BM$203:BM$399,"Não Existe"))*$BI12 | CA12: =_xlfn.SINGLE(_xlfn.XLOOKUP($A12,$A$203:$A$399,BN$203:BN$399,"Não Existe"))*$BI12 | CB12: =_xlfn.SINGLE(_xlfn.XLOOKUP($A12,$A$203:$A$399,BO$203:BO$399,"Não Existe"))*$BI12 | CC12: =_xlfn.SINGLE(_xlfn.XLOOKUP($A12,$A$203:$A$399,BP$203:BP$399,"Não Existe"))*$BI12 | CD12: =_xlfn.SINGLE(_xlfn.XLOOKUP($A12,$A$203:$A$399,BQ$203:BQ$399,"Não Existe"))*$BI12 | ... CH12: =_xlfn.SINGLE(_xlfn.XLOOKUP($A12,$A$203:$A$399,BU$203:BU$399,"Não Existe"))*$BI12
A13: 20.04 | B13: ST | C13: Analítica | D13: Saída | E13: =VLOOKUP($A13,PL.C!$B:$F,5,0) | F13: sim | G13: Budget | I13: 0 | J13: 0 | K13: 0 | L13: -35059 | M13: -30798 | N13: -41380 | O13: -38287 | P13: -44424 | Q13: -31023 | R13: -34511 | S13: -30476 | T13: -35359 | V13: -34259 | W13: -33077 | X13: -40001 | Y13: -37496 | Z13: -37077 | AA13: -43596 | AB13: -37086 | AC13: -46579 | AD13: -34604 | AE13: -37097 | AF13: -36170 | AG13: -33113 | AI13: -36801 | AJ13: -34023 | AK13: -29305 | AL13: -37253 | AM13: -37806 | AN13: -38873 | AO13: -41015 | AP13: -47607 | AQ13: -35633 | AR13: -38523 | AS13: -37403 | AT13: -37766 | AV13: -38714.652 | AW13: -35792.196 | AX13: -30828.86 | AY13: -39190.156 | AZ13: -39771.912 | BA13: -40894.396 | BB13: -43147.78 | BC13: -50082.564 | BD13: -37485.916 | BE13: -40526.196 | BF13: -39347.956 | BG13: -39729.832 | BI13: 1.05 | BJ13: -47378.1 | BK13: -41410.95 | BL13: -44462.25 | BM13: -43798.65 | BN13: -43013.25 | BO13: -52634.4 | BP13: -61463.85 | BQ13: -49513.8 | BR13: -54588.45 | BS13: -57379.35 | BT13: -52515.75 | BU13: -49901.25 | BW13: =_xlfn.SINGLE(_xlfn.XLOOKUP($A13,$A$203:$A$399,BJ$203:BJ$399,"Não Existe"))*$BI13 | BX13: =_xlfn.SINGLE(_xlfn.XLOOKUP($A13,$A$203:$A$399,BK$203:BK$399,"Não Existe"))*$BI13 | BY13: =_xlfn.SINGLE(_xlfn.XLOOKUP($A13,$A$203:$A$399,BL$203:BL$399,"Não Existe"))*$BI13 | BZ13: =_xlfn.SINGLE(_xlfn.XLOOKUP($A13,$A$203:$A$399,BM$203:BM$399,"Não Existe"))*$BI13 | CA13: =_xlfn.SINGLE(_xlfn.XLOOKUP($A13,$A$203:$A$399,BN$203:BN$399,"Não Existe"))*$BI13 | CB13: =_xlfn.SINGLE(_xlfn.XLOOKUP($A13,$A$203:$A$399,BO$203:BO$399,"Não Existe"))*$BI13 | CC13: =_xlfn.SINGLE(_xlfn.XLOOKUP($A13,$A$203:$A$399,BP$203:BP$399,"Não Existe"))*$BI13 | CD13: =_xlfn.SINGLE(_xlfn.XLOOKUP($A13,$A$203:$A$399,BQ$203:BQ$399,"Não Existe"))*$BI13 | ... CH13: =_xlfn.SINGLE(_xlfn.XLOOKUP($A13,$A$203:$A$399,BU$203:BU$399,"Não Existe"))*$BI13
A14: 20.05 | B14: DIFAL | C14: Analítica | D14: Saída | E14: Dedução da Receita | F14: sim | G14: Budget | I14: 0 | J14: 0 | K14: 0 | L14: 0 | M14: 0 | N14: 0 | O14: 0 | P14: -199 | Q14: -199 | R14: -199 | S14: 0 | T14: 0 | V14: 0 | W14: 0 | X14: 0 | Y14: 0 | Z14: 0 | AA14: 0 | AB14: 0 | AC14: 0 | AD14: 0 | AE14: 0 | AF14: 0 | AG14: 0 | AI14: 0 | AJ14: 0 | AK14: 0 | AL14: 0 | AM14: 0 | AN14: 0 | AO14: 0 | AP14: 0 | AQ14: 0 | AR14: 0 | AS14: 0 | AT14: 0 | AV14: 0 | AW14: 0 | AX14: 0 | AY14: 0 | AZ14: 0 | BA14: 0 | BB14: 0 | BC14: 0 | BD14: 0 | BE14: 0 | BF14: 0 | BG14: 0 | BI14: 1.05 | BJ14: 0 | BK14: 0 | BL14: 0 | BM14: 0 | BN14: 0 | BO14: 0 | BP14: 0 | BQ14: 0 | BR14: 0 | BS14: 0 | BT14: 0 | BU14: 0 | BW14: =_xlfn.SINGLE(_xlfn.XLOOKUP($A14,$A$203:$A$399,BJ$203:BJ$399,"Não Existe"))*$BI14 | BX14: =_xlfn.SINGLE(_xlfn.XLOOKUP($A14,$A$203:$A$399,BK$203:BK$399,"Não Existe"))*$BI14 | BY14: =_xlfn.SINGLE(_xlfn.XLOOKUP($A14,$A$203:$A$399,BL$203:BL$399,"Não Existe"))*$BI14 | BZ14: =_xlfn.SINGLE(_xlfn.XLOOKUP($A14,$A$203:$A$399,BM$203:BM$399,"Não Existe"))*$BI14 | CA14: =_xlfn.SINGLE(_xlfn.XLOOKUP($A14,$A$203:$A$399,BN$203:BN$399,"Não Existe"))*$BI14 | CB14: =_xlfn.SINGLE(_xlfn.XLOOKUP($A14,$A$203:$A$399,BO$203:BO$399,"Não Existe"))*$BI14 | CC14: =_xlfn.SINGLE(_xlfn.XLOOKUP($A14,$A$203:$A$399,BP$203:BP$399,"Não Existe"))*$BI14 | CD14: =_xlfn.SINGLE(_xlfn.XLOOKUP($A14,$A$203:$A$399,BQ$203:BQ$399,"Não Existe"))*$BI14 | ... CH14: =_xlfn.SINGLE(_xlfn.XLOOKUP($A14,$A$203:$A$399,BU$203:BU$399,"Não Existe"))*$BI14
A15: 21.01 | B15: ICMS | C15: Analítica | D15: Entrada | E15: =VLOOKUP($A15,PL.C!$B:$F,5,0) | F15: sim | G15: Budget | I15: 0 | J15: 0 | K15: 0 | L15: 0 | M15: 0 | N15: 0 | O15: 0 | P15: 0 | Q15: 0 | R15: 0 | S15: 0 | T15: 0 | V15: 0 | W15: 0 | X15: 0 | Y15: 0 | Z15: 0 | AA15: 0 | AB15: 0 | AC15: 0 | AD15: 0 | AE15: 0 | AF15: 0 | AG15: 0 | AI15: 0 | AJ15: 0 | AK15: 0 | AL15: 0 | AM15: 0 | AN15: 0 | AO15: 0 | AP15: 0 | AQ15: 0 | AR15: 0 | AS15: 0 | AT15: 0 | AV15: 0 | AW15: 0 | AX15: 0 | AY15: 0 | AZ15: 0 | BA15: 0 | BB15: 0 | BC15: 0 | BD15: 0 | BE15: 0 | BF15: 0 | BG15: 0 | BI15: 1.05 | BJ15: 0 | BK15: 0 | BL15: 0 | BM15: 0 | BN15: 0 | BO15: 0 | BP15: 0 | BQ15: 0 | BR15: 0 | BS15: 0 | BT15: 0 | BU15: 0 | BW15: =_xlfn.SINGLE(_xlfn.XLOOKUP($A15,$A$203:$A$399,BJ$203:BJ$399,"Não Existe"))*$BI15 | BX15: =_xlfn.SINGLE(_xlfn.XLOOKUP($A15,$A$203:$A$399,BK$203:BK$399,"Não Existe"))*$BI15 | BY15: =_xlfn.SINGLE(_xlfn.XLOOKUP($A15,$A$203:$A$399,BL$203:BL$399,"Não Existe"))*$BI15 | BZ15: =_xlfn.SINGLE(_xlfn.XLOOKUP($A15,$A$203:$A$399,BM$203:BM$399,"Não Existe"))*$BI15 | CA15: =_xlfn.SINGLE(_xlfn.XLOOKUP($A15,$A$203:$A$399,BN$203:BN$399,"Não Existe"))*$BI15 | CB15: =_xlfn.SINGLE(_xlfn.XLOOKUP($A15,$A$203:$A$399,BO$203:BO$399,"Não Existe"))*$BI15 | CC15: =_xlfn.SINGLE(_xlfn.XLOOKUP($A15,$A$203:$A$399,BP$203:BP$399,"Não Existe"))*$BI15 | CD15: =_xlfn.SINGLE(_xlfn.XLOOKUP($A15,$A$203:$A$399,BQ$203:BQ$399,"Não Existe"))*$BI15 | ... CH15: =_xlfn.SINGLE(_xlfn.XLOOKUP($A15,$A$203:$A$399,BU$203:BU$399,"Não Existe"))*$BI15
A16: 21.02 | B16: IPI | C16: Analítica | D16: Entrada | E16: =VLOOKUP($A16,PL.C!$B:$F,5,0) | F16: sim | G16: Budget | I16: 0 | J16: 0 | K16: 0 | L16: 0 | M16: 0 | N16: 0 | O16: 0 | P16: 0 | Q16: 0 | R16: 0 | S16: 0 | T16: 0 | V16: 0 | W16: 0 | X16: 0 | Y16: 0 | Z16: 0 | AA16: 0 | AB16: 0 | AC16: 0 | AD16: 0 | AE16: 0 | AF16: 0 | AG16: 0 | AI16: 0 | AJ16: 0 | AK16: 0 | AL16: 0 | AM16: 0 | AN16: 0 | AO16: 0 | AP16: 0 | AQ16: 0 | AR16: 0 | AS16: 0 | AT16: 0 | AV16: 0 | AW16: 0 | AX16: 0 | AY16: 0 | AZ16: 0 | BA16: 0 | BB16: 0 | BC16: 0 | BD16: 0 | BE16: 0 | BF16: 0 | BG16: 0 | BI16: 1.05 | BJ16: 0 | BK16: 0 | BL16: 0 | BM16: 0 | BN16: 0 | BO16: 0 | BP16: 0 | BQ16: 0 | BR16: 0 | BS16: 0 | BT16: 0 | BU16: 0 | BW16: =_xlfn.SINGLE(_xlfn.XLOOKUP($A16,$A$203:$A$399,BJ$203:BJ$399,"Não Existe"))*$BI16 | BX16: =_xlfn.SINGLE(_xlfn.XLOOKUP($A16,$A$203:$A$399,BK$203:BK$399,"Não Existe"))*$BI16 | BY16: =_xlfn.SINGLE(_xlfn.XLOOKUP($A16,$A$203:$A$399,BL$203:BL$399,"Não Existe"))*$BI16 | BZ16: =_xlfn.SINGLE(_xlfn.XLOOKUP($A16,$A$203:$A$399,BM$203:BM$399,"Não Existe"))*$BI16 | CA16: =_xlfn.SINGLE(_xlfn.XLOOKUP($A16,$A$203:$A$399,BN$203:BN$399,"Não Existe"))*$BI16 | CB16: =_xlfn.SINGLE(_xlfn.XLOOKUP($A16,$A$203:$A$399,BO$203:BO$399,"Não Existe"))*$BI16 | CC16: =_xlfn.SINGLE(_xlfn.XLOOKUP($A16,$A$203:$A$399,BP$203:BP$399,"Não Existe"))*$BI16 | CD16: =_xlfn.SINGLE(_xlfn.XLOOKUP($A16,$A$203:$A$399,BQ$203:BQ$399,"Não Existe"))*$BI16 | ... CH16: =_xlfn.SINGLE(_xlfn.XLOOKUP($A16,$A$203:$A$399,BU$203:BU$399,"Não Existe"))*$BI16
A17: 21.03 | B17: ISS | C17: Analítica | D17: Entrada | E17: =VLOOKUP($A17,PL.C!$B:$F,5,0) | F17: sim | G17: Budget | I17: 0 | J17: 0 | K17: 0 | L17: 0 | M17: 0 | N17: 0 | O17: 0 | P17: 0 | Q17: 0 | R17: 0 | S17: 0 | T17: 0 | V17: 0 | W17: 0 | X17: 0 | Y17: 0 | Z17: 0 | AA17: 0 | AB17: 0 | AC17: 0 | AD17: 0 | AE17: 0 | AF17: 0 | AG17: 0 | AI17: 0 | AJ17: 0 | AK17: 0 | AL17: 0 | AM17: 0 | AN17: 0 | AO17: 0 | AP17: 0 | AQ17: 0 | AR17: 0 | AS17: 0 | AT17: 0 | AV17: 0 | AW17: 0 | AX17: 0 | AY17: 0 | AZ17: 0 | BA17: 0 | BB17: 0 | BC17: 0 | BD17: 0 | BE17: 0 | BF17: 0 | BG17: 0 | BI17: 1.05 | BJ17: 0 | BK17: 0 | BL17: 0 | BM17: 0 | BN17: 0 | BO17: 0 | BP17: 0 | BQ17: 0 | BR17: 0 | BS17: 0 | BT17: 0 | BU17: 0 | BW17: =_xlfn.SINGLE(_xlfn.XLOOKUP($A17,$A$203:$A$399,BJ$203:BJ$399,"Não Existe"))*$BI17 | BX17: =_xlfn.SINGLE(_xlfn.XLOOKUP($A17,$A$203:$A$399,BK$203:BK$399,"Não Existe"))*$BI17 | BY17: =_xlfn.SINGLE(_xlfn.XLOOKUP($A17,$A$203:$A$399,BL$203:BL$399,"Não Existe"))*$BI17 | BZ17: =_xlfn.SINGLE(_xlfn.XLOOKUP($A17,$A$203:$A$399,BM$203:BM$399,"Não Existe"))*$BI17 | CA17: =_xlfn.SINGLE(_xlfn.XLOOKUP($A17,$A$203:$A$399,BN$203:BN$399,"Não Existe"))*$BI17 | CB17: =_xlfn.SINGLE(_xlfn.XLOOKUP($A17,$A$203:$A$399,BO$203:BO$399,"Não Existe"))*$BI17 | CC17: =_xlfn.SINGLE(_xlfn.XLOOKUP($A17,$A$203:$A$399,BP$203:BP$399,"Não Existe"))*$BI17 | CD17: =_xlfn.SINGLE(_xlfn.XLOOKUP($A17,$A$203:$A$399,BQ$203:BQ$399,"Não Existe"))*$BI17 | ... CH17: =_xlfn.SINGLE(_xlfn.XLOOKUP($A17,$A$203:$A$399,BU$203:BU$399,"Não Existe"))*$BI17
A18: 22.01 | B18: Repasse Distribuidores | C18: Analítica | D18: Saída | E18: =VLOOKUP($A18,PL.C!$B:$F,5,0) | F18: sim | G18: Budget | I18: 0 | J18: 0 | K18: 0 | L18: 0 | M18: -3638 | N18: -5703 | O18: -9759 | P18: -8530 | Q18: -7664 | R18: -10049 | S18: -8512 | T18: -8996 | V18: -9110 | W18: -9303 | X18: -10624 | Y18: -11355 | Z18: -8687 | AA18: -9074 | AB18: -11941 | AC18: -10053 | AD18: -13302 | AE18: -8302 | AF18: -8445 | AG18: -9682 | AI18: -10198 | AJ18: -11302 | AK18: -12459 | AL18: -9887 | AM18: -9844 | AN18: -7015 | AO18: -8369 | AP18: -4259 | AQ18: -5587 | AR18: -2795 | AS18: -2913 | AT18: -3183 | AV18: -10728.296 | AW18: -11889.704 | AX18: -13106.868 | AY18: -10401.124 | AZ18: -10355.888 | BA18: -7379.78 | BB18: -8804.188 | BC18: -4480.468 | BD18: -5877.524 | BE18: -2940.34 | BF18: -3064.476 | BG18: -3348.516 | BI18: 1.05 | BJ18: -3225.6 | BK18: -1289.4 | BL18: -4833.15 | BM18: -2663.85 | BN18: -525 | BO18: -3041.85 | BP18: -1912.05 | BQ18: -3277.05 | BR18: -771.75 | BS18: -1782.9 | BT18: -598.5 | BU18: -761.25 | BW18: =_xlfn.SINGLE(_xlfn.XLOOKUP($A18,$A$203:$A$399,BJ$203:BJ$399,"Não Existe"))*$BI18 | BX18: =_xlfn.SINGLE(_xlfn.XLOOKUP($A18,$A$203:$A$399,BK$203:BK$399,"Não Existe"))*$BI18 | BY18: =_xlfn.SINGLE(_xlfn.XLOOKUP($A18,$A$203:$A$399,BL$203:BL$399,"Não Existe"))*$BI18 | BZ18: =_xlfn.SINGLE(_xlfn.XLOOKUP($A18,$A$203:$A$399,BM$203:BM$399,"Não Existe"))*$BI18 | CA18: =_xlfn.SINGLE(_xlfn.XLOOKUP($A18,$A$203:$A$399,BN$203:BN$399,"Não Existe"))*$BI18 | CB18: =_xlfn.SINGLE(_xlfn.XLOOKUP($A18,$A$203:$A$399,BO$203:BO$399,"Não Existe"))*$BI18 | CC18: =_xlfn.SINGLE(_xlfn.XLOOKUP($A18,$A$203:$A$399,BP$203:BP$399,"Não Existe"))*$BI18 | CD18: =_xlfn.SINGLE(_xlfn.XLOOKUP($A18,$A$203:$A$399,BQ$203:BQ$399,"Não Existe"))*$BI18 | ... CH18: =_xlfn.SINGLE(_xlfn.XLOOKUP($A18,$A$203:$A$399,BU$203:BU$399,"Não Existe"))*$BI18
A19: 29.01 | B19: Salário líquido | C19: Analítica | D19: Saída | E19: =VLOOKUP($A19,PL.C!$B:$F,5,0) | F19: sim | G19: Budget | I19: 0 | J19: 0 | K19: 0 | L19: -46649 | M19: -82109 | N19: -83280 | O19: -52046 | P19: -50725 | Q19: -55318 | R19: -50980 | S19: -54279 | T19: -59238 | V19: -60514 | W19: -52381 | X19: -50287 | Y19: -48449 | Z19: -52967 | AA19: -55206 | AB19: -54213 | AC19: -49905 | AD19: -55517 | AE19: -52928 | AF19: -53237 | AG19: -76077 | AI19: -62756 | AJ19: -55514 | AK19: -53898 | AL19: -55008 | AM19: -56890 | AN19: -57893 | AO19: -57102 | AP19: -60049 | AQ19: -59562 | AR19: -57235 | AS19: -54569 | AT19: -57010 | AV19: -69031.6 | AW19: -61065.4 | AX19: -59287.8 | AY19: -60508.8 | AZ19: -62579 | BA19: -63682.3 | BB19: -62812.2 | BC19: -66053.9 | BD19: -65518.2 | BE19: -62958.5 | BF19: -60025.9 | BG19: -62711 | BI19: 1.1 | BJ19: -61710 | BK19: -91050.3 | BL19: -76434.6 | BM19: -67629.1 | BN19: -70059 | BO19: -71001.7 | BP19: -70081 | BQ19: -72475.7 | BR19: -77259.6 | BS19: -74771.4 | BT19: -71480.2 | BU19: -71594.6 | BW19: =_xlfn.SINGLE(_xlfn.XLOOKUP($A19,$A$203:$A$399,BJ$203:BJ$399,"Não Existe"))*$BI19 | BX19: =_xlfn.SINGLE(_xlfn.XLOOKUP($A19,$A$203:$A$399,BK$203:BK$399,"Não Existe"))*$BI19 | BY19: =_xlfn.SINGLE(_xlfn.XLOOKUP($A19,$A$203:$A$399,BL$203:BL$399,"Não Existe"))*$BI19 | BZ19: =_xlfn.SINGLE(_xlfn.XLOOKUP($A19,$A$203:$A$399,BM$203:BM$399,"Não Existe"))*$BI19 | CA19: =_xlfn.SINGLE(_xlfn.XLOOKUP($A19,$A$203:$A$399,BN$203:BN$399,"Não Existe"))*$BI19 | CB19: =_xlfn.SINGLE(_xlfn.XLOOKUP($A19,$A$203:$A$399,BO$203:BO$399,"Não Existe"))*$BI19 | CC19: =_xlfn.SINGLE(_xlfn.XLOOKUP($A19,$A$203:$A$399,BP$203:BP$399,"Não Existe"))*$BI19 | CD19: =_xlfn.SINGLE(_xlfn.XLOOKUP($A19,$A$203:$A$399,BQ$203:BQ$399,"Não Existe"))*$BI19 | ... CH19: =_xlfn.SINGLE(_xlfn.XLOOKUP($A19,$A$203:$A$399,BU$203:BU$399,"Não Existe"))*$BI19
A20: 29.02 | B20: 13o salário | C20: Analítica | D20: Saída | E20: =VLOOKUP($A20,PL.C!$B:$F,5,0) | F20: sim | G20: Budget | I20: 0 | J20: 0 | K20: 0 | L20: 0 | M20: 0 | N20: 0 | O20: 0 | P20: 0 | Q20: -19039 | R20: -20971 | S20: -21279 | T20: -17739 | V20: 0 | W20: 0 | X20: -1989 | Y20: 0 | Z20: -1600 | AA20: 0 | AB20: 0 | AC20: 0 | AD20: -20005 | AE20: -20005 | AF20: -20005 | AG20: -23346 | AI20: 0 | AJ20: 0 | AK20: 0 | AL20: 0 | AM20: -1351 | AN20: 0 | AO20: 0 | AP20: 0 | AQ20: -19734 | AR20: -20550 | AS20: -21089 | AT20: -13739 | AV20: 0 | AW20: 0 | AX20: 0 | AY20: 0 | AZ20: -1486.1 | BA20: 0 | BB20: 0 | BC20: 0 | BD20: -21707.4 | BE20: -22605 | BF20: -23197.9 | BG20: -15112.9 | BI20: 1.1 | BJ20: 0 | BK20: -2608.1 | BL20: 0 | BM20: 0 | BN20: 0 | BO20: 0 | BP20: -4062.3 | BQ20: 0 | BR20: -22825 | BS20: -23474 | BT20: -24260.5 | BU20: -24895.2 | BW20: =_xlfn.SINGLE(_xlfn.XLOOKUP($A20,$A$203:$A$399,BJ$203:BJ$399,"Não Existe"))*$BI20 | BX20: =_xlfn.SINGLE(_xlfn.XLOOKUP($A20,$A$203:$A$399,BK$203:BK$399,"Não Existe"))*$BI20 | BY20: =_xlfn.SINGLE(_xlfn.XLOOKUP($A20,$A$203:$A$399,BL$203:BL$399,"Não Existe"))*$BI20 | BZ20: =_xlfn.SINGLE(_xlfn.XLOOKUP($A20,$A$203:$A$399,BM$203:BM$399,"Não Existe"))*$BI20 | CA20: =_xlfn.SINGLE(_xlfn.XLOOKUP($A20,$A$203:$A$399,BN$203:BN$399,"Não Existe"))*$BI20 | CB20: =_xlfn.SINGLE(_xlfn.XLOOKUP($A20,$A$203:$A$399,BO$203:BO$399,"Não Existe"))*$BI20 | CC20: =_xlfn.SINGLE(_xlfn.XLOOKUP($A20,$A$203:$A$399,BP$203:BP$399,"Não Existe"))*$BI20 | CD20: =_xlfn.SINGLE(_xlfn.XLOOKUP($A20,$A$203:$A$399,BQ$203:BQ$399,"Não Existe"))*$BI20 | ... CH20: =_xlfn.SINGLE(_xlfn.XLOOKUP($A20,$A$203:$A$399,BU$203:BU$399,"Não Existe"))*$BI20
A21: 29.03 | B21: Férias | C21: Analítica | D21: Saída | E21: =VLOOKUP($A21,PL.C!$B:$F,5,0) | F21: sim | G21: Budget | I21: 0 | J21: -70 | K21: 0 | L21: -8358 | M21: -4706 | N21: -4421 | O21: -13272 | P21: -1932 | Q21: -5966 | R21: -11314 | S21: -4033 | T21: -3973 | V21: -21164 | W21: -15633 | X21: -12387 | Y21: -6140 | Z21: -5814 | AA21: -4322 | AB21: -9678 | AC21: -1989 | AD21: -6139 | AE21: -10120 | AF21: -10120 | AG21: -7052 | AI21: -11195 | AJ21: -16851 | AK21: -16093 | AL21: -4535 | AM21: -3072 | AN21: -4747 | AO21: -3859 | AP21: -2175 | AQ21: -6339 | AR21: -10219 | AS21: -6721 | AT21: -6547 | AV21: -12314.5 | AW21: -18536.1 | AX21: -17702.3 | AY21: -4988.5 | AZ21: -3379.2 | BA21: -5221.7 | BB21: -4244.9 | BC21: -2392.5 | BD21: -6972.9 | BE21: -11240.9 | BF21: -7393.1 | BG21: -7201.7 | BI21: 1.1 | BJ21: -14825.8 | BK21: -14831.3 | BL21: -10706.3 | BM21: -13510.2 | BN21: -3638.8 | BO21: -4829 | BP21: -10247.6 | BQ21: -2632.3 | BR21: -2860 | BS21: -8132.3 | BT21: -8132.3 | BU21: -2777.5 | BW21: =_xlfn.SINGLE(_xlfn.XLOOKUP($A21,$A$203:$A$399,BJ$203:BJ$399,"Não Existe"))*$BI21 | BX21: =_xlfn.SINGLE(_xlfn.XLOOKUP($A21,$A$203:$A$399,BK$203:BK$399,"Não Existe"))*$BI21 | BY21: =_xlfn.SINGLE(_xlfn.XLOOKUP($A21,$A$203:$A$399,BL$203:BL$399,"Não Existe"))*$BI21 | BZ21: =_xlfn.SINGLE(_xlfn.XLOOKUP($A21,$A$203:$A$399,BM$203:BM$399,"Não Existe"))*$BI21 | CA21: =_xlfn.SINGLE(_xlfn.XLOOKUP($A21,$A$203:$A$399,BN$203:BN$399,"Não Existe"))*$BI21 | CB21: =_xlfn.SINGLE(_xlfn.XLOOKUP($A21,$A$203:$A$399,BO$203:BO$399,"Não Existe"))*$BI21 | CC21: =_xlfn.SINGLE(_xlfn.XLOOKUP($A21,$A$203:$A$399,BP$203:BP$399,"Não Existe"))*$BI21 | CD21: =_xlfn.SINGLE(_xlfn.XLOOKUP($A21,$A$203:$A$399,BQ$203:BQ$399,"Não Existe"))*$BI21 | ... CH21: =_xlfn.SINGLE(_xlfn.XLOOKUP($A21,$A$203:$A$399,BU$203:BU$399,"Não Existe"))*$BI21
A22: 29.04 | B22: Rescisão | C22: Analítica | D22: Saída | E22: =VLOOKUP($A22,PL.C!$B:$F,5,0) | F22: sim | G22: Budget | I22: 0 | J22: 0 | K22: 0 | L22: -4968 | M22: 0 | N22: 0 | O22: -3470 | P22: 0 | Q22: -8 | R22: 0 | S22: 0 | T22: 0 | V22: -2450 | W22: -3756 | X22: 0 | Y22: 0 | Z22: 0 | AA22: 0 | AB22: -2760 | AC22: 0 | AD22: 0 | AE22: 0 | AF22: 0 | AG22: -4074 | AI22: -2866 | AJ22: 0 | AK22: -7934 | AL22: -4512 | AM22: -1204 | AN22: -3655 | AO22: -1279 | AP22: -160 | AQ22: 0 | AR22: 0 | AS22: 0 | AT22: -3997 | AV22: -3152.6 | AW22: 0 | AX22: -8727.4 | AY22: -4963.2 | AZ22: -1324.4 | BA22: -4020.5 | BB22: -1406.9 | BC22: -176 | BD22: 0 | BE22: 0 | BF22: 0 | BG22: -4396.7 | BI22: 1.1 | BJ22: -11272.8 | BK22: -1377.2 | BL22: 0 | BM22: -8243.4 | BN22: 0 | BO22: -1356.3 | BP22: 0 | BQ22: -6806.8 | BR22: -6560.4 | BS22: -2767.6 | BT22: 0 | BU22: 0 | BW22: =_xlfn.SINGLE(_xlfn.XLOOKUP($A22,$A$203:$A$399,BJ$203:BJ$399,"Não Existe"))*$BI22 | BX22: =_xlfn.SINGLE(_xlfn.XLOOKUP($A22,$A$203:$A$399,BK$203:BK$399,"Não Existe"))*$BI22 | BY22: =_xlfn.SINGLE(_xlfn.XLOOKUP($A22,$A$203:$A$399,BL$203:BL$399,"Não Existe"))*$BI22 | BZ22: =_xlfn.SINGLE(_xlfn.XLOOKUP($A22,$A$203:$A$399,BM$203:BM$399,"Não Existe"))*$BI22 | CA22: =_xlfn.SINGLE(_xlfn.XLOOKUP($A22,$A$203:$A$399,BN$203:BN$399,"Não Existe"))*$BI22 | CB22: =_xlfn.SINGLE(_xlfn.XLOOKUP($A22,$A$203:$A$399,BO$203:BO$399,"Não Existe"))*$BI22 | CC22: =_xlfn.SINGLE(_xlfn.XLOOKUP($A22,$A$203:$A$399,BP$203:BP$399,"Não Existe"))*$BI22 | CD22: =_xlfn.SINGLE(_xlfn.XLOOKUP($A22,$A$203:$A$399,BQ$203:BQ$399,"Não Existe"))*$BI22 | ... CH22: =_xlfn.SINGLE(_xlfn.XLOOKUP($A22,$A$203:$A$399,BU$203:BU$399,"Não Existe"))*$BI22
A23: 29.05 | B23: Multa rescisória | C23: Analítica | D23: Saída | E23: =VLOOKUP($A23,PL.C!$B:$F,5,0) | F23: sim | G23: Budget | I23: 0 | J23: 0 | K23: 0 | L23: 0 | M23: 0 | N23: 0 | O23: 0 | P23: 0 | Q23: 0 | R23: 0 | S23: 0 | T23: 0 | V23: 0 | W23: -1381 | X23: 0 | Y23: 0 | Z23: 0 | AA23: 0 | AB23: -5050 | AC23: 0 | AD23: 0 | AE23: 0 | AF23: 0 | AG23: 0 | AI23: -2806 | AJ23: 0 | AK23: -6125 | AL23: -6776 | AM23: -52 | AN23: 0 | AO23: 0 | AP23: 0 | AQ23: 0 | AR23: 0 | AS23: 0 | AT23: -3606 | AV23: -3086.6 | AW23: 0 | AX23: -6737.5 | AY23: -7453.6 | AZ23: -57.2 | BA23: 0 | BB23: 0 | BC23: 0 | BD23: 0 | BE23: 0 | BF23: 0 | BG23: -3966.6 | BI23: 1.1 | BJ23: -7667 | BK23: 0 | BL23: 0 | BM23: -4466 | BN23: 0 | BO23: 0 | BP23: 0 | BQ23: 0 | BR23: -910.8 | BS23: 0 | BT23: 0 | BU23: 0 | BW23: =_xlfn.SINGLE(_xlfn.XLOOKUP($A23,$A$203:$A$399,BJ$203:BJ$399,"Não Existe"))*$BI23 | BX23: =_xlfn.SINGLE(_xlfn.XLOOKUP($A23,$A$203:$A$399,BK$203:BK$399,"Não Existe"))*$BI23 | BY23: =_xlfn.SINGLE(_xlfn.XLOOKUP($A23,$A$203:$A$399,BL$203:BL$399,"Não Existe"))*$BI23 | BZ23: =_xlfn.SINGLE(_xlfn.XLOOKUP($A23,$A$203:$A$399,BM$203:BM$399,"Não Existe"))*$BI23 | CA23: =_xlfn.SINGLE(_xlfn.XLOOKUP($A23,$A$203:$A$399,BN$203:BN$399,"Não Existe"))*$BI23 | CB23: =_xlfn.SINGLE(_xlfn.XLOOKUP($A23,$A$203:$A$399,BO$203:BO$399,"Não Existe"))*$BI23 | CC23: =_xlfn.SINGLE(_xlfn.XLOOKUP($A23,$A$203:$A$399,BP$203:BP$399,"Não Existe"))*$BI23 | CD23: =_xlfn.SINGLE(_xlfn.XLOOKUP($A23,$A$203:$A$399,BQ$203:BQ$399,"Não Existe"))*$BI23 | ... CH23: =_xlfn.SINGLE(_xlfn.XLOOKUP($A23,$A$203:$A$399,BU$203:BU$399,"Não Existe"))*$BI23
A24: 29.06 | B24: INSS | C24: Analítica | D24: Saída | E24: =VLOOKUP($A24,PL.C!$B:$F,5,0) | F24: sim | G24: Budget | I24: 0 | J24: 0 | K24: 0 | L24: -43510 | M24: -37129 | N24: -38920 | O24: -38389 | P24: -42139 | Q24: -40061 | R24: -39922 | S24: -39402 | T24: -76311 | V24: -41546 | W24: -42528 | X24: -42395 | Y24: -43329 | Z24: -41036 | AA24: -40139 | AB24: -40320 | AC24: -42679 | AD24: -40024 | AE24: -41900 | AF24: -40759 | AG24: -88709 | AI24: -44552 | AJ24: -44969 | AK24: -44735 | AL24: -44735 | AM24: -42671 | AN24: -43326 | AO24: -41133 | AP24: -42028 | AQ24: -39470 | AR24: -39731 | AS24: -39561 | AT24: -74868 | AV24: -49007.2 | AW24: -49465.9 | AX24: -49208.5 | AY24: -49208.5 | AZ24: -46938.1 | BA24: -47658.6 | BB24: -45246.3 | BC24: -46230.8 | BD24: -43417 | BE24: -43704.1 | BF24: -43517.1 | BG24: -82354.8 | BI24: 1.1 | BJ24: -45678.6 | BK24: -63573.4 | BL24: -56023 | BM24: -51086.2 | BN24: -50290.9 | BO24: -49613.3 | BP24: -49493.4 | BQ24: -52673.5 | BR24: -53428.1 | BS24: -52497.5 | BT24: -50725.4 | BU24: -93604.5 | BW24: =_xlfn.SINGLE(_xlfn.XLOOKUP($A24,$A$203:$A$399,BJ$203:BJ$399,"Não Existe"))*$BI24 | BX24: =_xlfn.SINGLE(_xlfn.XLOOKUP($A24,$A$203:$A$399,BK$203:BK$399,"Não Existe"))*$BI24 | BY24: =_xlfn.SINGLE(_xlfn.XLOOKUP($A24,$A$203:$A$399,BL$203:BL$399,"Não Existe"))*$BI24 | BZ24: =_xlfn.SINGLE(_xlfn.XLOOKUP($A24,$A$203:$A$399,BM$203:BM$399,"Não Existe"))*$BI24 | CA24: =_xlfn.SINGLE(_xlfn.XLOOKUP($A24,$A$203:$A$399,BN$203:BN$399,"Não Existe"))*$BI24 | CB24: =_xlfn.SINGLE(_xlfn.XLOOKUP($A24,$A$203:$A$399,BO$203:BO$399,"Não Existe"))*$BI24 | CC24: =_xlfn.SINGLE(_xlfn.XLOOKUP($A24,$A$203:$A$399,BP$203:BP$399,"Não Existe"))*$BI24 | CD24: =_xlfn.SINGLE(_xlfn.XLOOKUP($A24,$A$203:$A$399,BQ$203:BQ$399,"Não Existe"))*$BI24 | ... CH24: =_xlfn.SINGLE(_xlfn.XLOOKUP($A24,$A$203:$A$399,BU$203:BU$399,"Não Existe"))*$BI24
A25: 29.07 | B25: FGTS | C25: Analítica | D25: Saída | E25: =VLOOKUP($A25,PL.C!$B:$F,5,0) | F25: sim | G25: Budget | I25: 0 | J25: 0 | K25: 0 | L25: -13717 | M25: -6602 | N25: -6474 | O25: -12083 | P25: -7636 | Q25: -6891 | R25: -7255 | S25: -7095 | T25: -11650 | V25: -11817 | W25: -7065 | X25: -7208 | Y25: -7806 | Z25: -6848 | AA25: -6702 | AB25: -6936 | AC25: -7547 | AD25: -6492 | AE25: -7030 | AF25: -6861 | AG25: -13170 | AI25: -12528 | AJ25: -7499 | AK25: -7338 | AL25: -7914 | AM25: -7053 | AN25: -6752 | AO25: -7152 | AP25: -8090 | AQ25: -7132 | AR25: -7332 | AS25: -7143 | AT25: -11104 | AV25: -13780.8 | AW25: -8248.9 | AX25: -8071.8 | AY25: -8705.4 | AZ25: -7758.3 | BA25: -7427.2 | BB25: -7867.2 | BC25: -8899 | BD25: -7845.2 | BE25: -8065.2 | BF25: -7857.3 | BG25: -12214.4 | BI25: 1.1 | BJ25: -11719.4 | BK25: -11611.6 | BL25: -9865.9 | BM25: -8682.3 | BN25: -8720.8 | BO25: -8565.7 | BP25: -8597.6 | BQ25: -9051.9 | BR25: -9134.4 | BS25: -9084.9 | BT25: -9141 | BU25: -13610.3 | BW25: =_xlfn.SINGLE(_xlfn.XLOOKUP($A25,$A$203:$A$399,BJ$203:BJ$399,"Não Existe"))*$BI25 | BX25: =_xlfn.SINGLE(_xlfn.XLOOKUP($A25,$A$203:$A$399,BK$203:BK$399,"Não Existe"))*$BI25 | BY25: =_xlfn.SINGLE(_xlfn.XLOOKUP($A25,$A$203:$A$399,BL$203:BL$399,"Não Existe"))*$BI25 | BZ25: =_xlfn.SINGLE(_xlfn.XLOOKUP($A25,$A$203:$A$399,BM$203:BM$399,"Não Existe"))*$BI25 | CA25: =_xlfn.SINGLE(_xlfn.XLOOKUP($A25,$A$203:$A$399,BN$203:BN$399,"Não Existe"))*$BI25 | CB25: =_xlfn.SINGLE(_xlfn.XLOOKUP($A25,$A$203:$A$399,BO$203:BO$399,"Não Existe"))*$BI25 | CC25: =_xlfn.SINGLE(_xlfn.XLOOKUP($A25,$A$203:$A$399,BP$203:BP$399,"Não Existe"))*$BI25 | CD25: =_xlfn.SINGLE(_xlfn.XLOOKUP($A25,$A$203:$A$399,BQ$203:BQ$399,"Não Existe"))*$BI25 | ... CH25: =_xlfn.SINGLE(_xlfn.XLOOKUP($A25,$A$203:$A$399,BU$203:BU$399,"Não Existe"))*$BI25
A26: 29.08 | B26: IRRF | C26: Analítica | D26: Saída | E26: =VLOOKUP($A26,PL.C!$B:$F,5,0) | F26: sim | G26: Budget | I26: 0 | J26: 0 | K26: 0 | L26: -3145 | M26: -2674 | N26: -2727 | O26: -2763 | P26: -3344 | Q26: -2674 | R26: -2706 | S26: -2690 | T26: -3822 | V26: -1561 | W26: -1781 | X26: -2262 | Y26: -2660 | Z26: -1615 | AA26: -1658 | AB26: -1735 | AC26: -3001 | AD26: -1597 | AE26: -1639 | AF26: -1618 | AG26: -3943 | AI26: -2067 | AJ26: -2258 | AK26: -2698 | AL26: -3087 | AM26: -2025 | AN26: -2564 | AO26: -2018 | AP26: -3664 | AQ26: -1988 | AR26: -2065 | AS26: -2004 | AT26: -2048 | AV26: -2273.7 | AW26: -2483.8 | AX26: -2967.8 | AY26: -3395.7 | AZ26: -2227.5 | BA26: -2820.4 | BB26: -2219.8 | BC26: -4030.4 | BD26: -2186.8 | BE26: -2271.5 | BF26: -2204.4 | BG26: -2252.8 | BI26: 1.1 | BJ26: -4481.4 | BK26: -5255.8 | BL26: 0 | BM26: -6886 | BN26: -2751.1 | BO26: -2519 | BP26: -2359.5 | BQ26: -2359.5 | BR26: -2359.5 | BS26: -2417.8 | BT26: -2379.3 | BU26: -2379.3 | BW26: =_xlfn.SINGLE(_xlfn.XLOOKUP($A26,$A$203:$A$399,BJ$203:BJ$399,"Não Existe"))*$BI26 | BX26: =_xlfn.SINGLE(_xlfn.XLOOKUP($A26,$A$203:$A$399,BK$203:BK$399,"Não Existe"))*$BI26 | BY26: =_xlfn.SINGLE(_xlfn.XLOOKUP($A26,$A$203:$A$399,BL$203:BL$399,"Não Existe"))*$BI26 | BZ26: =_xlfn.SINGLE(_xlfn.XLOOKUP($A26,$A$203:$A$399,BM$203:BM$399,"Não Existe"))*$BI26 | CA26: =_xlfn.SINGLE(_xlfn.XLOOKUP($A26,$A$203:$A$399,BN$203:BN$399,"Não Existe"))*$BI26 | CB26: =_xlfn.SINGLE(_xlfn.XLOOKUP($A26,$A$203:$A$399,BO$203:BO$399,"Não Existe"))*$BI26 | CC26: =_xlfn.SINGLE(_xlfn.XLOOKUP($A26,$A$203:$A$399,BP$203:BP$399,"Não Existe"))*$BI26 | CD26: =_xlfn.SINGLE(_xlfn.XLOOKUP($A26,$A$203:$A$399,BQ$203:BQ$399,"Não Existe"))*$BI26 | ... CH26: =_xlfn.SINGLE(_xlfn.XLOOKUP($A26,$A$203:$A$399,BU$203:BU$399,"Não Existe"))*$BI26
... A44: 32.01 | B44: Locação de Máquinas e Equipamentos | C44: Analítica | D44: Saída | E44: =VLOOKUP($A44,PL.C!$B:$F,5,0) | F44: sim | G44: Budget | I44: 0 | J44: 0 | K44: 0 | L44: -3300 | M44: -3300 | N44: -3300 | O44: -3750 | P44: -3300 | Q44: -3300 | R44: -3300 | S44: -3300 | T44: -3300 | V44: -3300 | W44: -3300 | X44: -3300 | Y44: -3300 | Z44: 0 | AA44: -6600 | AB44: -3300 | AC44: -3300 | AD44: -3300 | AE44: -3300 | AF44: -3300 | AG44: -3300 | AI44: -3300 | AJ44: -3300 | AK44: -3300 | AL44: -3350 | AM44: -3300 | AN44: -3300 | AO44: -3300 | AP44: -3300 | AQ44: -3300 | AR44: -3300 | AS44: -3300 | AT44: -3300 | AV44: -3471.6 | AW44: -3471.6 | AX44: -3471.6 | AY44: -3524.2 | AZ44: -3471.6 | BA44: -3471.6 | BB44: -3471.6 | BC44: -3471.6 | BD44: -3471.6 | BE44: -3471.6 | BF44: -3471.6 | BG44: -3471.6 | BI44: 1.05 | BJ44: -3465 | BK44: -3638.25 | BL44: -3638.25 | BM44: -3638.25 | BN44: -3638.25 | BO44: -3638.25 | BP44: -3638.25 | BQ44: -3638.25 | BR44: -3638.25 | BS44: -3638.25 | BT44: -3638.25 | BU44: -3963.75 | BW44: =_xlfn.SINGLE(_xlfn.XLOOKUP($A44,$A$203:$A$399,BJ$203:BJ$399,"Não Existe"))*$BI44 | BX44: =_xlfn.SINGLE(_xlfn.XLOOKUP($A44,$A$203:$A$399,BK$203:BK$399,"Não Existe"))*$BI44 | BY44: =_xlfn.SINGLE(_xlfn.XLOOKUP($A44,$A$203:$A$399,BL$203:BL$399,"Não Existe"))*$BI44 | BZ44: =_xlfn.SINGLE(_xlfn.XLOOKUP($A44,$A$203:$A$399,BM$203:BM$399,"Não Existe"))*$BI44 | CA44: =_xlfn.SINGLE(_xlfn.XLOOKUP($A44,$A$203:$A$399,BN$203:BN$399,"Não Existe"))*$BI44 | CB44: =_xlfn.SINGLE(_xlfn.XLOOKUP($A44,$A$203:$A$399,BO$203:BO$399,"Não Existe"))*$BI44 | CC44: =_xlfn.SINGLE(_xlfn.XLOOKUP($A44,$A$203:$A$399,BP$203:BP$399,"Não Existe"))*$BI44 | CD44: =_xlfn.SINGLE(_xlfn.XLOOKUP($A44,$A$203:$A$399,BQ$203:BQ$399,"Não Existe"))*$BI44 | ... CH44: =_xlfn.SINGLE(_xlfn.XLOOKUP($A44,$A$203:$A$399,BU$203:BU$399,"Não Existe"))*$BI44
A45: 32.02 | B45: Aluguel Industrial | G45: Budget | BI45: 1.05 | BJ45: 0 | BK45: 0 | BL45: 0 | BM45: 0 | BN45: 0 | BO45: 0 | BP45: 0 | BQ45: 0 | BR45: 0 | BS45: -8648.85 | BT45: -8150.1 | BU45: -8432.55 | BW45: =_xlfn.SINGLE(_xlfn.XLOOKUP($A45,$A$203:$A$399,BJ$203:BJ$399,"Não Existe"))*$BI45 | BX45: =_xlfn.SINGLE(_xlfn.XLOOKUP($A45,$A$203:$A$399,BK$203:BK$399,"Não Existe"))*$BI45 | BY45: =_xlfn.SINGLE(_xlfn.XLOOKUP($A45,$A$203:$A$399,BL$203:BL$399,"Não Existe"))*$BI45 | BZ45: =_xlfn.SINGLE(_xlfn.XLOOKUP($A45,$A$203:$A$399,BM$203:BM$399,"Não Existe"))*$BI45 | CA45: =_xlfn.SINGLE(_xlfn.XLOOKUP($A45,$A$203:$A$399,BN$203:BN$399,"Não Existe"))*$BI45 | CB45: =_xlfn.SINGLE(_xlfn.XLOOKUP($A45,$A$203:$A$399,BO$203:BO$399,"Não Existe"))*$BI45 | CC45: =_xlfn.SINGLE(_xlfn.XLOOKUP($A45,$A$203:$A$399,BP$203:BP$399,"Não Existe"))*$BI45 | CD45: =_xlfn.SINGLE(_xlfn.XLOOKUP($A45,$A$203:$A$399,BQ$203:BQ$399,"Não Existe"))*$BI45 | ... CH45: =_xlfn.SINGLE(_xlfn.XLOOKUP($A45,$A$203:$A$399,BU$203:BU$399,"Não Existe"))*$BI45
A46: 33.01 | B46: Energia | C46: Analítica | D46: Saída | E46: =VLOOKUP($A46,PL.C!$B:$F,5,0) | F46: sim | G46: Budget | I46: 0 | J46: 0 | K46: 0 | L46: -14042 | M46: -6938 | N46: -15830 | O46: -8806 | P46: -7781 | Q46: 0 | R46: -7773 | S46: -15715 | T46: -9281 | V46: -7311 | W46: -8136 | X46: 0 | Y46: -7965 | Z46: -16001 | AA46: -8149 | AB46: 0 | AC46: -15924 | AD46: 0 | AE46: -19666 | AF46: 0 | AG46: -19866 | AI46: 0 | AJ46: -13624 | AK46: -20253 | AL46: -11766 | AM46: -8614 | AN46: -7994 | AO46: -8670 | AP46: 0 | AQ46: -8802 | AR46: -10415 | AS46: -17758 | AT46: 0 | AV46: 0 | AW46: -14332.448 | AX46: -21306.156 | AY46: -12377.832 | AZ46: -9061.928 | BA46: -8409.688 | BB46: -9120.84 | BC46: 0 | BD46: -9259.704 | BE46: -10956.58 | BF46: -18681.416 | BG46: 0 | BI46: 1.05 | BJ46: 0 | BK46: 0 | BL46: 0 | BM46: -370.65 | BN46: -869.4 | BO46: -416.85 | BP46: -442.05 | BQ46: -709.8 | BR46: -993.3 | BS46: -722.4 | BT46: -998.55 | BU46: -930.3 | BW46: =_xlfn.SINGLE(_xlfn.XLOOKUP($A46,$A$203:$A$399,BJ$203:BJ$399,"Não Existe"))*$BI46 | BX46: =_xlfn.SINGLE(_xlfn.XLOOKUP($A46,$A$203:$A$399,BK$203:BK$399,"Não Existe"))*$BI46 | BY46: =_xlfn.SINGLE(_xlfn.XLOOKUP($A46,$A$203:$A$399,BL$203:BL$399,"Não Existe"))*$BI46 | BZ46: =_xlfn.SINGLE(_xlfn.XLOOKUP($A46,$A$203:$A$399,BM$203:BM$399,"Não Existe"))*$BI46 | CA46: =_xlfn.SINGLE(_xlfn.XLOOKUP($A46,$A$203:$A$399,BN$203:BN$399,"Não Existe"))*$BI46 | CB46: =_xlfn.SINGLE(_xlfn.XLOOKUP($A46,$A$203:$A$399,BO$203:BO$399,"Não Existe"))*$BI46 | CC46: =_xlfn.SINGLE(_xlfn.XLOOKUP($A46,$A$203:$A$399,BP$203:BP$399,"Não Existe"))*$BI46 | CD46: =_xlfn.SINGLE(_xlfn.XLOOKUP($A46,$A$203:$A$399,BQ$203:BQ$399,"Não Existe"))*$BI46 | ... CH46: =_xlfn.SINGLE(_xlfn.XLOOKUP($A46,$A$203:$A$399,BU$203:BU$399,"Não Existe"))*$BI46
A47: 33.02 | B47: Gás | C47: Analítica | D47: Saída | E47: =VLOOKUP($A47,PL.C!$B:$F,5,0) | F47: sim | G47: Budget | I47: 0 | J47: 0 | K47: 0 | L47: -6487 | M47: -9646 | N47: -12882 | O47: -9089 | P47: -10969 | Q47: -10236 | R47: -7029 | S47: -11096 | T47: -9135 | V47: -8869 | W47: -10375 | X47: -12773 | Y47: -11559 | Z47: -12337 | AA47: -11208 | AB47: -14935 | AC47: -16704 | AD47: -10748 | AE47: -14723 | AF47: -15906 | AG47: -15614 | AI47: -9912 | AJ47: -8107 | AK47: -13197 | AL47: -8510 | AM47: -19360 | AN47: -9727 | AO47: -11789 | AP47: -16144 | AQ47: -7860 | AR47: -15056 | AS47: -12267 | AT47: -11859 | AV47: -10427.424 | AW47: -8528.564 | AX47: -13883.244 | AY47: -8952.52 | AZ47: -20366.72 | BA47: -10232.804 | BB47: -12402.028 | BC47: -16983.488 | BD47: -8268.72 | BE47: -15838.912 | BF47: -12904.884 | BG47: -12475.668 | BI47: 1.05 | BJ47: -15680.7 | BK47: -12854.1 | BL47: -11068.05 | BM47: -11680.2 | BN47: -15589.35 | BO47: -12877.2 | BP47: -18252.15 | BQ47: -12417.3 | BR47: -12520.2 | BS47: -18091.5 | BT47: -11469.15 | BU47: -13086.15 | BW47: =_xlfn.SINGLE(_xlfn.XLOOKUP($A47,$A$203:$A$399,BJ$203:BJ$399,"Não Existe"))*$BI47 | BX47: =_xlfn.SINGLE(_xlfn.XLOOKUP($A47,$A$203:$A$399,BK$203:BK$399,"Não Existe"))*$BI47 | BY47: =_xlfn.SINGLE(_xlfn.XLOOKUP($A47,$A$203:$A$399,BL$203:BL$399,"Não Existe"))*$BI47 | BZ47: =_xlfn.SINGLE(_xlfn.XLOOKUP($A47,$A$203:$A$399,BM$203:BM$399,"Não Existe"))*$BI47 | CA47: =_xlfn.SINGLE(_xlfn.XLOOKUP($A47,$A$203:$A$399,BN$203:BN$399,"Não Existe"))*$BI47 | CB47: =_xlfn.SINGLE(_xlfn.XLOOKUP($A47,$A$203:$A$399,BO$203:BO$399,"Não Existe"))*$BI47 | CC47: =_xlfn.SINGLE(_xlfn.XLOOKUP($A47,$A$203:$A$399,BP$203:BP$399,"Não Existe"))*$BI47 | CD47: =_xlfn.SINGLE(_xlfn.XLOOKUP($A47,$A$203:$A$399,BQ$203:BQ$399,"Não Existe"))*$BI47 | ... CH47: =_xlfn.SINGLE(_xlfn.XLOOKUP($A47,$A$203:$A$399,BU$203:BU$399,"Não Existe"))*$BI47
A48: 33.03 | B48: Agua | C48: Analítica | D48: Saída | E48: =VLOOKUP($A48,PL.C!$B:$F,5,0) | F48: sim | G48: Budget | I48: 0 | J48: 0 | K48: 0 | L48: -352 | M48: -360 | N48: -616 | O48: -616 | P48: -451 | Q48: -526 | R48: -343 | S48: -792 | T48: -482 | V48: -305 | W48: -453 | X48: -319 | Y48: -383 | Z48: -722 | AA48: -446 | AB48: -392 | AC48: -709 | AD48: -631 | AE48: -390 | AF48: -408 | AG48: -313 | AI48: -284 | AJ48: 0 | AK48: -823 | AL48: -551 | AM48: -511 | AN48: -360 | AO48: -472 | AP48: -491 | AQ48: -466 | AR48: -579 | AS48: -599 | AT48: -389 | AV48: -298.768 | AW48: 0 | AX48: -865.796 | AY48: -579.652 | AZ48: -537.572 | BA48: -378.72 | BB48: -496.544 | BC48: -516.532 | BD48: -490.232 | BE48: -609.108 | BF48: -630.148 | BG48: -409.228 | BI48: 1.2 | BJ48: -566.4 | BK48: -625.2 | BL48: -498 | BM48: -613.2 | BN48: -566.4 | BO48: -1092 | BP48: -890.4 | BQ48: 0 | BR48: -2325.6 | BS48: -2554.8 | BT48: -2085.6 | BU48: -1292.4 | BW48: =_xlfn.SINGLE(_xlfn.XLOOKUP($A48,$A$203:$A$399,BJ$203:BJ$399,"Não Existe"))*$BI48 | BX48: =_xlfn.SINGLE(_xlfn.XLOOKUP($A48,$A$203:$A$399,BK$203:BK$399,"Não Existe"))*$BI48 | BY48: =_xlfn.SINGLE(_xlfn.XLOOKUP($A48,$A$203:$A$399,BL$203:BL$399,"Não Existe"))*$BI48 | BZ48: =_xlfn.SINGLE(_xlfn.XLOOKUP($A48,$A$203:$A$399,BM$203:BM$399,"Não Existe"))*$BI48 | CA48: =_xlfn.SINGLE(_xlfn.XLOOKUP($A48,$A$203:$A$399,BN$203:BN$399,"Não Existe"))*$BI48 | CB48: =_xlfn.SINGLE(_xlfn.XLOOKUP($A48,$A$203:$A$399,BO$203:BO$399,"Não Existe"))*$BI48 | CC48: =_xlfn.SINGLE(_xlfn.XLOOKUP($A48,$A$203:$A$399,BP$203:BP$399,"Não Existe"))*$BI48 | CD48: =_xlfn.SINGLE(_xlfn.XLOOKUP($A48,$A$203:$A$399,BQ$203:BQ$399,"Não Existe"))*$BI48 | ... CH48: =_xlfn.SINGLE(_xlfn.XLOOKUP($A48,$A$203:$A$399,BU$203:BU$399,"Não Existe"))*$BI48
A49: 33.04 | B49: Consumíveis de Produção | C49: Analítica | D49: Saída | E49: =VLOOKUP($A49,PL.C!$B:$F,5,0) | F49: sim | G49: Budget | I49: -3074 | J49: 0 | K49: -840 | L49: -9222 | M49: -886 | N49: -1105 | O49: 0 | P49: -11 | Q49: 0 | R49: 0 | S49: -2034 | T49: -5988 | V49: -122 | W49: -2917 | X49: -1620 | Y49: -56 | Z49: -1064 | AA49: -1216 | AB49: -99 | AC49: -40 | AD49: -1167 | AE49: -1452 | AF49: -2052 | AG49: -1807 | AI49: -814 | AJ49: -353 | AK49: -1463 | AL49: -29 | AM49: -1668 | AN49: -2340 | AO49: -289 | AP49: -1120 | AQ49: -3731 | AR49: -1242 | AS49: -956 | AT49: -147 | AV49: -856.328 | AW49: -371.356 | AX49: -1539.076 | AY49: -30.508 | AZ49: -1754.736 | BA49: -2461.68 | BB49: -304.028 | BC49: -1178.24 | BD49: -3925.012 | BE49: -1306.584 | BF49: -1005.712 | BG49: -154.644 | BI49: 1.05 | BJ49: -1453.2 | BK49: -84 | BL49: -2420.25 | BM49: -804.3 | BN49: -4952.85 | BO49: -5505.15 | BP49: -753.9 | BQ49: -1746.15 | BR49: -9893.1 | BS49: -554.4 | BT49: -4128.6 | BU49: -58.8 | BW49: =_xlfn.SINGLE(_xlfn.XLOOKUP($A49,$A$203:$A$399,BJ$203:BJ$399,"Não Existe"))*$BI49 | BX49: =_xlfn.SINGLE(_xlfn.XLOOKUP($A49,$A$203:$A$399,BK$203:BK$399,"Não Existe"))*$BI49 | BY49: =_xlfn.SINGLE(_xlfn.XLOOKUP($A49,$A$203:$A$399,BL$203:BL$399,"Não Existe"))*$BI49 | BZ49: =_xlfn.SINGLE(_xlfn.XLOOKUP($A49,$A$203:$A$399,BM$203:BM$399,"Não Existe"))*$BI49 | CA49: =_xlfn.SINGLE(_xlfn.XLOOKUP($A49,$A$203:$A$399,BN$203:BN$399,"Não Existe"))*$BI49 | CB49: =_xlfn.SINGLE(_xlfn.XLOOKUP($A49,$A$203:$A$399,BO$203:BO$399,"Não Existe"))*$BI49 | CC49: =_xlfn.SINGLE(_xlfn.XLOOKUP($A49,$A$203:$A$399,BP$203:BP$399,"Não Existe"))*$BI49 | CD49: =_xlfn.SINGLE(_xlfn.XLOOKUP($A49,$A$203:$A$399,BQ$203:BQ$399,"Não Existe"))*$BI49 | ... CH49: =_xlfn.SINGLE(_xlfn.XLOOKUP($A49,$A$203:$A$399,BU$203:BU$399,"Não Existe"))*$BI49
A50: 33.05 | B50: Outros custos fabris | C50: Analítica | D50: Saída | E50: =VLOOKUP($A50,PL.C!$B:$F,5,0) | F50: sim | G50: Budget | I50: 0 | J50: 0 | K50: 0 | L50: -1477 | M50: -2839 | N50: -153 | O50: 0 | P50: -373 | Q50: -250 | R50: -1700 | S50: 0 | T50: 0 | V50: -50 | W50: -62 | X50: 0 | Y50: -96 | Z50: 0 | AA50: -59 | AB50: -198 | AC50: -330 | AD50: -1107 | AE50: -1757 | AF50: 0 | AG50: 0 | AI50: 0 | AJ50: 0 | AK50: 0 | AL50: 0 | AM50: 0 | AN50: -100 | AO50: 0 | AP50: -120 | AQ50: 0 | AR50: 0 | AS50: 0 | AT50: -37 | AV50: 0 | AW50: 0 | AX50: 0 | AY50: 0 | AZ50: 0 | BA50: -105.2 | BB50: 0 | BC50: -126.24 | BD50: 0 | BE50: 0 | BF50: 0 | BG50: -38.924 | BI50: 1.05 | BJ50: -43.05 | BK50: -84 | BL50: -563.85 | BM50: -164.85 | BN50: -1647.45 | BO50: 0 | BP50: 0 | BQ50: -52.5 | BR50: -1345.05 | BS50: 0 | BT50: -500.85 | BU50: 0 | BW50: =_xlfn.SINGLE(_xlfn.XLOOKUP($A50,$A$203:$A$399,BJ$203:BJ$399,"Não Existe"))*$BI50 | BX50: =_xlfn.SINGLE(_xlfn.XLOOKUP($A50,$A$203:$A$399,BK$203:BK$399,"Não Existe"))*$BI50 | BY50: =_xlfn.SINGLE(_xlfn.XLOOKUP($A50,$A$203:$A$399,BL$203:BL$399,"Não Existe"))*$BI50 | BZ50: =_xlfn.SINGLE(_xlfn.XLOOKUP($A50,$A$203:$A$399,BM$203:BM$399,"Não Existe"))*$BI50 | CA50: =_xlfn.SINGLE(_xlfn.XLOOKUP($A50,$A$203:$A$399,BN$203:BN$399,"Não Existe"))*$BI50 | CB50: =_xlfn.SINGLE(_xlfn.XLOOKUP($A50,$A$203:$A$399,BO$203:BO$399,"Não Existe"))*$BI50 | CC50: =_xlfn.SINGLE(_xlfn.XLOOKUP($A50,$A$203:$A$399,BP$203:BP$399,"Não Existe"))*$BI50 | CD50: =_xlfn.SINGLE(_xlfn.XLOOKUP($A50,$A$203:$A$399,BQ$203:BQ$399,"Não Existe"))*$BI50 | ... CH50: =_xlfn.SINGLE(_xlfn.XLOOKUP($A50,$A$203:$A$399,BU$203:BU$399,"Não Existe"))*$BI50
A51: 34.01 | B51: Manutenção de ar condicionado | C51: Analítica | D51: Saída | E51: =VLOOKUP($A51,PL.C!$B:$F,5,0) | F51: sim | G51: Budget | I51: 0 | J51: 0 | K51: 0 | L51: 0 | M51: 0 | N51: 0 | O51: 0 | P51: -250 | Q51: 0 | R51: 0 | S51: 0 | T51: -360 | V51: 0 | W51: 0 | X51: -280 | Y51: 0 | Z51: -150 | AA51: 0 | AB51: 0 | AC51: 0 | AD51: 0 | AE51: 0 | AF51: 0 | AG51: -600 | AI51: -280 | AJ51: 0 | AK51: -850 | AL51: -250 | AM51: 0 | AN51: 0 | AO51: 0 | AP51: -610 | AQ51: 0 | AR51: 0 | AS51: 0 | AT51: 0 | AV51: -294.56 | AW51: 0 | AX51: -894.2 | AY51: -263 | AZ51: 0 | BA51: 0 | BB51: 0 | BC51: -641.72 | BD51: 0 | BE51: 0 | BF51: 0 | BG51: 0 | BI51: 1.05 | BJ51: -672 | BK51: 0 | BL51: 0 | BM51: 0 | BN51: 0 | BO51: 0 | BP51: 0 | BQ51: 0 | BR51: 0 | BS51: 0 | BT51: 0 | BU51: -157.5 | BW51: =_xlfn.SINGLE(_xlfn.XLOOKUP($A51,$A$203:$A$399,BJ$203:BJ$399,"Não Existe"))*$BI51 | BX51: =_xlfn.SINGLE(_xlfn.XLOOKUP($A51,$A$203:$A$399,BK$203:BK$399,"Não Existe"))*$BI51 | BY51: =_xlfn.SINGLE(_xlfn.XLOOKUP($A51,$A$203:$A$399,BL$203:BL$399,"Não Existe"))*$BI51 | BZ51: =_xlfn.SINGLE(_xlfn.XLOOKUP($A51,$A$203:$A$399,BM$203:BM$399,"Não Existe"))*$BI51 | CA51: =_xlfn.SINGLE(_xlfn.XLOOKUP($A51,$A$203:$A$399,BN$203:BN$399,"Não Existe"))*$BI51 | CB51: =_xlfn.SINGLE(_xlfn.XLOOKUP($A51,$A$203:$A$399,BO$203:BO$399,"Não Existe"))*$BI51 | CC51: =_xlfn.SINGLE(_xlfn.XLOOKUP($A51,$A$203:$A$399,BP$203:BP$399,"Não Existe"))*$BI51 | CD51: =_xlfn.SINGLE(_xlfn.XLOOKUP($A51,$A$203:$A$399,BQ$203:BQ$399,"Não Existe"))*$BI51 | ... CH51: =_xlfn.SINGLE(_xlfn.XLOOKUP($A51,$A$203:$A$399,BU$203:BU$399,"Não Existe"))*$BI51
A52: 34.04 | B52: Manutenção de infra-estrutura | C52: Analítica | D52: Saída | E52: =VLOOKUP($A52,PL.C!$B:$F,5,0) | F52: sim | G52: Budget | I52: 0 | J52: 0 | K52: 0 | L52: -108 | M52: -2267 | N52: -860 | O52: -1680 | P52: -1701 | Q52: -1532 | R52: -215 | S52: -100 | T52: -1561 | V52: -9752 | W52: -7920 | X52: -1035 | Y52: -1290 | Z52: -916 | AA52: -3100 | AB52: -341 | AC52: -916 | AD52: -1497 | AE52: -1346 | AF52: -3365 | AG52: -98 | AI52: -118 | AJ52: -810 | AK52: -1028 | AL52: -2972 | AM52: -7947 | AN52: -1034 | AO52: -479 | AP52: -930 | AQ52: -145 | AR52: -50 | AS52: -17145 | AT52: -220 | AV52: -124.136 | AW52: -852.12 | AX52: -1081.456 | AY52: -3126.544 | AZ52: -8360.244 | BA52: -1087.768 | BB52: -503.908 | BC52: -978.36 | BD52: -152.54 | BE52: -52.6 | BF52: -18036.54 | BG52: -231.44 | BI52: 1.05 | BJ52: -1397.55 | BK52: -6310.5 | BL52: -6443.85 | BM52: -1927.8 | BN52: -961.8 | BO52: -1822.8 | BP52: -703.5 | BQ52: -349.65 | BR52: -5839.05 | BS52: -7493.85 | BT52: -1365 | BU52: -3182.55 | BW52: =_xlfn.SINGLE(_xlfn.XLOOKUP($A52,$A$203:$A$399,BJ$203:BJ$399,"Não Existe"))*$BI52 | BX52: =_xlfn.SINGLE(_xlfn.XLOOKUP($A52,$A$203:$A$399,BK$203:BK$399,"Não Existe"))*$BI52 | BY52: =_xlfn.SINGLE(_xlfn.XLOOKUP($A52,$A$203:$A$399,BL$203:BL$399,"Não Existe"))*$BI52 | BZ52: =_xlfn.SINGLE(_xlfn.XLOOKUP($A52,$A$203:$A$399,BM$203:BM$399,"Não Existe"))*$BI52 | CA52: =_xlfn.SINGLE(_xlfn.XLOOKUP($A52,$A$203:$A$399,BN$203:BN$399,"Não Existe"))*$BI52 | CB52: =_xlfn.SINGLE(_xlfn.XLOOKUP($A52,$A$203:$A$399,BO$203:BO$399,"Não Existe"))*$BI52 | CC52: =_xlfn.SINGLE(_xlfn.XLOOKUP($A52,$A$203:$A$399,BP$203:BP$399,"Não Existe"))*$BI52 | CD52: =_xlfn.SINGLE(_xlfn.XLOOKUP($A52,$A$203:$A$399,BQ$203:BQ$399,"Não Existe"))*$BI52 | ... CH52: =_xlfn.SINGLE(_xlfn.XLOOKUP($A52,$A$203:$A$399,BU$203:BU$399,"Não Existe"))*$BI52
A53: 34.05 | B53: Manutenção de máquinas | C53: Analítica | D53: Saída | E53: =VLOOKUP($A53,PL.C!$B:$F,5,0) | F53: sim | G53: Budget | I53: 0 | J53: 0 | K53: 0 | L53: -2418 | M53: -3512 | N53: -3837 | O53: -1701 | P53: -1336 | Q53: -1670 | R53: -6135 | S53: -2160 | T53: -6979 | V53: -4623 | W53: -6401 | X53: -5444 | Y53: -3266 | Z53: -2453 | AA53: -4765 | AB53: -6667 | AC53: -6392 | AD53: -3198 | AE53: -6758 | AF53: -2435 | AG53: -2090 | AI53: -4652 | AJ53: -4068 | AK53: -13880 | AL53: -4541 | AM53: -2372 | AN53: -4891 | AO53: -2162 | AP53: -2993 | AQ53: -12867 | AR53: -2029 | AS53: -7864 | AT53: -10739 | AV53: -4893.904 | AW53: -4279.536 | AX53: -14601.76 | AY53: -4777.132 | AZ53: -2495.344 | BA53: -5145.332 | BB53: -2274.424 | BC53: -3148.636 | BD53: -13536.084 | BE53: -2134.508 | BF53: -8272.928 | BG53: -11297.428 | BI53: 1.05 | BJ53: -2292.15 | BK53: -1807.05 | BL53: -2384.55 | BM53: -5134.5 | BN53: -4275.6 | BO53: -8149.05 | BP53: -7770 | BQ53: -5182.8 | BR53: -9646.35 | BS53: -11588.85 | BT53: -1853.25 | BU53: -1638 | BW53: =_xlfn.SINGLE(_xlfn.XLOOKUP($A53,$A$203:$A$399,BJ$203:BJ$399,"Não Existe"))*$BI53 | BX53: =_xlfn.SINGLE(_xlfn.XLOOKUP($A53,$A$203:$A$399,BK$203:BK$399,"Não Existe"))*$BI53 | BY53: =_xlfn.SINGLE(_xlfn.XLOOKUP($A53,$A$203:$A$399,BL$203:BL$399,"Não Existe"))*$BI53 | BZ53: =_xlfn.SINGLE(_xlfn.XLOOKUP($A53,$A$203:$A$399,BM$203:BM$399,"Não Existe"))*$BI53 | CA53: =_xlfn.SINGLE(_xlfn.XLOOKUP($A53,$A$203:$A$399,BN$203:BN$399,"Não Existe"))*$BI53 | CB53: =_xlfn.SINGLE(_xlfn.XLOOKUP($A53,$A$203:$A$399,BO$203:BO$399,"Não Existe"))*$BI53 | CC53: =_xlfn.SINGLE(_xlfn.XLOOKUP($A53,$A$203:$A$399,BP$203:BP$399,"Não Existe"))*$BI53 | CD53: =_xlfn.SINGLE(_xlfn.XLOOKUP($A53,$A$203:$A$399,BQ$203:BQ$399,"Não Existe"))*$BI53 | ... CH53: =_xlfn.SINGLE(_xlfn.XLOOKUP($A53,$A$203:$A$399,BU$203:BU$399,"Não Existe"))*$BI53
A54: 34.06 | B54: Manutenção de Ferramentas | C54: Analítica | D54: Saída | E54: =VLOOKUP($A54,PL.C!$B:$F,5,0) | F54: sim | G54: Budget | I54: 0 | J54: 0 | K54: 0 | L54: 0 | M54: 0 | N54: 0 | O54: 0 | P54: 0 | Q54: 0 | R54: 0 | S54: 0 | T54: 0 | V54: 0 | W54: 0 | X54: 0 | Y54: 0 | Z54: 0 | AA54: 0 | AB54: 0 | AC54: 0 | AD54: 0 | AE54: 0 | AF54: 0 | AG54: 0 | AI54: 0 | AJ54: 0 | AK54: 0 | AL54: 0 | AM54: 0 | AN54: 0 | AO54: -40 | AP54: 0 | AQ54: 0 | AR54: 0 | AS54: 0 | AT54: 0 | AV54: 0 | AW54: 0 | AX54: 0 | AY54: 0 | AZ54: 0 | BA54: 0 | BB54: -42.08 | BC54: 0 | BD54: 0 | BE54: 0 | BF54: 0 | BG54: 0 | BI54: 1.05 | BJ54: 0 | BK54: 0 | BL54: 0 | BM54: 0 | BN54: 0 | BO54: 0 | BP54: 0 | BQ54: 0 | BR54: 0 | BS54: 0 | BT54: 0 | BU54: 0 | BW54: =_xlfn.SINGLE(_xlfn.XLOOKUP($A54,$A$203:$A$399,BJ$203:BJ$399,"Não Existe"))*$BI54 | BX54: =_xlfn.SINGLE(_xlfn.XLOOKUP($A54,$A$203:$A$399,BK$203:BK$399,"Não Existe"))*$BI54 | BY54: =_xlfn.SINGLE(_xlfn.XLOOKUP($A54,$A$203:$A$399,BL$203:BL$399,"Não Existe"))*$BI54 | BZ54: =_xlfn.SINGLE(_xlfn.XLOOKUP($A54,$A$203:$A$399,BM$203:BM$399,"Não Existe"))*$BI54 | CA54: =_xlfn.SINGLE(_xlfn.XLOOKUP($A54,$A$203:$A$399,BN$203:BN$399,"Não Existe"))*$BI54 | CB54: =_xlfn.SINGLE(_xlfn.XLOOKUP($A54,$A$203:$A$399,BO$203:BO$399,"Não Existe"))*$BI54 | CC54: =_xlfn.SINGLE(_xlfn.XLOOKUP($A54,$A$203:$A$399,BP$203:BP$399,"Não Existe"))*$BI54 | CD54: =_xlfn.SINGLE(_xlfn.XLOOKUP($A54,$A$203:$A$399,BQ$203:BQ$399,"Não Existe"))*$BI54 | ... CH54: =_xlfn.SINGLE(_xlfn.XLOOKUP($A54,$A$203:$A$399,BU$203:BU$399,"Não Existe"))*$BI54
A55: 34.07 | B55: Calibração de instrumentos | C55: Analítica | D55: Saída | E55: =VLOOKUP($A55,PL.C!$B:$F,5,0) | F55: sim | G55: Budget | I55: 0 | J55: 0 | K55: 0 | L55: 0 | M55: 0 | N55: 0 | O55: 0 | P55: 0 | Q55: 0 | R55: 0 | S55: 0 | T55: 0 | V55: 0 | W55: 0 | X55: 0 | Y55: 0 | Z55: 0 | AA55: 0 | AB55: 0 | AC55: 0 | AD55: 0 | AE55: 0 | AF55: 0 | AG55: 0 | AI55: 0 | AJ55: 0 | AK55: 0 | AL55: 0 | AM55: 0 | AN55: 0 | AO55: 0 | AP55: 0 | AQ55: 0 | AR55: 0 | AS55: 0 | AT55: 0 | AV55: 0 | AW55: 0 | AX55: 0 | AY55: 0 | AZ55: 0 | BA55: 0 | BB55: 0 | BC55: 0 | BD55: 0 | BE55: 0 | BF55: 0 | BG55: 0 | BI55: 1.05 | BJ55: 0 | BK55: 0 | BL55: -685.65 | BM55: 0 | BN55: 0 | BO55: 0 | BP55: 0 | BQ55: 0 | BR55: 0 | BS55: 0 | BT55: 0 | BU55: 0 | BW55: =_xlfn.SINGLE(_xlfn.XLOOKUP($A55,$A$203:$A$399,BJ$203:BJ$399,"Não Existe"))*$BI55 | BX55: =_xlfn.SINGLE(_xlfn.XLOOKUP($A55,$A$203:$A$399,BK$203:BK$399,"Não Existe"))*$BI55 | BY55: =_xlfn.SINGLE(_xlfn.XLOOKUP($A55,$A$203:$A$399,BL$203:BL$399,"Não Existe"))*$BI55 | BZ55: =_xlfn.SINGLE(_xlfn.XLOOKUP($A55,$A$203:$A$399,BM$203:BM$399,"Não Existe"))*$BI55 | CA55: =_xlfn.SINGLE(_xlfn.XLOOKUP($A55,$A$203:$A$399,BN$203:BN$399,"Não Existe"))*$BI55 | CB55: =_xlfn.SINGLE(_xlfn.XLOOKUP($A55,$A$203:$A$399,BO$203:BO$399,"Não Existe"))*$BI55 | CC55: =_xlfn.SINGLE(_xlfn.XLOOKUP($A55,$A$203:$A$399,BP$203:BP$399,"Não Existe"))*$BI55 | CD55: =_xlfn.SINGLE(_xlfn.XLOOKUP($A55,$A$203:$A$399,BQ$203:BQ$399,"Não Existe"))*$BI55 | ... CH55: =_xlfn.SINGLE(_xlfn.XLOOKUP($A55,$A$203:$A$399,BU$203:BU$399,"Não Existe"))*$BI55
A56: 35.02 | B56: Comissão de vendedores direto | C56: Analítica | D56: Saída | E56: =VLOOKUP($A56,PL.C!$B:$F,5,0) | F56: sim | G56: Budget | I56: 0 | J56: 0 | K56: 0 | L56: 0 | M56: -6850 | N56: 0 | O56: -4570 | P56: -5660 | Q56: 0 | R56: -8220 | S56: -2600 | T56: 0 | V56: -2575 | W56: 0 | X56: -4160 | Y56: -5440 | Z56: 0 | AA56: 0 | AB56: 0 | AC56: 0 | AD56: 0 | AE56: 0 | AF56: -840 | AG56: -1912 | AI56: 0 | AJ56: 0 | AK56: 0 | AL56: 0 | AM56: 0 | AN56: 0 | AO56: 0 | AP56: 0 | AQ56: 0 | AR56: 0 | AS56: 0 | AT56: 0 | AV56: 0 | AW56: 0 | AX56: 0 | AY56: 0 | AZ56: 0 | BA56: 0 | BB56: 0 | BC56: 0 | BD56: 0 | BE56: 0 | BF56: 0 | BG56: 0 | BI56: 1.05 | BJ56: 0 | BK56: 0 | BL56: 0 | BM56: 0 | BN56: 0 | BO56: 0 | BP56: 0 | BQ56: 0 | BR56: 0 | BS56: 0 | BT56: 0 | BU56: 0 | BW56: =_xlfn.SINGLE(_xlfn.XLOOKUP($A56,$A$203:$A$399,BJ$203:BJ$399,"Não Existe"))*$BI56 | BX56: =_xlfn.SINGLE(_xlfn.XLOOKUP($A56,$A$203:$A$399,BK$203:BK$399,"Não Existe"))*$BI56 | BY56: =_xlfn.SINGLE(_xlfn.XLOOKUP($A56,$A$203:$A$399,BL$203:BL$399,"Não Existe"))*$BI56 | BZ56: =_xlfn.SINGLE(_xlfn.XLOOKUP($A56,$A$203:$A$399,BM$203:BM$399,"Não Existe"))*$BI56 | CA56: =_xlfn.SINGLE(_xlfn.XLOOKUP($A56,$A$203:$A$399,BN$203:BN$399,"Não Existe"))*$BI56 | CB56: =_xlfn.SINGLE(_xlfn.XLOOKUP($A56,$A$203:$A$399,BO$203:BO$399,"Não Existe"))*$BI56 | CC56: =_xlfn.SINGLE(_xlfn.XLOOKUP($A56,$A$203:$A$399,BP$203:BP$399,"Não Existe"))*$BI56 | CD56: =_xlfn.SINGLE(_xlfn.XLOOKUP($A56,$A$203:$A$399,BQ$203:BQ$399,"Não Existe"))*$BI56 | ... CH56: =_xlfn.SINGLE(_xlfn.XLOOKUP($A56,$A$203:$A$399,BU$203:BU$399,"Não Existe"))*$BI56
A57: 36.01 | B57: Salário líquido | C57: Analítica | D57: Saída | E57: =VLOOKUP($A57,PL.C!$B:$F,5,0) | F57: sim | G57: Budget | I57: 0 | J57: 0 | K57: 0 | L57: -220 | M57: -2532 | N57: -2532 | O57: -2532 | P57: -2532 | Q57: -2532 | R57: -2532 | S57: -2532 | T57: -2542 | V57: -2542 | W57: -2548 | X57: -2548 | Y57: 0 | Z57: -2548 | AA57: -2548 | AB57: -2548 | AC57: -2548 | AD57: -2548 | AE57: -2548 | AF57: -2548 | AG57: -2620 | AI57: -2572 | AJ57: -2583 | AK57: -2583 | AL57: -254 | AM57: -2583 | AN57: 0 | AO57: -4792 | AP57: -4792 | AQ57: -4792 | AR57: -4792 | AS57: -4792 | AT57: -4792 | AV57: -2705.744 | AW57: -2717.316 | AX57: -2717.316 | AY57: -267.208 | AZ57: -2717.316 | BA57: 0 | BB57: -5041.184 | BC57: -5041.184 | BD57: -5041.184 | BE57: -5041.184 | BF57: -5041.184 | BG57: -5041.184 | BI57: 1.1 | BJ57: -5271.2 | BK57: -5303.1 | BL57: -5303.1 | BM57: -5303.1 | BN57: -5303.1 | BO57: -10254.2 | BP57: -310.2 | BQ57: -10254.2 | BR57: -1453.1 | BS57: -5854.2 | BT57: -5854.2 | BU57: -5854.2 | BW57: =_xlfn.SINGLE(_xlfn.XLOOKUP($A57,$A$203:$A$399,BJ$203:BJ$399,"Não Existe"))*$BI57 | BX57: =_xlfn.SINGLE(_xlfn.XLOOKUP($A57,$A$203:$A$399,BK$203:BK$399,"Não Existe"))*$BI57 | BY57: =_xlfn.SINGLE(_xlfn.XLOOKUP($A57,$A$203:$A$399,BL$203:BL$399,"Não Existe"))*$BI57 | BZ57: =_xlfn.SINGLE(_xlfn.XLOOKUP($A57,$A$203:$A$399,BM$203:BM$399,"Não Existe"))*$BI57 | CA57: =_xlfn.SINGLE(_xlfn.XLOOKUP($A57,$A$203:$A$399,BN$203:BN$399,"Não Existe"))*$BI57 | CB57: =_xlfn.SINGLE(_xlfn.XLOOKUP($A57,$A$203:$A$399,BO$203:BO$399,"Não Existe"))*$BI57 | CC57: =_xlfn.SINGLE(_xlfn.XLOOKUP($A57,$A$203:$A$399,BP$203:BP$399,"Não Existe"))*$BI57 | CD57: =_xlfn.SINGLE(_xlfn.XLOOKUP($A57,$A$203:$A$399,BQ$203:BQ$399,"Não Existe"))*$BI57 | ... CH57: =_xlfn.SINGLE(_xlfn.XLOOKUP($A57,$A$203:$A$399,BU$203:BU$399,"Não Existe"))*$BI57
... A201: 55.02 | B201: Pagamento de devolução de terceiros | C201: Analítica | D201: Saída | E201: =VLOOKUP($A201,PL.C!$B:$F,5,0) | F201: sim | G201: Budget | I201: 0 | J201: 0 | K201: 0 | L201: 0 | M201: 0 | N201: 0 | O201: 0 | P201: 0 | Q201: 0 | R201: 0 | S201: 0 | T201: 0 | V201: 0 | W201: 0 | X201: 0 | Y201: 0 | Z201: 0 | AA201: 0 | AB201: 0 | AC201: 0 | AD201: 0 | AE201: 0 | AF201: 0 | AG201: 0 | AI201: 0 | AJ201: 0 | AK201: 0 | AL201: 0 | AM201: 0 | AN201: -132 | AO201: -376 | AP201: 0 | AQ201: 0 | AR201: 0 | AS201: 0 | AT201: 0 | AV201: 0 | AW201: 0 | AX201: 0 | AY201: 0 | AZ201: 0 | BA201: -138.864 | BB201: -395.552 | BC201: 0 | BD201: 0 | BE201: 0 | BF201: 0 | BG201: 0 | BI201: 1.05 | BJ201: 0 | BK201: 0 | BL201: 0 | BM201: 0 | BN201: 0 | BO201: 0 | BP201: 0 | BQ201: 0 | BR201: 0 | BS201: 0 | BT201: 0 | BU201: 0 | BW201: =_xlfn.SINGLE(_xlfn.XLOOKUP($A201,$A$203:$A$399,BJ$203:BJ$399,"Não Existe"))*$BI201 | BX201: =_xlfn.SINGLE(_xlfn.XLOOKUP($A201,$A$203:$A$399,BK$203:BK$399,"Não Existe"))*$BI201 | BY201: =_xlfn.SINGLE(_xlfn.XLOOKUP($A201,$A$203:$A$399,BL$203:BL$399,"Não Existe"))*$BI201 | BZ201: =_xlfn.SINGLE(_xlfn.XLOOKUP($A201,$A$203:$A$399,BM$203:BM$399,"Não Existe"))*$BI201 | CA201: =_xlfn.SINGLE(_xlfn.XLOOKUP($A201,$A$203:$A$399,BN$203:BN$399,"Não Existe"))*$BI201 | CB201: =_xlfn.SINGLE(_xlfn.XLOOKUP($A201,$A$203:$A$399,BO$203:BO$399,"Não Existe"))*$BI201 | CC201: =_xlfn.SINGLE(_xlfn.XLOOKUP($A201,$A$203:$A$399,BP$203:BP$399,"Não Existe"))*$BI201 | CD201: =_xlfn.SINGLE(_xlfn.XLOOKUP($A201,$A$203:$A$399,BQ$203:BQ$399,"Não Existe"))*$BI201 | ... CH201: =_xlfn.SINGLE(_xlfn.XLOOKUP($A201,$A$203:$A$399,BU$203:BU$399,"Não Existe"))*$BI201
A203: 10.01 | B203: =VLOOKUP(A203,PL.C!$B:$F,2,0) | C203: Analítica | D203: Entrada | E203: =VLOOKUP($A203,PL.C!$B:$F,5,0) | F203: sim | G203: forecast | I203: 0 | J203: 36476 | K203: 42099 | L203: 1778806 | M203: 980903 | N203: 1146964 | O203: 1067595 | P203: 993317 | Q203: 1045459 | R203: 995263 | S203: 809964 | T203: 1083586 | V203: 920566 | W203: 847949 | X203: 1081182 | Y203: 971699 | Z203: 986935 | AA203: 1087558 | AB203: 1124216 | AC203: 1156838 | AD203: 1059419 | AE203: 993808 | AF203: 1098796 | AG203: 1075932 | AI203: 853337 | AJ203: 840528 | AK203: 1260369 | AL203: 1012027 | AM203: 1155106 | AN203: 1181187 | AO203: 1160671 | AP203: 1231074 | AQ203: 1117419 | AR203: 1131961 | AS203: 1242942 | AT203: 1217485 | AV203: 1166003 | AW203: 1074202 | AX203: 1240216 | AY203: 1161330 | AZ203: 1311768 | BA203: 1333554 | BB203: 1300800 | BC203: 1477740 | BD203: 1272163 | BE203: 1565818 | BF203: 1318343 | BG203: 1229136 | BJ203: 1306998 | BK203: 1221986 | BL203: 1334743 | BM203: 1308998 | BN203: 1298620 | BO203: 1359959 | BP203: 1554225 | BQ203: 1431233 | BR203: 1407902 | BS203: 1559041 | BT203: 1264392 | BU203: 1474531 | BW203: =_xlfn.XLOOKUP($A203,D!$O$3:$O$199,D!P$3:P$199,) | BX203: =_xlfn.XLOOKUP($A203,D!$O$3:$O$199,D!Q$3:Q$199,) | BY203: =_xlfn.XLOOKUP($A203,D!$O$3:$O$199,D!R$3:R$199,) | BZ203: =_xlfn.XLOOKUP($A203,D!$O$3:$O$199,D!S$3:S$199,) | CA203: =_xlfn.XLOOKUP($A203,D!$O$3:$O$199,D!T$3:T$199,) | CB203: =_xlfn.XLOOKUP($A203,D!$O$3:$O$199,D!U$3:U$199,) | CC203: =_xlfn.XLOOKUP($A203,D!$O$3:$O$199,D!V$3:V$199,) | CD203: =_xlfn.XLOOKUP($A203,D!$O$3:$O$199,D!W$3:W$199,) | ... CH203: =_xlfn.XLOOKUP($A203,D!$O$3:$O$199,D!AA$3:AA$199,)
A204: 10.02 | B204: =VLOOKUP(A204,PL.C!$B:$F,2,0) | C204: Analítica | D204: Entrada | E204: =VLOOKUP($A204,PL.C!$B:$F,5,0) | F204: sim | G204: forecast | I204: 0 | J204: 0 | K204: 0 | L204: 0 | M204: 0 | N204: 0 | O204: 0 | P204: 0 | Q204: 37 | R204: 0 | S204: 0 | T204: 0 | V204: 0 | W204: 0 | X204: 0 | Y204: 0 | Z204: 579 | AA204: 0 | AB204: 0 | AC204: 0 | AD204: 0 | AE204: 0 | AF204: 0 | AG204: 0 | AI204: 0 | AJ204: 0 | AK204: 0 | AL204: 0 | AM204: 0 | AN204: 0 | AO204: 0 | AP204: 0 | AQ204: 0 | AR204: 0 | AS204: 0 | AT204: 0 | AV204: 20 | AW204: 0 | AX204: 0 | AY204: 0 | AZ204: 0 | BA204: 0 | BB204: 0 | BC204: 0 | BD204: 0 | BE204: 0 | BF204: 0 | BG204: 0 | BJ204: 0 | BK204: 424 | BL204: 0 | BM204: 0 | BN204: 0 | BO204: 0 | BP204: 0 | BQ204: 0 | BR204: 0 | BS204: 0 | BT204: 0 | BU204: 0 | BW204: =_xlfn.XLOOKUP($A204,D!$O$3:$O$199,D!P$3:P$199,) | BX204: =_xlfn.XLOOKUP($A204,D!$O$3:$O$199,D!Q$3:Q$199,) | BY204: =_xlfn.XLOOKUP($A204,D!$O$3:$O$199,D!R$3:R$199,) | BZ204: =_xlfn.XLOOKUP($A204,D!$O$3:$O$199,D!S$3:S$199,) | CA204: =_xlfn.XLOOKUP($A204,D!$O$3:$O$199,D!T$3:T$199,) | CB204: =_xlfn.XLOOKUP($A204,D!$O$3:$O$199,D!U$3:U$199,) | CC204: =_xlfn.XLOOKUP($A204,D!$O$3:$O$199,D!V$3:V$199,) | CD204: =_xlfn.XLOOKUP($A204,D!$O$3:$O$199,D!W$3:W$199,) | ... CH204: =_xlfn.XLOOKUP($A204,D!$O$3:$O$199,D!AA$3:AA$199,)
A205: 10.03 | B205: =VLOOKUP(A205,PL.C!$B:$F,2,0) | C205: Analítica | D205: Entrada | E205: =VLOOKUP($A205,PL.C!$B:$F,5,0) | F205: sim | G205: forecast | I205: 0 | J205: 0 | K205: 0 | L205: 0 | M205: 0 | N205: 1109 | O205: 1458 | P205: 1835 | Q205: 2850 | R205: 762 | S205: 614 | T205: 2959 | V205: 4039 | W205: 1033 | X205: 1029 | Y205: 997 | Z205: 869 | AA205: 916 | AB205: 1657 | AC205: 764 | AD205: 783 | AE205: 1959 | AF205: 456 | AG205: 612 | AI205: 425 | AJ205: 10862 | AK205: 5968 | AL205: 1002 | AM205: 374 | AN205: 396 | AO205: 389 | AP205: 2848 | AQ205: 1126 | AR205: 6437 | AS205: 2605 | AT205: 3477 | AV205: 9230 | AW205: 1393 | AX205: 2030 | AY205: 1471 | AZ205: 2735 | BA205: 1832 | BB205: 1320 | BC205: 6770 | BD205: 4512 | BE205: 1745 | BF205: 0 | BG205: 2754 | BJ205: 571 | BK205: 4278 | BL205: 1821 | BM205: 767 | BN205: 881 | BO205: 3371 | BP205: 5488 | BQ205: 3414 | BR205: 2248 | BS205: 1848 | BT205: 2126 | BU205: 18485 | BW205: =_xlfn.XLOOKUP($A205,D!$O$3:$O$199,D!P$3:P$199,) | BX205: =_xlfn.XLOOKUP($A205,D!$O$3:$O$199,D!Q$3:Q$199,) | BY205: =_xlfn.XLOOKUP($A205,D!$O$3:$O$199,D!R$3:R$199,) | BZ205: =_xlfn.XLOOKUP($A205,D!$O$3:$O$199,D!S$3:S$199,) | CA205: =_xlfn.XLOOKUP($A205,D!$O$3:$O$199,D!T$3:T$199,) | CB205: =_xlfn.XLOOKUP($A205,D!$O$3:$O$199,D!U$3:U$199,) | CC205: =_xlfn.XLOOKUP($A205,D!$O$3:$O$199,D!V$3:V$199,) | CD205: =_xlfn.XLOOKUP($A205,D!$O$3:$O$199,D!W$3:W$199,) | ... CH205: =_xlfn.XLOOKUP($A205,D!$O$3:$O$199,D!AA$3:AA$199,)
A206: 10.04 | B206: =VLOOKUP(A206,PL.C!$B:$F,2,0) | C206: Analítica | D206: Saída | E206: =VLOOKUP($A206,PL.C!$B:$F,5,0) | F206: sim | G206: forecast | I206: 0 | J206: 0 | K206: 0 | L206: 0 | M206: 0 | N206: 0 | O206: 0 | P206: 0 | Q206: -56 | R206: -10 | S206: 0 | T206: 0 | V206: 0 | W206: 0 | X206: 0 | Y206: 0 | Z206: 0 | AA206: 0 | AB206: 0 | AC206: 0 | AD206: 0 | AE206: 0 | AF206: -268 | AG206: -22 | AI206: 0 | AJ206: 0 | AK206: 0 | AL206: 0 | AM206: 0 | AN206: 0 | AO206: 0 | AP206: 0 | AQ206: 0 | AR206: 0 | AS206: 0 | AT206: 0 | AV206: 0 | AW206: 0 | AX206: 0 | AY206: 0 | AZ206: 0 | BA206: 0 | BB206: 0 | BC206: 0 | BD206: 0 | BE206: 0 | BF206: 0 | BG206: 0 | BJ206: 0 | BK206: 0 | BL206: 0 | BM206: 0 | BN206: 0 | BO206: 0 | BP206: 0 | BQ206: 0 | BR206: 0 | BS206: 0 | BT206: 0 | BU206: 0 | BW206: =_xlfn.XLOOKUP($A206,D!$O$3:$O$199,D!P$3:P$199,) | BX206: =_xlfn.XLOOKUP($A206,D!$O$3:$O$199,D!Q$3:Q$199,) | BY206: =_xlfn.XLOOKUP($A206,D!$O$3:$O$199,D!R$3:R$199,) | BZ206: =_xlfn.XLOOKUP($A206,D!$O$3:$O$199,D!S$3:S$199,) | CA206: =_xlfn.XLOOKUP($A206,D!$O$3:$O$199,D!T$3:T$199,) | CB206: =_xlfn.XLOOKUP($A206,D!$O$3:$O$199,D!U$3:U$199,) | CC206: =_xlfn.XLOOKUP($A206,D!$O$3:$O$199,D!V$3:V$199,) | CD206: =_xlfn.XLOOKUP($A206,D!$O$3:$O$199,D!W$3:W$199,) | ... CH206: =_xlfn.XLOOKUP($A206,D!$O$3:$O$199,D!AA$3:AA$199,)
A207: 10.06 | B207: =VLOOKUP(A207,PL.C!$B:$F,2,0) | C207: Analítica | D207: Saída | E207: =VLOOKUP($A207,PL.C!$B:$F,5,0) | F207: sim | G207: forecast | I207: 0 | J207: -666 | K207: 0 | L207: -224 | M207: 0 | N207: -47 | O207: -870 | P207: -298 | Q207: -139 | R207: -199 | S207: -60 | T207: -898 | V207: -515 | W207: -274 | X207: -440 | Y207: -1154 | Z207: -431 | AA207: -249 | AB207: -181 | AC207: -196 | AD207: -174 | AE207: -346 | AF207: -127 | AG207: -312 | AI207: -323 | AJ207: -589 | AK207: -207 | AL207: -64 | AM207: -446 | AN207: -136 | AO207: -407 | AP207: -530 | AQ207: -96 | AR207: -287 | AS207: -1700 | AT207: -353 | AV207: -685 | AW207: -1000 | AX207: -1563 | AY207: -337 | AZ207: -648 | BA207: -1647 | BB207: -398 | BC207: -95 | BD207: -2863 | BE207: -183 | BF207: -718 | BG207: -2047 | BJ207: -408 | BK207: -294 | BL207: -676 | BM207: -4195 | BN207: -1695 | BO207: -619 | BP207: -426 | BQ207: -1113 | BR207: -626 | BS207: -777 | BT207: -936 | BU207: -274 | BW207: =_xlfn.XLOOKUP($A207,D!$O$3:$O$199,D!P$3:P$199,) | BX207: =_xlfn.XLOOKUP($A207,D!$O$3:$O$199,D!Q$3:Q$199,) | BY207: =_xlfn.XLOOKUP($A207,D!$O$3:$O$199,D!R$3:R$199,) | BZ207: =_xlfn.XLOOKUP($A207,D!$O$3:$O$199,D!S$3:S$199,) | CA207: =_xlfn.XLOOKUP($A207,D!$O$3:$O$199,D!T$3:T$199,) | CB207: =_xlfn.XLOOKUP($A207,D!$O$3:$O$199,D!U$3:U$199,) | CC207: =_xlfn.XLOOKUP($A207,D!$O$3:$O$199,D!V$3:V$199,) | CD207: =_xlfn.XLOOKUP($A207,D!$O$3:$O$199,D!W$3:W$199,) | ... CH207: =_xlfn.XLOOKUP($A207,D!$O$3:$O$199,D!AA$3:AA$199,)
A208: 10.07 | B208: =VLOOKUP(A208,PL.C!$B:$F,2,0) | C208: Analítica | D208: Saída | E208: Dedução da Receita | F208: sim | G208: forecast | I208: 0 | J208: 0 | K208: 0 | L208: 0 | M208: 0 | N208: 0 | O208: 0 | P208: -441 | Q208: 0 | R208: 0 | S208: 0 | T208: 0 | V208: 0 | W208: 0 | X208: 0 | Y208: 0 | Z208: 0 | AA208: 0 | AB208: 0 | AC208: 0 | AD208: 0 | AE208: 0 | AF208: 0 | AG208: 0 | AI208: 0 | AJ208: 0 | AK208: 0 | AL208: 0 | AM208: 0 | AN208: 0 | AO208: 0 | AP208: 0 | AQ208: 0 | AR208: 0 | AS208: 0 | AT208: 0 | AV208: 0 | AW208: 0 | AX208: 0 | AY208: 0 | AZ208: 0 | BA208: 0 | BB208: 0 | BC208: 0 | BD208: 0 | BE208: 0 | BF208: 0 | BG208: 0 | BJ208: 0 | BK208: 0 | BL208: 0 | BM208: 0 | BN208: 0 | BO208: 0 | BP208: 0 | BQ208: 0 | BR208: 0 | BS208: 0 | BT208: 0 | BU208: 0 | BW208: =_xlfn.XLOOKUP($A208,D!$O$3:$O$199,D!P$3:P$199,) | BX208: =_xlfn.XLOOKUP($A208,D!$O$3:$O$199,D!Q$3:Q$199,) | BY208: =_xlfn.XLOOKUP($A208,D!$O$3:$O$199,D!R$3:R$199,) | BZ208: =_xlfn.XLOOKUP($A208,D!$O$3:$O$199,D!S$3:S$199,) | CA208: =_xlfn.XLOOKUP($A208,D!$O$3:$O$199,D!T$3:T$199,) | CB208: =_xlfn.XLOOKUP($A208,D!$O$3:$O$199,D!U$3:U$199,) | CC208: =_xlfn.XLOOKUP($A208,D!$O$3:$O$199,D!V$3:V$199,) | CD208: =_xlfn.XLOOKUP($A208,D!$O$3:$O$199,D!W$3:W$199,) | ... CH208: =_xlfn.XLOOKUP($A208,D!$O$3:$O$199,D!AA$3:AA$199,)
A209: 10.08 | B209: =VLOOKUP(A209,PL.C!$B:$F,2,0) | C209: Analítica | D209: Saída | E209: Dedução da Receita | F209: sim | G209: forecast | I209: 0 | J209: 0 | K209: 0 | L209: 0 | M209: 0 | N209: 0 | O209: 0 | P209: 0 | Q209: 0 | R209: 0 | S209: 0 | T209: 0 | V209: 0 | W209: 0 | X209: 0 | Y209: 0 | Z209: 0 | AA209: 0 | AB209: 0 | AC209: 0 | AD209: 0 | AE209: 0 | AF209: 0 | AG209: 0 | AI209: 0 | AJ209: 0 | AK209: -5708 | AL209: 0 | AM209: 0 | AN209: 0 | AO209: 0 | AP209: 0 | AQ209: 0 | AR209: 0 | AS209: -43 | AT209: 0 | AV209: 0 | AW209: -806 | AX209: 0 | AY209: 0 | AZ209: 0 | BA209: 0 | BB209: 0 | BC209: 0 | BD209: 0 | BE209: -36 | BF209: 0 | BG209: -1775 | BJ209: 0 | BK209: 0 | BL209: 0 | BM209: 0 | BN209: 0 | BO209: 0 | BP209: 0 | BQ209: 0 | BR209: 0 | BS209: 0 | BT209: 0 | BU209: 0 | BW209: =_xlfn.XLOOKUP($A209,D!$O$3:$O$199,D!P$3:P$199,) | BX209: =_xlfn.XLOOKUP($A209,D!$O$3:$O$199,D!Q$3:Q$199,) | BY209: =_xlfn.XLOOKUP($A209,D!$O$3:$O$199,D!R$3:R$199,) | BZ209: =_xlfn.XLOOKUP($A209,D!$O$3:$O$199,D!S$3:S$199,) | CA209: =_xlfn.XLOOKUP($A209,D!$O$3:$O$199,D!T$3:T$199,) | CB209: =_xlfn.XLOOKUP($A209,D!$O$3:$O$199,D!U$3:U$199,) | CC209: =_xlfn.XLOOKUP($A209,D!$O$3:$O$199,D!V$3:V$199,) | CD209: =_xlfn.XLOOKUP($A209,D!$O$3:$O$199,D!W$3:W$199,) | ... CH209: =_xlfn.XLOOKUP($A209,D!$O$3:$O$199,D!AA$3:AA$199,)
A210: 20.01 | B210: =VLOOKUP(A210,PL.C!$B:$F,2,0) | C210: Analítica | D210: Saída | E210: =VLOOKUP($A210,PL.C!$B:$F,5,0) | F210: sim | G210: forecast | I210: 0 | J210: 0 | K210: 0 | L210: -17145 | M210: -40272 | N210: -11766 | O210: -25370 | P210: -35444 | Q210: -23590 | R210: -13045 | S210: -24365 | T210: -13572 | V210: 0 | W210: -96 | X210: -96 | Y210: -112 | Z210: -13864 | AA210: -21137 | AB210: -26746 | AC210: -1262 | AD210: -14899 | AE210: -18945 | AF210: -16601 | AG210: 0 | AI210: -3105 | AJ210: -10384 | AK210: -28789 | AL210: 0 | AM210: -13909 | AN210: -13163 | AO210: -22284 | AP210: -8500 | AQ210: -17373 | AR210: -23021 | AS210: -8071 | AT210: -22326 | AV210: 0 | AW210: 0 | AX210: -10404 | AY210: -16712 | AZ210: -14283 | BA210: -11672 | BB210: -16337 | BC210: -26883 | BD210: -17415 | BE210: -20904 | BF210: -29056 | BG210: -9544 | BJ210: -8435 | BK210: -28656 | BL210: -23857 | BM210: -7511 | BN210: -38603 | BO210: -18974 | BP210: -15919 | BQ210: -30164 | BR210: -35516 | BS210: -17975 | BT210: -6873 | BU210: -46228 | BW210: =_xlfn.XLOOKUP($A210,D!$O$3:$O$199,D!P$3:P$199,) | BX210: =_xlfn.XLOOKUP($A210,D!$O$3:$O$199,D!Q$3:Q$199,) | BY210: =_xlfn.XLOOKUP($A210,D!$O$3:$O$199,D!R$3:R$199,) | BZ210: =_xlfn.XLOOKUP($A210,D!$O$3:$O$199,D!S$3:S$199,) | CA210: =_xlfn.XLOOKUP($A210,D!$O$3:$O$199,D!T$3:T$199,) | CB210: =_xlfn.XLOOKUP($A210,D!$O$3:$O$199,D!U$3:U$199,) | CC210: =_xlfn.XLOOKUP($A210,D!$O$3:$O$199,D!V$3:V$199,) | CD210: =_xlfn.XLOOKUP($A210,D!$O$3:$O$199,D!W$3:W$199,) | ... CH210: =_xlfn.XLOOKUP($A210,D!$O$3:$O$199,D!AA$3:AA$199,)
A211: 20.04 | B211: =VLOOKUP(A211,PL.C!$B:$F,2,0) | C211: Analítica | D211: Saída | E211: =VLOOKUP($A211,PL.C!$B:$F,5,0) | F211: sim | G211: forecast | I211: 0 | J211: 0 | K211: 0 | L211: -35059 | M211: -30798 | N211: -41380 | O211: -38287 | P211: -44424 | Q211: -31023 | R211: -34511 | S211: -30476 | T211: -35359 | V211: -34259 | W211: -33077 | X211: -40001 | Y211: -37496 | Z211: -37077 | AA211: -43596 | AB211: -37086 | AC211: -46579 | AD211: -34604 | AE211: -37097 | AF211: -36170 | AG211: -33113 | AI211: -36801 | AJ211: -34023 | AK211: -29305 | AL211: -37253 | AM211: -37806 | AN211: -38873 | AO211: -41015 | AP211: -47607 | AQ211: -35633 | AR211: -38523 | AS211: -37403 | AT211: -37766 | AV211: -45122 | AW211: -39439 | AX211: -42345 | AY211: -41713 | AZ211: -40965 | BA211: -50128 | BB211: -58537 | BC211: -47156 | BD211: -51989 | BE211: -54647 | BF211: -50015 | BG211: -47525 | BJ211: -54805 | BK211: -50998 | BL211: -52013 | BM211: -48208 | BN211: -57014 | BO211: -48145 | BP211: -68086 | BQ211: -59927 | BR211: -56345 | BS211: -46989 | BT211: -61535 | BU211: -62195 | BW211: =_xlfn.XLOOKUP($A211,D!$O$3:$O$199,D!P$3:P$199,) | BX211: =_xlfn.XLOOKUP($A211,D!$O$3:$O$199,D!Q$3:Q$199,) | BY211: =_xlfn.XLOOKUP($A211,D!$O$3:$O$199,D!R$3:R$199,) | BZ211: =_xlfn.XLOOKUP($A211,D!$O$3:$O$199,D!S$3:S$199,) | CA211: =_xlfn.XLOOKUP($A211,D!$O$3:$O$199,D!T$3:T$199,) | CB211: =_xlfn.XLOOKUP($A211,D!$O$3:$O$199,D!U$3:U$199,) | CC211: =_xlfn.XLOOKUP($A211,D!$O$3:$O$199,D!V$3:V$199,) | CD211: =_xlfn.XLOOKUP($A211,D!$O$3:$O$199,D!W$3:W$199,) | ... CH211: =_xlfn.XLOOKUP($A211,D!$O$3:$O$199,D!AA$3:AA$199,)
A212: 20.05 | B212: DIFAL | C212: Analítica | D212: Saída | E212: Dedução da Receita | F212: sim | G212: forecast | I212: 0 | J212: 0 | K212: 0 | L212: 0 | M212: 0 | N212: 0 | O212: 0 | P212: -199 | Q212: -199 | R212: -199 | S212: 0 | T212: 0 | V212: 0 | W212: 0 | X212: 0 | Y212: 0 | Z212: 0 | AA212: 0 | AB212: 0 | AC212: 0 | AD212: 0 | AE212: 0 | AF212: 0 | AG212: 0 | AI212: 0 | AJ212: 0 | AK212: 0 | AL212: 0 | AM212: 0 | AN212: 0 | AO212: 0 | AP212: 0 | AQ212: 0 | AR212: 0 | AS212: 0 | AT212: 0 | AV212: 0 | AW212: 0 | AX212: 0 | AY212: 0 | AZ212: 0 | BA212: 0 | BB212: 0 | BC212: 0 | BD212: 0 | BE212: 0 | BF212: 0 | BG212: 0 | BJ212: 0 | BK212: 0 | BL212: 0 | BM212: 0 | BN212: 0 | BO212: 0 | BP212: 0 | BQ212: 0 | BR212: 0 | BS212: 0 | BT212: 0 | BU212: 0 | BW212: =_xlfn.XLOOKUP($A212,D!$O$3:$O$199,D!P$3:P$199,) | BX212: =_xlfn.XLOOKUP($A212,D!$O$3:$O$199,D!Q$3:Q$199,) | BY212: =_xlfn.XLOOKUP($A212,D!$O$3:$O$199,D!R$3:R$199,) | BZ212: =_xlfn.XLOOKUP($A212,D!$O$3:$O$199,D!S$3:S$199,) | CA212: =_xlfn.XLOOKUP($A212,D!$O$3:$O$199,D!T$3:T$199,) | CB212: =_xlfn.XLOOKUP($A212,D!$O$3:$O$199,D!U$3:U$199,) | CC212: =_xlfn.XLOOKUP($A212,D!$O$3:$O$199,D!V$3:V$199,) | CD212: =_xlfn.XLOOKUP($A212,D!$O$3:$O$199,D!W$3:W$199,) | ... CH212: =_xlfn.XLOOKUP($A212,D!$O$3:$O$199,D!AA$3:AA$199,)
A213: 21.01 | B213: =VLOOKUP(A213,PL.C!$B:$F,2,0) | C213: Analítica | D213: Entrada | E213: =VLOOKUP($A213,PL.C!$B:$F,5,0) | F213: sim | G213: forecast | I213: 0 | J213: 0 | K213: 0 | L213: 0 | M213: 0 | N213: 0 | O213: 0 | P213: 0 | Q213: 0 | R213: 0 | S213: 0 | T213: 0 | V213: 0 | W213: 0 | X213: 0 | Y213: 0 | Z213: 0 | AA213: 0 | AB213: 0 | AC213: 0 | AD213: 0 | AE213: 0 | AF213: 0 | AG213: 0 | AI213: 0 | AJ213: 0 | AK213: 0 | AL213: 0 | AM213: 0 | AN213: 0 | AO213: 0 | AP213: 0 | AQ213: 0 | AR213: 0 | AS213: 0 | AT213: 0 | AV213: 0 | AW213: 0 | AX213: 0 | AY213: 0 | AZ213: 0 | BA213: 0 | BB213: 0 | BC213: 0 | BD213: 0 | BE213: 0 | BF213: 0 | BG213: 0 | BJ213: 0 | BK213: 0 | BL213: 0 | BM213: 0 | BN213: 0 | BO213: 0 | BP213: 0 | BQ213: 0 | BR213: 0 | BS213: 0 | BT213: 0 | BU213: 0 | BW213: =_xlfn.XLOOKUP($A213,D!$O$3:$O$199,D!P$3:P$199,) | BX213: =_xlfn.XLOOKUP($A213,D!$O$3:$O$199,D!Q$3:Q$199,) | BY213: =_xlfn.XLOOKUP($A213,D!$O$3:$O$199,D!R$3:R$199,) | BZ213: =_xlfn.XLOOKUP($A213,D!$O$3:$O$199,D!S$3:S$199,) | CA213: =_xlfn.XLOOKUP($A213,D!$O$3:$O$199,D!T$3:T$199,) | CB213: =_xlfn.XLOOKUP($A213,D!$O$3:$O$199,D!U$3:U$199,) | CC213: =_xlfn.XLOOKUP($A213,D!$O$3:$O$199,D!V$3:V$199,) | CD213: =_xlfn.XLOOKUP($A213,D!$O$3:$O$199,D!W$3:W$199,) | ... CH213: =_xlfn.XLOOKUP($A213,D!$O$3:$O$199,D!AA$3:AA$199,)
A214: 21.02 | B214: =VLOOKUP(A214,PL.C!$B:$F,2,0) | C214: Analítica | D214: Entrada | E214: =VLOOKUP($A214,PL.C!$B:$F,5,0) | F214: sim | G214: forecast | I214: 0 | J214: 0 | K214: 0 | L214: 0 | M214: 0 | N214: 0 | O214: 0 | P214: 0 | Q214: 0 | R214: 0 | S214: 0 | T214: 0 | V214: 0 | W214: 0 | X214: 0 | Y214: 0 | Z214: 0 | AA214: 0 | AB214: 0 | AC214: 0 | AD214: 0 | AE214: 0 | AF214: 0 | AG214: 0 | AI214: 0 | AJ214: 0 | AK214: 0 | AL214: 0 | AM214: 0 | AN214: 0 | AO214: 0 | AP214: 0 | AQ214: 0 | AR214: 0 | AS214: 0 | AT214: 0 | AV214: 0 | AW214: 0 | AX214: 0 | AY214: 0 | AZ214: 0 | BA214: 0 | BB214: 0 | BC214: 0 | BD214: 0 | BE214: 0 | BF214: 0 | BG214: 0 | BJ214: 0 | BK214: 0 | BL214: 0 | BM214: 0 | BN214: 0 | BO214: 0 | BP214: 0 | BQ214: 0 | BR214: 0 | BS214: 0 | BT214: 0 | BU214: 0 | BW214: =_xlfn.XLOOKUP($A214,D!$O$3:$O$199,D!P$3:P$199,) | BX214: =_xlfn.XLOOKUP($A214,D!$O$3:$O$199,D!Q$3:Q$199,) | BY214: =_xlfn.XLOOKUP($A214,D!$O$3:$O$199,D!R$3:R$199,) | BZ214: =_xlfn.XLOOKUP($A214,D!$O$3:$O$199,D!S$3:S$199,) | CA214: =_xlfn.XLOOKUP($A214,D!$O$3:$O$199,D!T$3:T$199,) | CB214: =_xlfn.XLOOKUP($A214,D!$O$3:$O$199,D!U$3:U$199,) | CC214: =_xlfn.XLOOKUP($A214,D!$O$3:$O$199,D!V$3:V$199,) | CD214: =_xlfn.XLOOKUP($A214,D!$O$3:$O$199,D!W$3:W$199,) | ... CH214: =_xlfn.XLOOKUP($A214,D!$O$3:$O$199,D!AA$3:AA$199,)
A215: 21.03 | B215: =VLOOKUP(A215,PL.C!$B:$F,2,0) | C215: Analítica | D215: Entrada | E215: =VLOOKUP($A215,PL.C!$B:$F,5,0) | F215: sim | G215: forecast | I215: 0 | J215: 0 | K215: 0 | L215: 0 | M215: 0 | N215: 0 | O215: 0 | P215: 0 | Q215: 0 | R215: 0 | S215: 0 | T215: 0 | V215: 0 | W215: 0 | X215: 0 | Y215: 0 | Z215: 0 | AA215: 0 | AB215: 0 | AC215: 0 | AD215: 0 | AE215: 0 | AF215: 0 | AG215: 0 | AI215: 0 | AJ215: 0 | AK215: 0 | AL215: 0 | AM215: 0 | AN215: 0 | AO215: 0 | AP215: 0 | AQ215: 0 | AR215: 0 | AS215: 0 | AT215: 0 | AV215: 0 | AW215: 0 | AX215: 0 | AY215: 0 | AZ215: 0 | BA215: 0 | BB215: 0 | BC215: 0 | BD215: 0 | BE215: 0 | BF215: 0 | BG215: 0 | BJ215: 0 | BK215: 0 | BL215: 0 | BM215: 0 | BN215: 0 | BO215: 0 | BP215: 0 | BQ215: 0 | BR215: 0 | BS215: 0 | BT215: 0 | BU215: 0 | BW215: =_xlfn.XLOOKUP($A215,D!$O$3:$O$199,D!P$3:P$199,) | BX215: =_xlfn.XLOOKUP($A215,D!$O$3:$O$199,D!Q$3:Q$199,) | BY215: =_xlfn.XLOOKUP($A215,D!$O$3:$O$199,D!R$3:R$199,) | BZ215: =_xlfn.XLOOKUP($A215,D!$O$3:$O$199,D!S$3:S$199,) | CA215: =_xlfn.XLOOKUP($A215,D!$O$3:$O$199,D!T$3:T$199,) | CB215: =_xlfn.XLOOKUP($A215,D!$O$3:$O$199,D!U$3:U$199,) | CC215: =_xlfn.XLOOKUP($A215,D!$O$3:$O$199,D!V$3:V$199,) | CD215: =_xlfn.XLOOKUP($A215,D!$O$3:$O$199,D!W$3:W$199,) | ... CH215: =_xlfn.XLOOKUP($A215,D!$O$3:$O$199,D!AA$3:AA$199,)
A216: 22.01 | B216: =VLOOKUP(A216,PL.C!$B:$F,2,0) | C216: Analítica | D216: Saída | E216: =VLOOKUP($A216,PL.C!$B:$F,5,0) | F216: sim | G216: forecast | I216: 0 | J216: 0 | K216: 0 | L216: 0 | M216: -3638 | N216: -5703 | O216: -9759 | P216: -8530 | Q216: -7664 | R216: -10049 | S216: -8512 | T216: -8996 | V216: -9110 | W216: -9303 | X216: -10624 | Y216: -11355 | Z216: -8687 | AA216: -9074 | AB216: -11941 | AC216: -10053 | AD216: -13302 | AE216: -8302 | AF216: -8445 | AG216: -9682 | AI216: -10198 | AJ216: -11302 | AK216: -12459 | AL216: -9887 | AM216: -9844 | AN216: -7015 | AO216: -8369 | AP216: -4259 | AQ216: -5587 | AR216: -2795 | AS216: -2913 | AT216: -3183 | AV216: -3072 | AW216: -1228 | AX216: -4603 | AY216: -2537 | AZ216: -500 | BA216: -2897 | BB216: -1821 | BC216: -3121 | BD216: -735 | BE216: -1698 | BF216: -570 | BG216: -725 | BJ216: -4473 | BK216: -563 | BL216: -505 | BM216: -2492 | BN216: -2188 | BO216: -659 | BP216: -997 | BQ216: 0 | BR216: -2021 | BS216: -507 | BT216: -1831 | BU216: -1067 | BW216: =_xlfn.XLOOKUP($A216,D!$O$3:$O$199,D!P$3:P$199,) | BX216: =_xlfn.XLOOKUP($A216,D!$O$3:$O$199,D!Q$3:Q$199,) | BY216: =_xlfn.XLOOKUP($A216,D!$O$3:$O$199,D!R$3:R$199,) | BZ216: =_xlfn.XLOOKUP($A216,D!$O$3:$O$199,D!S$3:S$199,) | CA216: =_xlfn.XLOOKUP($A216,D!$O$3:$O$199,D!T$3:T$199,) | CB216: =_xlfn.XLOOKUP($A216,D!$O$3:$O$199,D!U$3:U$199,) | CC216: =_xlfn.XLOOKUP($A216,D!$O$3:$O$199,D!V$3:V$199,) | CD216: =_xlfn.XLOOKUP($A216,D!$O$3:$O$199,D!W$3:W$199,) | ... CH216: =_xlfn.XLOOKUP($A216,D!$O$3:$O$199,D!AA$3:AA$199,)
A217: 29.01 | B217: =VLOOKUP(A217,PL.C!$B:$F,2,0) | C217: Analítica | D217: Saída | E217: =VLOOKUP($A217,PL.C!$B:$F,5,0) | F217: sim | G217: forecast | I217: 0 | J217: 0 | K217: 0 | L217: -46649 | M217: -82109 | N217: -83280 | O217: -52046 | P217: -50725 | Q217: -55318 | R217: -50980 | S217: -54279 | T217: -59238 | V217: -60514 | W217: -52381 | X217: -50287 | Y217: -48449 | Z217: -52967 | AA217: -55206 | AB217: -54213 | AC217: -49905 | AD217: -55517 | AE217: -52928 | AF217: -53237 | AG217: -76077 | AI217: -62756 | AJ217: -55514 | AK217: -53898 | AL217: -55008 | AM217: -56890 | AN217: -57893 | AO217: -57102 | AP217: -60049 | AQ217: -59562 | AR217: -57235 | AS217: -54569 | AT217: -57010 | AV217: -56100 | AW217: -82773 | AX217: -69486 | AY217: -61481 | AZ217: -63690 | BA217: -64547 | BB217: -63710 | BC217: -65887 | BD217: -70236 | BE217: -67974 | BF217: -64982 | BG217: -65086 | BJ217: -95726 | BK217: -67540 | BL217: -68723 | BM217: -68992 | BN217: -68950 | BO217: -63967 | BP217: -67857 | BQ217: -61617 | BR217: -75522 | BS217: -67811 | BT217: -65086 | BU217: -63557 | BW217: =_xlfn.XLOOKUP($A217,D!$O$3:$O$199,D!P$3:P$199,) | BX217: =_xlfn.XLOOKUP($A217,D!$O$3:$O$199,D!Q$3:Q$199,) | BY217: =_xlfn.XLOOKUP($A217,D!$O$3:$O$199,D!R$3:R$199,) | BZ217: =_xlfn.XLOOKUP($A217,D!$O$3:$O$199,D!S$3:S$199,) | CA217: =_xlfn.XLOOKUP($A217,D!$O$3:$O$199,D!T$3:T$199,) | CB217: =_xlfn.XLOOKUP($A217,D!$O$3:$O$199,D!U$3:U$199,) | CC217: =_xlfn.XLOOKUP($A217,D!$O$3:$O$199,D!V$3:V$199,) | CD217: =_xlfn.XLOOKUP($A217,D!$O$3:$O$199,D!W$3:W$199,) | ... CH217: =_xlfn.XLOOKUP($A217,D!$O$3:$O$199,D!AA$3:AA$199,)
A218: 29.02 | B218: =VLOOKUP(A218,PL.C!$B:$F,2,0) | C218: Analítica | D218: Saída | E218: =VLOOKUP($A218,PL.C!$B:$F,5,0) | F218: sim | G218: forecast | I218: 0 | J218: 0 | K218: 0 | L218: 0 | M218: 0 | N218: 0 | O218: 0 | P218: 0 | Q218: -19039 | R218: -20971 | S218: -21279 | T218: -17739 | V218: 0 | W218: 0 | X218: -1989 | Y218: 0 | Z218: -1600 | AA218: 0 | AB218: 0 | AC218: 0 | AD218: -20005 | AE218: -20005 | AF218: -20005 | AG218: -23346 | AI218: 0 | AJ218: 0 | AK218: 0 | AL218: 0 | AM218: -1351 | AN218: 0 | AO218: 0 | AP218: 0 | AQ218: -19734 | AR218: -20550 | AS218: -21089 | AT218: -13739 | AV218: 0 | AW218: -2371 | AX218: 0 | AY218: 0 | AZ218: 0 | BA218: 0 | BB218: -3693 | BC218: 0 | BD218: -20750 | BE218: -21340 | BF218: -22055 | BG218: -22632 | BJ218: -319 | BK218: 0 | BL218: 0 | BM218: -5059 | BN218: 0 | BO218: 0 | BP218: 0 | BQ218: -1512 | BR218: -20441 | BS218: -20441 | BT218: -22209 | BU218: -18092 | BW218: =_xlfn.XLOOKUP($A218,D!$O$3:$O$199,D!P$3:P$199,) | BX218: =_xlfn.XLOOKUP($A218,D!$O$3:$O$199,D!Q$3:Q$199,) | BY218: =_xlfn.XLOOKUP($A218,D!$O$3:$O$199,D!R$3:R$199,) | BZ218: =_xlfn.XLOOKUP($A218,D!$O$3:$O$199,D!S$3:S$199,) | CA218: =_xlfn.XLOOKUP($A218,D!$O$3:$O$199,D!T$3:T$199,) | CB218: =_xlfn.XLOOKUP($A218,D!$O$3:$O$199,D!U$3:U$199,) | CC218: =_xlfn.XLOOKUP($A218,D!$O$3:$O$199,D!V$3:V$199,) | CD218: =_xlfn.XLOOKUP($A218,D!$O$3:$O$199,D!W$3:W$199,) | ... CH218: =_xlfn.XLOOKUP($A218,D!$O$3:$O$199,D!AA$3:AA$199,)
A219: 29.03 | B219: =VLOOKUP(A219,PL.C!$B:$F,2,0) | C219: Analítica | D219: Saída | E219: =VLOOKUP($A219,PL.C!$B:$F,5,0) | F219: sim | G219: forecast | I219: 0 | J219: -70 | K219: 0 | L219: -8358 | M219: -4706 | N219: -4421 | O219: -13272 | P219: -1932 | Q219: -5966 | R219: -11314 | S219: -4033 | T219: -3973 | V219: -21164 | W219: -15633 | X219: -12387 | Y219: -6140 | Z219: -5814 | AA219: -4322 | AB219: -9678 | AC219: -1989 | AD219: -6139 | AE219: -10120 | AF219: -10120 | AG219: -7052 | AI219: -11195 | AJ219: -16851 | AK219: -16093 | AL219: -4535 | AM219: -3072 | AN219: -4747 | AO219: -3859 | AP219: -2175 | AQ219: -6339 | AR219: -10219 | AS219: -6721 | AT219: -6547 | AV219: -13478 | AW219: -13483 | AX219: -9733 | AY219: -12282 | AZ219: -3308 | BA219: -4390 | BB219: -9316 | BC219: -2393 | BD219: -2600 | BE219: -7393 | BF219: -7393 | BG219: -2525 | BJ219: -13403 | BK219: -21825 | BL219: -15885 | BM219: -6868 | BN219: -8595 | BO219: 0 | BP219: -10119 | BQ219: -2529 | BR219: -11832 | BS219: -9208 | BT219: -9369 | BU219: -3069 | BW219: =_xlfn.XLOOKUP($A219,D!$O$3:$O$199,D!P$3:P$199,) | BX219: =_xlfn.XLOOKUP($A219,D!$O$3:$O$199,D!Q$3:Q$199,) | BY219: =_xlfn.XLOOKUP($A219,D!$O$3:$O$199,D!R$3:R$199,) | BZ219: =_xlfn.XLOOKUP($A219,D!$O$3:$O$199,D!S$3:S$199,) | CA219: =_xlfn.XLOOKUP($A219,D!$O$3:$O$199,D!T$3:T$199,) | CB219: =_xlfn.XLOOKUP($A219,D!$O$3:$O$199,D!U$3:U$199,) | CC219: =_xlfn.XLOOKUP($A219,D!$O$3:$O$199,D!V$3:V$199,) | CD219: =_xlfn.XLOOKUP($A219,D!$O$3:$O$199,D!W$3:W$199,) | ... CH219: =_xlfn.XLOOKUP($A219,D!$O$3:$O$199,D!AA$3:AA$199,)
A220: 29.04 | B220: =VLOOKUP(A220,PL.C!$B:$F,2,0) | C220: Analítica | D220: Saída | E220: =VLOOKUP($A220,PL.C!$B:$F,5,0) | F220: sim | G220: forecast | I220: 0 | J220: 0 | K220: 0 | L220: -4968 | M220: 0 | N220: 0 | O220: -3470 | P220: 0 | Q220: -8 | R220: 0 | S220: 0 | T220: 0 | V220: -2450 | W220: -3756 | X220: 0 | Y220: 0 | Z220: 0 | AA220: 0 | AB220: -2760 | AC220: 0 | AD220: 0 | AE220: 0 | AF220: 0 | AG220: -4074 | AI220: -2866 | AJ220: 0 | AK220: -7934 | AL220: -4512 | AM220: -1204 | AN220: -3655 | AO220: -1279 | AP220: -160 | AQ220: 0 | AR220: 0 | AS220: 0 | AT220: -3997 | AV220: -10248 | AW220: -1252 | AX220: 0 | AY220: -7494 | AZ220: 0 | BA220: -1233 | BB220: 0 | BC220: -6188 | BD220: -5964 | BE220: -2516 | BF220: 0 | BG220: 0 | BJ220: 0 | BK220: -204 | BL220: -1481 | BM220: -10901 | BN220: -1051 | BO220: -7966 | BP220: -1123 | BQ220: -17006 | BR220: -23014 | BS220: 0 | BT220: -1340 | BU220: 0 | BW220: =_xlfn.XLOOKUP($A220,D!$O$3:$O$199,D!P$3:P$199,) | BX220: =_xlfn.XLOOKUP($A220,D!$O$3:$O$199,D!Q$3:Q$199,) | BY220: =_xlfn.XLOOKUP($A220,D!$O$3:$O$199,D!R$3:R$199,) | BZ220: =_xlfn.XLOOKUP($A220,D!$O$3:$O$199,D!S$3:S$199,) | CA220: =_xlfn.XLOOKUP($A220,D!$O$3:$O$199,D!T$3:T$199,) | CB220: =_xlfn.XLOOKUP($A220,D!$O$3:$O$199,D!U$3:U$199,) | CC220: =_xlfn.XLOOKUP($A220,D!$O$3:$O$199,D!V$3:V$199,) | CD220: =_xlfn.XLOOKUP($A220,D!$O$3:$O$199,D!W$3:W$199,) | ... CH220: =_xlfn.XLOOKUP($A220,D!$O$3:$O$199,D!AA$3:AA$199,)
A221: 29.05 | B221: =VLOOKUP(A221,PL.C!$B:$F,2,0) | C221: Analítica | D221: Saída | E221: =VLOOKUP($A221,PL.C!$B:$F,5,0) | F221: sim | G221: forecast | I221: 0 | J221: 0 | K221: 0 | L221: 0 | M221: 0 | N221: 0 | O221: 0 | P221: 0 | Q221: 0 | R221: 0 | S221: 0 | T221: 0 | V221: 0 | W221: -1381 | X221: 0 | Y221: 0 | Z221: 0 | AA221: 0 | AB221: -5050 | AC221: 0 | AD221: 0 | AE221: 0 | AF221: 0 | AG221: 0 | AI221: -2806 | AJ221: 0 | AK221: -6125 | AL221: -6776 | AM221: -52 | AN221: 0 | AO221: 0 | AP221: 0 | AQ221: 0 | AR221: 0 | AS221: 0 | AT221: -3606 | AV221: -6970 | AW221: 0 | AX221: 0 | AY221: -4060 | AZ221: 0 | BA221: 0 | BB221: 0 | BC221: 0 | BD221: -828 | BE221: 0 | BF221: 0 | BG221: 0 | BJ221: 0 | BK221: 0 | BL221: 0 | BM221: -6019 | BN221: -114 | BO221: -10193 | BP221: 0 | BQ221: -1793 | BR221: -26602 | BS221: 0 | BT221: 0 | BU221: 0 | BW221: =_xlfn.XLOOKUP($A221,D!$O$3:$O$199,D!P$3:P$199,) | BX221: =_xlfn.XLOOKUP($A221,D!$O$3:$O$199,D!Q$3:Q$199,) | BY221: =_xlfn.XLOOKUP($A221,D!$O$3:$O$199,D!R$3:R$199,) | BZ221: =_xlfn.XLOOKUP($A221,D!$O$3:$O$199,D!S$3:S$199,) | CA221: =_xlfn.XLOOKUP($A221,D!$O$3:$O$199,D!T$3:T$199,) | CB221: =_xlfn.XLOOKUP($A221,D!$O$3:$O$199,D!U$3:U$199,) | CC221: =_xlfn.XLOOKUP($A221,D!$O$3:$O$199,D!V$3:V$199,) | CD221: =_xlfn.XLOOKUP($A221,D!$O$3:$O$199,D!W$3:W$199,) | ... CH221: =_xlfn.XLOOKUP($A221,D!$O$3:$O$199,D!AA$3:AA$199,)
A222: 29.06 | B222: =VLOOKUP(A222,PL.C!$B:$F,2,0) | C222: Analítica | D222: Saída | E222: =VLOOKUP($A222,PL.C!$B:$F,5,0) | F222: sim | G222: forecast | I222: 0 | J222: 0 | K222: 0 | L222: -43510 | M222: -37129 | N222: -38920 | O222: -38389 | P222: -42139 | Q222: -40061 | R222: -39922 | S222: -39402 | T222: -76311 | V222: -41546 | W222: -42528 | X222: -42395 | Y222: -43329 | Z222: -41036 | AA222: -40139 | AB222: -40320 | AC222: -42679 | AD222: -40024 | AE222: -41900 | AF222: -40759 | AG222: -88709 | AI222: -44552 | AJ222: -44969 | AK222: -44735 | AL222: -44735 | AM222: -42671 | AN222: -43326 | AO222: -41133 | AP222: -42028 | AQ222: -39470 | AR222: -39731 | AS222: -39561 | AT222: -74868 | AV222: -41526 | AW222: -57794 | AX222: -50930 | AY222: -46442 | AZ222: -45719 | BA222: -45103 | BB222: -44994 | BC222: -47885 | BD222: -48571 | BE222: -47725 | BF222: -46114 | BG222: -85095 | BJ222: -56391 | BK222: -51537 | BL222: -51667 | BM222: -51186 | BN222: -48767 | BO222: -47345 | BP222: -46485 | BQ222: -50540 | BR222: -49717 | BS222: -47907 | BT222: -46824 | BU222: -84944 | BW222: =_xlfn.XLOOKUP($A222,D!$O$3:$O$199,D!P$3:P$199,) | BX222: =_xlfn.XLOOKUP($A222,D!$O$3:$O$199,D!Q$3:Q$199,) | BY222: =_xlfn.XLOOKUP($A222,D!$O$3:$O$199,D!R$3:R$199,) | BZ222: =_xlfn.XLOOKUP($A222,D!$O$3:$O$199,D!S$3:S$199,) | CA222: =_xlfn.XLOOKUP($A222,D!$O$3:$O$199,D!T$3:T$199,) | CB222: =_xlfn.XLOOKUP($A222,D!$O$3:$O$199,D!U$3:U$199,) | CC222: =_xlfn.XLOOKUP($A222,D!$O$3:$O$199,D!V$3:V$199,) | CD222: =_xlfn.XLOOKUP($A222,D!$O$3:$O$199,D!W$3:W$199,) | ... CH222: =_xlfn.XLOOKUP($A222,D!$O$3:$O$199,D!AA$3:AA$199,)
A223: 29.07 | B223: =VLOOKUP(A223,PL.C!$B:$F,2,0) | C223: Analítica | D223: Saída | E223: =VLOOKUP($A223,PL.C!$B:$F,5,0) | F223: sim | G223: forecast | I223: 0 | J223: 0 | K223: 0 | L223: -13717 | M223: -6602 | N223: -6474 | O223: -12083 | P223: -7636 | Q223: -6891 | R223: -7255 | S223: -7095 | T223: -11650 | V223: -11817 | W223: -7065 | X223: -7208 | Y223: -7806 | Z223: -6848 | AA223: -6702 | AB223: -6936 | AC223: -7547 | AD223: -6492 | AE223: -7030 | AF223: -6861 | AG223: -13170 | AI223: -12528 | AJ223: -7499 | AK223: -7338 | AL223: -7914 | AM223: -7053 | AN223: -6752 | AO223: -7152 | AP223: -8090 | AQ223: -7132 | AR223: -7332 | AS223: -7143 | AT223: -11104 | AV223: -10654 | AW223: -10556 | AX223: -8969 | AY223: -7893 | AZ223: -7928 | BA223: -7787 | BB223: -7816 | BC223: -8229 | BD223: -8304 | BE223: -8259 | BF223: -8310 | BG223: -12373 | BJ223: -15675 | BK223: -9701 | BL223: -9476 | BM223: -9329 | BN223: -8637 | BO223: -8259 | BP223: -8285 | BQ223: -9998 | BR223: -8802 | BS223: -8053 | BT223: -8277 | BU223: -12448 | BW223: =_xlfn.XLOOKUP($A223,D!$O$3:$O$199,D!P$3:P$199,) | BX223: =_xlfn.XLOOKUP($A223,D!$O$3:$O$199,D!Q$3:Q$199,) | BY223: =_xlfn.XLOOKUP($A223,D!$O$3:$O$199,D!R$3:R$199,) | BZ223: =_xlfn.XLOOKUP($A223,D!$O$3:$O$199,D!S$3:S$199,) | CA223: =_xlfn.XLOOKUP($A223,D!$O$3:$O$199,D!T$3:T$199,) | CB223: =_xlfn.XLOOKUP($A223,D!$O$3:$O$199,D!U$3:U$199,) | CC223: =_xlfn.XLOOKUP($A223,D!$O$3:$O$199,D!V$3:V$199,) | CD223: =_xlfn.XLOOKUP($A223,D!$O$3:$O$199,D!W$3:W$199,) | ... CH223: =_xlfn.XLOOKUP($A223,D!$O$3:$O$199,D!AA$3:AA$199,)
A224: 29.08 | B224: =VLOOKUP(A224,PL.C!$B:$F,2,0) | C224: Analítica | D224: Saída | E224: =VLOOKUP($A224,PL.C!$B:$F,5,0) | F224: sim | G224: forecast | I224: 0 | J224: 0 | K224: 0 | L224: -3145 | M224: -2674 | N224: -2727 | O224: -2763 | P224: -3344 | Q224: -2674 | R224: -2706 | S224: -2690 | T224: -3822 | V224: -1561 | W224: -1781 | X224: -2262 | Y224: -2660 | Z224: -1615 | AA224: -1658 | AB224: -1735 | AC224: -3001 | AD224: -1597 | AE224: -1639 | AF224: -1618 | AG224: -3943 | AI224: -2067 | AJ224: -2258 | AK224: -2698 | AL224: -3087 | AM224: -2025 | AN224: -2564 | AO224: -2018 | AP224: -3664 | AQ224: -1988 | AR224: -2065 | AS224: -2004 | AT224: -2048 | AV224: -4074 | AW224: -4778 | AX224: 0 | AY224: -6260 | AZ224: -2501 | BA224: -2290 | BB224: -2145 | BC224: -2145 | BD224: -2145 | BE224: -2198 | BF224: -2163 | BG224: -2163 | BJ224: -5868 | BK224: -2907 | BL224: -3342 | BM224: -2281 | BN224: -2342 | BO224: -2450 | BP224: -2327 | BQ224: -4300 | BR224: -2348 | BS224: -2373 | BT224: -2266 | BU224: -2346 | BW224: =_xlfn.XLOOKUP($A224,D!$O$3:$O$199,D!P$3:P$199,) | BX224: =_xlfn.XLOOKUP($A224,D!$O$3:$O$199,D!Q$3:Q$199,) | BY224: =_xlfn.XLOOKUP($A224,D!$O$3:$O$199,D!R$3:R$199,) | BZ224: =_xlfn.XLOOKUP($A224,D!$O$3:$O$199,D!S$3:S$199,) | CA224: =_xlfn.XLOOKUP($A224,D!$O$3:$O$199,D!T$3:T$199,) | CB224: =_xlfn.XLOOKUP($A224,D!$O$3:$O$199,D!U$3:U$199,) | CC224: =_xlfn.XLOOKUP($A224,D!$O$3:$O$199,D!V$3:V$199,) | CD224: =_xlfn.XLOOKUP($A224,D!$O$3:$O$199,D!W$3:W$199,) | ... CH224: =_xlfn.XLOOKUP($A224,D!$O$3:$O$199,D!AA$3:AA$199,)
... A242: 32.01 | B242: =VLOOKUP(A242,PL.C!$B:$F,2,0) | C242: Analítica | D242: Saída | E242: =VLOOKUP($A242,PL.C!$B:$F,5,0) | F242: sim | G242: forecast | I242: 0 | J242: 0 | K242: 0 | L242: -3300 | M242: -3300 | N242: -3300 | O242: -3750 | P242: -3300 | Q242: -3300 | R242: -3300 | S242: -3300 | T242: -3300 | V242: -3300 | W242: -3300 | X242: -3300 | Y242: -3300 | Z242: 0 | AA242: -6600 | AB242: -3300 | AC242: -3300 | AD242: -3300 | AE242: -3300 | AF242: -3300 | AG242: -3300 | AI242: -3300 | AJ242: -3300 | AK242: -3300 | AL242: -3350 | AM242: -3300 | AN242: -3300 | AO242: -3300 | AP242: -3300 | AQ242: -3300 | AR242: -3300 | AS242: -3300 | AT242: -3300 | AV242: -3300 | AW242: -3465 | AX242: -3465 | AY242: -3465 | AZ242: -3465 | BA242: -3465 | BB242: -3465 | BC242: -3465 | BD242: -3465 | BE242: -3465 | BF242: -3465 | BG242: -3775 | BJ242: -3465 | BK242: -3810 | BL242: -3810 | BM242: -3810 | BN242: -3810 | BO242: -3810 | BP242: -3810 | BQ242: -155 | BR242: -2500 | BS242: -5000 | BT242: 0 | BU242: -2500 | BW242: =_xlfn.XLOOKUP($A242,D!$O$3:$O$199,D!P$3:P$199,) | BX242: =_xlfn.XLOOKUP($A242,D!$O$3:$O$199,D!Q$3:Q$199,) | BY242: =_xlfn.XLOOKUP($A242,D!$O$3:$O$199,D!R$3:R$199,) | BZ242: =_xlfn.XLOOKUP($A242,D!$O$3:$O$199,D!S$3:S$199,) | CA242: =_xlfn.XLOOKUP($A242,D!$O$3:$O$199,D!T$3:T$199,) | CB242: =_xlfn.XLOOKUP($A242,D!$O$3:$O$199,D!U$3:U$199,) | CC242: =_xlfn.XLOOKUP($A242,D!$O$3:$O$199,D!V$3:V$199,) | CD242: =_xlfn.XLOOKUP($A242,D!$O$3:$O$199,D!W$3:W$199,) | ... CH242: =_xlfn.XLOOKUP($A242,D!$O$3:$O$199,D!AA$3:AA$199,)
A243: 32.02 | B243: Aluguel Industrial | G243: forecast | AV243: 0 | AW243: 0 | AX243: 0 | AY243: 0 | AZ243: 0 | BA243: 0 | BB243: 0 | BC243: 0 | BD243: 0 | BE243: -8237 | BF243: -7762 | BG243: -8031 | BJ243: -8012 | BK243: -7996 | BL243: -7980 | BM243: -8000 | BN243: -8000 | BO243: -8000 | BP243: -8000 | BQ243: -8000 | BR243: -8132 | BS243: -7867 | BT243: -8070 | BU243: -7931 | BW243: =_xlfn.XLOOKUP($A243,D!$O$3:$O$199,D!P$3:P$199,) | BX243: =_xlfn.XLOOKUP($A243,D!$O$3:$O$199,D!Q$3:Q$199,) | BY243: =_xlfn.XLOOKUP($A243,D!$O$3:$O$199,D!R$3:R$199,) | BZ243: =_xlfn.XLOOKUP($A243,D!$O$3:$O$199,D!S$3:S$199,) | CA243: =_xlfn.XLOOKUP($A243,D!$O$3:$O$199,D!T$3:T$199,) | CB243: =_xlfn.XLOOKUP($A243,D!$O$3:$O$199,D!U$3:U$199,) | CC243: =_xlfn.XLOOKUP($A243,D!$O$3:$O$199,D!V$3:V$199,) | CD243: =_xlfn.XLOOKUP($A243,D!$O$3:$O$199,D!W$3:W$199,) | ... CH243: =_xlfn.XLOOKUP($A243,D!$O$3:$O$199,D!AA$3:AA$199,)
A244: 33.01 | B244: =VLOOKUP(A244,PL.C!$B:$F,2,0) | C244: Analítica | D244: Saída | E244: =VLOOKUP($A244,PL.C!$B:$F,5,0) | F244: sim | G244: forecast | I244: 0 | J244: 0 | K244: 0 | L244: -14042 | M244: -6938 | N244: -15830 | O244: -8806 | P244: -7781 | Q244: 0 | R244: -7773 | S244: -15715 | T244: -9281 | V244: -7311 | W244: -8136 | X244: 0 | Y244: -7965 | Z244: -16001 | AA244: -8149 | AB244: 0 | AC244: -15924 | AD244: 0 | AE244: -19666 | AF244: 0 | AG244: -19866 | AI244: 0 | AJ244: -13624 | AK244: -20253 | AL244: -11766 | AM244: -8614 | AN244: -7994 | AO244: -8670 | AP244: 0 | AQ244: -8802 | AR244: -10415 | AS244: -17758 | AT244: 0 | AV244: 0 | AW244: 0 | AX244: 0 | AY244: -353 | AZ244: -828 | BA244: -397 | BB244: -421 | BC244: -676 | BD244: -946 | BE244: -688 | BF244: -951 | BG244: -886 | BJ244: -920 | BK244: -905 | BL244: -892 | BM244: -909 | BN244: -977 | BO244: -2464 | BP244: -1339 | BQ244: -892 | BR244: -923 | BS244: -7094 | BT244: -8255 | BU244: -8304 | BW244: =_xlfn.XLOOKUP($A244,D!$O$3:$O$199,D!P$3:P$199,) | BX244: =_xlfn.XLOOKUP($A244,D!$O$3:$O$199,D!Q$3:Q$199,) | BY244: =_xlfn.XLOOKUP($A244,D!$O$3:$O$199,D!R$3:R$199,) | BZ244: =_xlfn.XLOOKUP($A244,D!$O$3:$O$199,D!S$3:S$199,) | CA244: =_xlfn.XLOOKUP($A244,D!$O$3:$O$199,D!T$3:T$199,) | CB244: =_xlfn.XLOOKUP($A244,D!$O$3:$O$199,D!U$3:U$199,) | CC244: =_xlfn.XLOOKUP($A244,D!$O$3:$O$199,D!V$3:V$199,) | CD244: =_xlfn.XLOOKUP($A244,D!$O$3:$O$199,D!W$3:W$199,) | ... CH244: =_xlfn.XLOOKUP($A244,D!$O$3:$O$199,D!AA$3:AA$199,)
A245: 33.02 | B245: =VLOOKUP(A245,PL.C!$B:$F,2,0) | C245: Analítica | D245: Saída | E245: =VLOOKUP($A245,PL.C!$B:$F,5,0) | F245: sim | G245: forecast | I245: 0 | J245: 0 | K245: 0 | L245: -6487 | M245: -9646 | N245: -12882 | O245: -9089 | P245: -10969 | Q245: -10236 | R245: -7029 | S245: -11096 | T245: -9135 | V245: -8869 | W245: -10375 | X245: -12773 | Y245: -11559 | Z245: -12337 | AA245: -11208 | AB245: -14935 | AC245: -16704 | AD245: -10748 | AE245: -14723 | AF245: -15906 | AG245: -15614 | AI245: -9912 | AJ245: -8107 | AK245: -13197 | AL245: -8510 | AM245: -19360 | AN245: -9727 | AO245: -11789 | AP245: -16144 | AQ245: -7860 | AR245: -15056 | AS245: -12267 | AT245: -11859 | AV245: -14934 | AW245: -12242 | AX245: -10541 | AY245: -11124 | AZ245: -14847 | BA245: -12264 | BB245: -17383 | BC245: -11826 | BD245: -11924 | BE245: -17230 | BF245: -10923 | BG245: -12463 | BJ245: -13709 | BK245: -7082 | BL245: -16513 | BM245: -14079 | BN245: -12325 | BO245: -15392 | BP245: -17013 | BQ245: -13675 | BR245: -22138 | BS245: -14800 | BT245: -16114 | BU245: -21179 | BW245: =_xlfn.XLOOKUP($A245,D!$O$3:$O$199,D!P$3:P$199,) | BX245: =_xlfn.XLOOKUP($A245,D!$O$3:$O$199,D!Q$3:Q$199,) | BY245: =_xlfn.XLOOKUP($A245,D!$O$3:$O$199,D!R$3:R$199,) | BZ245: =_xlfn.XLOOKUP($A245,D!$O$3:$O$199,D!S$3:S$199,) | CA245: =_xlfn.XLOOKUP($A245,D!$O$3:$O$199,D!T$3:T$199,) | CB245: =_xlfn.XLOOKUP($A245,D!$O$3:$O$199,D!U$3:U$199,) | CC245: =_xlfn.XLOOKUP($A245,D!$O$3:$O$199,D!V$3:V$199,) | CD245: =_xlfn.XLOOKUP($A245,D!$O$3:$O$199,D!W$3:W$199,) | ... CH245: =_xlfn.XLOOKUP($A245,D!$O$3:$O$199,D!AA$3:AA$199,)
A246: 33.03 | B246: =VLOOKUP(A246,PL.C!$B:$F,2,0) | C246: Analítica | D246: Saída | E246: =VLOOKUP($A246,PL.C!$B:$F,5,0) | F246: sim | G246: forecast | I246: 0 | J246: 0 | K246: 0 | L246: -352 | M246: -360 | N246: -616 | O246: -616 | P246: -451 | Q246: -526 | R246: -343 | S246: -792 | T246: -482 | V246: -305 | W246: -453 | X246: -319 | Y246: -383 | Z246: -722 | AA246: -446 | AB246: -392 | AC246: -709 | AD246: -631 | AE246: -390 | AF246: -408 | AG246: -313 | AI246: -284 | AJ246: 0 | AK246: -823 | AL246: -551 | AM246: -511 | AN246: -360 | AO246: -472 | AP246: -491 | AQ246: -466 | AR246: -579 | AS246: -599 | AT246: -389 | AV246: -472 | AW246: -521 | AX246: -415 | AY246: -511 | AZ246: -472 | BA246: -910 | BB246: -742 | BC246: 0 | BD246: -1938 | BE246: -2129 | BF246: -1738 | BG246: -1077 | BJ246: -2653 | BK246: -1077 | BL246: -1492 | BM246: -4411 | BN246: -3175 | BO246: -3041 | BP246: -3793 | BQ246: -3831 | BR246: -4115 | BS246: -3774 | BT246: -2421 | BU246: -4505 | BW246: =_xlfn.XLOOKUP($A246,D!$O$3:$O$199,D!P$3:P$199,) | BX246: =_xlfn.XLOOKUP($A246,D!$O$3:$O$199,D!Q$3:Q$199,) | BY246: =_xlfn.XLOOKUP($A246,D!$O$3:$O$199,D!R$3:R$199,) | BZ246: =_xlfn.XLOOKUP($A246,D!$O$3:$O$199,D!S$3:S$199,) | CA246: =_xlfn.XLOOKUP($A246,D!$O$3:$O$199,D!T$3:T$199,) | CB246: =_xlfn.XLOOKUP($A246,D!$O$3:$O$199,D!U$3:U$199,) | CC246: =_xlfn.XLOOKUP($A246,D!$O$3:$O$199,D!V$3:V$199,) | CD246: =_xlfn.XLOOKUP($A246,D!$O$3:$O$199,D!W$3:W$199,) | ... CH246: =_xlfn.XLOOKUP($A246,D!$O$3:$O$199,D!AA$3:AA$199,)
A247: 33.04 | B247: =VLOOKUP(A247,PL.C!$B:$F,2,0) | C247: Analítica | D247: Saída | E247: =VLOOKUP($A247,PL.C!$B:$F,5,0) | F247: sim | G247: forecast | I247: -3074 | J247: 0 | K247: -840 | L247: -9222 | M247: -886 | N247: -1105 | O247: 0 | P247: -11 | Q247: 0 | R247: 0 | S247: -2034 | T247: -5988 | V247: -122 | W247: -2917 | X247: -1620 | Y247: -56 | Z247: -1064 | AA247: -1216 | AB247: -99 | AC247: -40 | AD247: -1167 | AE247: -1452 | AF247: -2052 | AG247: -1807 | AI247: -814 | AJ247: -353 | AK247: -1463 | AL247: -29 | AM247: -1668 | AN247: -2340 | AO247: -289 | AP247: -1120 | AQ247: -3731 | AR247: -1242 | AS247: -956 | AT247: -147 | AV247: -1384 | AW247: -80 | AX247: -2305 | AY247: -766 | AZ247: -4717 | BA247: -5243 | BB247: -718 | BC247: -1663 | BD247: -9422 | BE247: -528 | BF247: -3932 | BG247: -56 | BJ247: -2578 | BK247: -5195 | BL247: -390 | BM247: -904 | BN247: -160 | BO247: -685 | BP247: -3134 | BQ247: -1728 | BR247: -3681 | BS247: -4093 | BT247: -1133 | BU247: -1189 | BW247: =_xlfn.XLOOKUP($A247,D!$O$3:$O$199,D!P$3:P$199,) | BX247: =_xlfn.XLOOKUP($A247,D!$O$3:$O$199,D!Q$3:Q$199,) | BY247: =_xlfn.XLOOKUP($A247,D!$O$3:$O$199,D!R$3:R$199,) | BZ247: =_xlfn.XLOOKUP($A247,D!$O$3:$O$199,D!S$3:S$199,) | CA247: =_xlfn.XLOOKUP($A247,D!$O$3:$O$199,D!T$3:T$199,) | CB247: =_xlfn.XLOOKUP($A247,D!$O$3:$O$199,D!U$3:U$199,) | CC247: =_xlfn.XLOOKUP($A247,D!$O$3:$O$199,D!V$3:V$199,) | CD247: =_xlfn.XLOOKUP($A247,D!$O$3:$O$199,D!W$3:W$199,) | ... CH247: =_xlfn.XLOOKUP($A247,D!$O$3:$O$199,D!AA$3:AA$199,)
A248: 33.05 | B248: =VLOOKUP(A248,PL.C!$B:$F,2,0) | C248: Analítica | D248: Saída | E248: =VLOOKUP($A248,PL.C!$B:$F,5,0) | F248: sim | G248: forecast | I248: 0 | J248: 0 | K248: 0 | L248: -1477 | M248: -2839 | N248: -153 | O248: 0 | P248: -373 | Q248: -250 | R248: -1700 | S248: 0 | T248: 0 | V248: -50 | W248: -62 | X248: 0 | Y248: -96 | Z248: 0 | AA248: -59 | AB248: -198 | AC248: -330 | AD248: -1107 | AE248: -1757 | AF248: 0 | AG248: 0 | AI248: 0 | AJ248: 0 | AK248: 0 | AL248: 0 | AM248: 0 | AN248: -100 | AO248: 0 | AP248: -120 | AQ248: 0 | AR248: 0 | AS248: 0 | AT248: -37 | AV248: -41 | AW248: -80 | AX248: -537 | AY248: -157 | AZ248: -1569 | BA248: 0 | BB248: 0 | BC248: -50 | BD248: -1281 | BE248: 0 | BF248: -477 | BG248: 0 | BJ248: 0 | BK248: 0 | BL248: -200 | BM248: 0 | BN248: 0 | BO248: 0 | BP248: 0 | BQ248: -605 | BR248: 0 | BS248: -744 | BT248: -247 | BU248: 0 | BW248: =_xlfn.XLOOKUP($A248,D!$O$3:$O$199,D!P$3:P$199,) | BX248: =_xlfn.XLOOKUP($A248,D!$O$3:$O$199,D!Q$3:Q$199,) | BY248: =_xlfn.XLOOKUP($A248,D!$O$3:$O$199,D!R$3:R$199,) | BZ248: =_xlfn.XLOOKUP($A248,D!$O$3:$O$199,D!S$3:S$199,) | CA248: =_xlfn.XLOOKUP($A248,D!$O$3:$O$199,D!T$3:T$199,) | CB248: =_xlfn.XLOOKUP($A248,D!$O$3:$O$199,D!U$3:U$199,) | CC248: =_xlfn.XLOOKUP($A248,D!$O$3:$O$199,D!V$3:V$199,) | CD248: =_xlfn.XLOOKUP($A248,D!$O$3:$O$199,D!W$3:W$199,) | ... CH248: =_xlfn.XLOOKUP($A248,D!$O$3:$O$199,D!AA$3:AA$199,)
A249: 34.01 | B249: =VLOOKUP(A249,PL.C!$B:$F,2,0) | C249: Analítica | D249: Saída | E249: =VLOOKUP($A249,PL.C!$B:$F,5,0) | F249: sim | G249: forecast | I249: 0 | J249: 0 | K249: 0 | L249: 0 | M249: 0 | N249: 0 | O249: 0 | P249: -250 | Q249: 0 | R249: 0 | S249: 0 | T249: -360 | V249: 0 | W249: 0 | X249: -280 | Y249: 0 | Z249: -150 | AA249: 0 | AB249: 0 | AC249: 0 | AD249: 0 | AE249: 0 | AF249: 0 | AG249: -600 | AI249: -280 | AJ249: 0 | AK249: -850 | AL249: -250 | AM249: 0 | AN249: 0 | AO249: 0 | AP249: -610 | AQ249: 0 | AR249: 0 | AS249: 0 | AT249: 0 | AV249: -640 | AW249: 0 | AX249: 0 | AY249: 0 | AZ249: 0 | BA249: 0 | BB249: 0 | BC249: 0 | BD249: 0 | BE249: 0 | BF249: 0 | BG249: -150 | BJ249: -420 | BK249: 0 | BL249: 0 | BM249: 0 | BN249: 0 | BO249: 0 | BP249: 0 | BQ249: 0 | BR249: 0 | BS249: 0 | BT249: -660 | BU249: 0 | BW249: =_xlfn.XLOOKUP($A249,D!$O$3:$O$199,D!P$3:P$199,) | BX249: =_xlfn.XLOOKUP($A249,D!$O$3:$O$199,D!Q$3:Q$199,) | BY249: =_xlfn.XLOOKUP($A249,D!$O$3:$O$199,D!R$3:R$199,) | BZ249: =_xlfn.XLOOKUP($A249,D!$O$3:$O$199,D!S$3:S$199,) | CA249: =_xlfn.XLOOKUP($A249,D!$O$3:$O$199,D!T$3:T$199,) | CB249: =_xlfn.XLOOKUP($A249,D!$O$3:$O$199,D!U$3:U$199,) | CC249: =_xlfn.XLOOKUP($A249,D!$O$3:$O$199,D!V$3:V$199,) | CD249: =_xlfn.XLOOKUP($A249,D!$O$3:$O$199,D!W$3:W$199,) | ... CH249: =_xlfn.XLOOKUP($A249,D!$O$3:$O$199,D!AA$3:AA$199,)
A250: 34.04 | B250: =VLOOKUP(A250,PL.C!$B:$F,2,0) | C250: Analítica | D250: Saída | E250: =VLOOKUP($A250,PL.C!$B:$F,5,0) | F250: sim | G250: forecast | I250: 0 | J250: 0 | K250: 0 | L250: -108 | M250: -2267 | N250: -860 | O250: -1680 | P250: -1701 | Q250: -1532 | R250: -215 | S250: -100 | T250: -1561 | V250: -9752 | W250: -7920 | X250: -1035 | Y250: -1290 | Z250: -916 | AA250: -3100 | AB250: -341 | AC250: -916 | AD250: -1497 | AE250: -1346 | AF250: -3365 | AG250: -98 | AI250: -118 | AJ250: -810 | AK250: -1028 | AL250: -2972 | AM250: -7947 | AN250: -1034 | AO250: -479 | AP250: -930 | AQ250: -145 | AR250: -50 | AS250: -17145 | AT250: -220 | AV250: -1331 | AW250: -6010 | AX250: -6137 | AY250: -1836 | AZ250: -916 | BA250: -1736 | BB250: -670 | BC250: -333 | BD250: -5561 | BE250: -7137 | BF250: -1300 | BG250: -3031 | BJ250: -2454 | BK250: -7155 | BL250: -1479 | BM250: -31283 | BN250: -4556 | BO250: -1400 | BP250: -80 | BQ250: -7668 | BR250: -232 | BS250: -8323 | BT250: -10788 | BU250: -2229 | BW250: =_xlfn.XLOOKUP($A250,D!$O$3:$O$199,D!P$3:P$199,) | BX250: =_xlfn.XLOOKUP($A250,D!$O$3:$O$199,D!Q$3:Q$199,) | BY250: =_xlfn.XLOOKUP($A250,D!$O$3:$O$199,D!R$3:R$199,) | BZ250: =_xlfn.XLOOKUP($A250,D!$O$3:$O$199,D!S$3:S$199,) | CA250: =_xlfn.XLOOKUP($A250,D!$O$3:$O$199,D!T$3:T$199,) | CB250: =_xlfn.XLOOKUP($A250,D!$O$3:$O$199,D!U$3:U$199,) | CC250: =_xlfn.XLOOKUP($A250,D!$O$3:$O$199,D!V$3:V$199,) | CD250: =_xlfn.XLOOKUP($A250,D!$O$3:$O$199,D!W$3:W$199,) | ... CH250: =_xlfn.XLOOKUP($A250,D!$O$3:$O$199,D!AA$3:AA$199,)
A251: 34.05 | B251: =VLOOKUP(A251,PL.C!$B:$F,2,0) | C251: Analítica | D251: Saída | E251: =VLOOKUP($A251,PL.C!$B:$F,5,0) | F251: sim | G251: forecast | I251: 0 | J251: 0 | K251: 0 | L251: -2418 | M251: -3512 | N251: -3837 | O251: -1701 | P251: -1336 | Q251: -1670 | R251: -6135 | S251: -2160 | T251: -6979 | V251: -4623 | W251: -6401 | X251: -5444 | Y251: -3266 | Z251: -2453 | AA251: -4765 | AB251: -6667 | AC251: -6392 | AD251: -3198 | AE251: -6758 | AF251: -2435 | AG251: -2090 | AI251: -4652 | AJ251: -4068 | AK251: -13880 | AL251: -4541 | AM251: -2372 | AN251: -4891 | AO251: -2162 | AP251: -2993 | AQ251: -12867 | AR251: -2029 | AS251: -7864 | AT251: -10739 | AV251: -2183 | AW251: -1721 | AX251: -2271 | AY251: -4890 | AZ251: -4072 | BA251: -7761 | BB251: -7400 | BC251: -4936 | BD251: -9187 | BE251: -11037 | BF251: -1765 | BG251: -1560 | BJ251: -2585 | BK251: -5438 | BL251: -3072 | BM251: -2719 | BN251: -3709 | BO251: -6438 | BP251: -3904 | BQ251: -6718 | BR251: -6120 | BS251: -7171 | BT251: -20326 | BU251: -10896 | BW251: =_xlfn.XLOOKUP($A251,D!$O$3:$O$199,D!P$3:P$199,) | BX251: =_xlfn.XLOOKUP($A251,D!$O$3:$O$199,D!Q$3:Q$199,) | BY251: =_xlfn.XLOOKUP($A251,D!$O$3:$O$199,D!R$3:R$199,) | BZ251: =_xlfn.XLOOKUP($A251,D!$O$3:$O$199,D!S$3:S$199,) | CA251: =_xlfn.XLOOKUP($A251,D!$O$3:$O$199,D!T$3:T$199,) | CB251: =_xlfn.XLOOKUP($A251,D!$O$3:$O$199,D!U$3:U$199,) | CC251: =_xlfn.XLOOKUP($A251,D!$O$3:$O$199,D!V$3:V$199,) | CD251: =_xlfn.XLOOKUP($A251,D!$O$3:$O$199,D!W$3:W$199,) | ... CH251: =_xlfn.XLOOKUP($A251,D!$O$3:$O$199,D!AA$3:AA$199,)
A252: 34.06 | B252: =VLOOKUP(A252,PL.C!$B:$F,2,0) | C252: Analítica | D252: Saída | E252: =VLOOKUP($A252,PL.C!$B:$F,5,0) | F252: sim | G252: forecast | I252: 0 | J252: 0 | K252: 0 | L252: 0 | M252: 0 | N252: 0 | O252: 0 | P252: 0 | Q252: 0 | R252: 0 | S252: 0 | T252: 0 | V252: 0 | W252: 0 | X252: 0 | Y252: 0 | Z252: 0 | AA252: 0 | AB252: 0 | AC252: 0 | AD252: 0 | AE252: 0 | AF252: 0 | AG252: 0 | AI252: 0 | AJ252: 0 | AK252: 0 | AL252: 0 | AM252: 0 | AN252: 0 | AO252: -40 | AP252: 0 | AQ252: 0 | AR252: 0 | AS252: 0 | AT252: 0 | AV252: 0 | AW252: 0 | AX252: 0 | AY252: 0 | AZ252: 0 | BA252: 0 | BB252: 0 | BC252: 0 | BD252: 0 | BE252: 0 | BF252: 0 | BG252: 0 | BJ252: 0 | BK252: 0 | BL252: 0 | BM252: 0 | BN252: -215 | BO252: 0 | BP252: 0 | BQ252: 0 | BR252: 0 | BS252: 0 | BT252: 0 | BU252: 0 | BW252: =_xlfn.XLOOKUP($A252,D!$O$3:$O$199,D!P$3:P$199,) | BX252: =_xlfn.XLOOKUP($A252,D!$O$3:$O$199,D!Q$3:Q$199,) | BY252: =_xlfn.XLOOKUP($A252,D!$O$3:$O$199,D!R$3:R$199,) | BZ252: =_xlfn.XLOOKUP($A252,D!$O$3:$O$199,D!S$3:S$199,) | CA252: =_xlfn.XLOOKUP($A252,D!$O$3:$O$199,D!T$3:T$199,) | CB252: =_xlfn.XLOOKUP($A252,D!$O$3:$O$199,D!U$3:U$199,) | CC252: =_xlfn.XLOOKUP($A252,D!$O$3:$O$199,D!V$3:V$199,) | CD252: =_xlfn.XLOOKUP($A252,D!$O$3:$O$199,D!W$3:W$199,) | ... CH252: =_xlfn.XLOOKUP($A252,D!$O$3:$O$199,D!AA$3:AA$199,)
A253: 34.07 | B253: =VLOOKUP(A253,PL.C!$B:$F,2,0) | C253: Analítica | D253: Saída | E253: =VLOOKUP($A253,PL.C!$B:$F,5,0) | F253: sim | G253: forecast | I253: 0 | J253: 0 | K253: 0 | L253: 0 | M253: 0 | N253: 0 | O253: 0 | P253: 0 | Q253: 0 | R253: 0 | S253: 0 | T253: 0 | V253: 0 | W253: 0 | X253: 0 | Y253: 0 | Z253: 0 | AA253: 0 | AB253: 0 | AC253: 0 | AD253: 0 | AE253: 0 | AF253: 0 | AG253: 0 | AI253: 0 | AJ253: 0 | AK253: 0 | AL253: 0 | AM253: 0 | AN253: 0 | AO253: 0 | AP253: 0 | AQ253: 0 | AR253: 0 | AS253: 0 | AT253: 0 | AV253: 0 | AW253: 0 | AX253: -653 | AY253: 0 | AZ253: 0 | BA253: 0 | BB253: 0 | BC253: 0 | BD253: 0 | BE253: 0 | BF253: 0 | BG253: 0 | BJ253: 0 | BK253: 0 | BL253: 0 | BM253: 0 | BN253: 0 | BO253: 0 | BP253: 0 | BQ253: 0 | BR253: 0 | BS253: 0 | BT253: 0 | BU253: 0 | BW253: =_xlfn.XLOOKUP($A253,D!$O$3:$O$199,D!P$3:P$199,) | BX253: =_xlfn.XLOOKUP($A253,D!$O$3:$O$199,D!Q$3:Q$199,) | BY253: =_xlfn.XLOOKUP($A253,D!$O$3:$O$199,D!R$3:R$199,) | BZ253: =_xlfn.XLOOKUP($A253,D!$O$3:$O$199,D!S$3:S$199,) | CA253: =_xlfn.XLOOKUP($A253,D!$O$3:$O$199,D!T$3:T$199,) | CB253: =_xlfn.XLOOKUP($A253,D!$O$3:$O$199,D!U$3:U$199,) | CC253: =_xlfn.XLOOKUP($A253,D!$O$3:$O$199,D!V$3:V$199,) | CD253: =_xlfn.XLOOKUP($A253,D!$O$3:$O$199,D!W$3:W$199,) | ... CH253: =_xlfn.XLOOKUP($A253,D!$O$3:$O$199,D!AA$3:AA$199,)
A254: 35.02 | B254: =VLOOKUP(A254,PL.C!$B:$F,2,0) | C254: Analítica | D254: Saída | E254: =VLOOKUP($A254,PL.C!$B:$F,5,0) | F254: sim | G254: forecast | I254: 0 | J254: 0 | K254: 0 | L254: 0 | M254: -6850 | N254: 0 | O254: -4570 | P254: -5660 | Q254: 0 | R254: -8220 | S254: -2600 | T254: 0 | V254: -2575 | W254: 0 | X254: -4160 | Y254: -5440 | Z254: 0 | AA254: 0 | AB254: 0 | AC254: 0 | AD254: 0 | AE254: 0 | AF254: -840 | AG254: -1912 | AI254: 0 | AJ254: 0 | AK254: 0 | AL254: 0 | AM254: 0 | AN254: 0 | AO254: 0 | AP254: 0 | AQ254: 0 | AR254: 0 | AS254: 0 | AT254: 0 | AV254: 0 | AW254: 0 | AX254: 0 | AY254: 0 | AZ254: 0 | BA254: 0 | BB254: 0 | BC254: 0 | BD254: 0 | BE254: 0 | BF254: 0 | BG254: 0 | BJ254: 0 | BK254: 0 | BL254: 0 | BM254: 0 | BN254: 0 | BO254: 0 | BP254: 0 | BQ254: 0 | BR254: 0 | BS254: 0 | BT254: 0 | BU254: 0 | BW254: =_xlfn.XLOOKUP($A254,D!$O$3:$O$199,D!P$3:P$199,) | BX254: =_xlfn.XLOOKUP($A254,D!$O$3:$O$199,D!Q$3:Q$199,) | BY254: =_xlfn.XLOOKUP($A254,D!$O$3:$O$199,D!R$3:R$199,) | BZ254: =_xlfn.XLOOKUP($A254,D!$O$3:$O$199,D!S$3:S$199,) | CA254: =_xlfn.XLOOKUP($A254,D!$O$3:$O$199,D!T$3:T$199,) | CB254: =_xlfn.XLOOKUP($A254,D!$O$3:$O$199,D!U$3:U$199,) | CC254: =_xlfn.XLOOKUP($A254,D!$O$3:$O$199,D!V$3:V$199,) | CD254: =_xlfn.XLOOKUP($A254,D!$O$3:$O$199,D!W$3:W$199,) | ... CH254: =_xlfn.XLOOKUP($A254,D!$O$3:$O$199,D!AA$3:AA$199,)
A255: 36.01 | B255: =VLOOKUP(A255,PL.C!$B:$F,2,0) | C255: Analítica | D255: Saída | E255: =VLOOKUP($A255,PL.C!$B:$F,5,0) | F255: sim | G255: forecast | I255: 0 | J255: 0 | K255: 0 | L255: -220 | M255: -2532 | N255: -2532 | O255: -2532 | P255: -2532 | Q255: -2532 | R255: -2532 | S255: -2532 | T255: -2542 | V255: -2542 | W255: -2548 | X255: -2548 | Y255: 0 | Z255: -2548 | AA255: -2548 | AB255: -2548 | AC255: -2548 | AD255: -2548 | AE255: -2548 | AF255: -2548 | AG255: -2620 | AI255: -2572 | AJ255: -2583 | AK255: -2583 | AL255: -254 | AM255: -2583 | AN255: 0 | AO255: -4792 | AP255: -4792 | AQ255: -4792 | AR255: -4792 | AS255: -4792 | AT255: -4792 | AV255: -4792 | AW255: -4821 | AX255: -4821 | AY255: -4821 | AZ255: -4821 | BA255: -9322 | BB255: -282 | BC255: -9322 | BD255: -1321 | BE255: -5322 | BF255: -5322 | BG255: -5322 | BJ255: -5956 | BK255: -6374 | BL255: -5635 | BM255: -5635 | BN255: -5635 | BO255: -5635 | BP255: -458 | BQ255: -5508 | BR255: -5635 | BS255: -5635 | BT255: -5635 | BU255: -5635 | BW255: =_xlfn.XLOOKUP($A255,D!$O$3:$O$199,D!P$3:P$199,) | BX255: =_xlfn.XLOOKUP($A255,D!$O$3:$O$199,D!Q$3:Q$199,) | BY255: =_xlfn.XLOOKUP($A255,D!$O$3:$O$199,D!R$3:R$199,) | BZ255: =_xlfn.XLOOKUP($A255,D!$O$3:$O$199,D!S$3:S$199,) | CA255: =_xlfn.XLOOKUP($A255,D!$O$3:$O$199,D!T$3:T$199,) | CB255: =_xlfn.XLOOKUP($A255,D!$O$3:$O$199,D!U$3:U$199,) | CC255: =_xlfn.XLOOKUP($A255,D!$O$3:$O$199,D!V$3:V$199,) | CD255: =_xlfn.XLOOKUP($A255,D!$O$3:$O$199,D!W$3:W$199,) | ... CH255: =_xlfn.XLOOKUP($A255,D!$O$3:$O$199,D!AA$3:AA$199,)
... A399: 55.02 | B399: =VLOOKUP(A399,PL.C!$B:$F,2,0) | C399: Analítica | D399: Saída | E399: =VLOOKUP($A399,PL.C!$B:$F,5,0) | F399: sim | G399: forecast | I399: 0 | J399: 0 | K399: 0 | L399: 0 | M399: 0 | N399: 0 | O399: 0 | P399: 0 | Q399: 0 | R399: 0 | S399: 0 | T399: 0 | V399: 0 | W399: 0 | X399: 0 | Y399: 0 | Z399: 0 | AA399: 0 | AB399: 0 | AC399: 0 | AD399: 0 | AE399: 0 | AF399: 0 | AG399: 0 | AI399: 0 | AJ399: 0 | AK399: 0 | AL399: 0 | AM399: 0 | AN399: -132 | AO399: -376 | AP399: 0 | AQ399: 0 | AR399: 0 | AS399: 0 | AT399: 0 | AV399: 0 | AW399: 0 | AX399: 0 | AY399: 0 | AZ399: 0 | BA399: 0 | BB399: 0 | BC399: 0 | BD399: 0 | BE399: 0 | BF399: 0 | BG399: 0 | BJ399: 0 | BK399: 0 | BL399: 0 | BM399: 0 | BN399: 0 | BO399: 0 | BP399: 0 | BQ399: 0 | BR399: 0 | BS399: 0 | BT399: 0 | BU399: 0 | BW399: =_xlfn.XLOOKUP($A399,D!$O$3:$O$199,D!P$3:P$199,) | BX399: =_xlfn.XLOOKUP($A399,D!$O$3:$O$199,D!Q$3:Q$199,) | BY399: =_xlfn.XLOOKUP($A399,D!$O$3:$O$199,D!R$3:R$199,) | BZ399: =_xlfn.XLOOKUP($A399,D!$O$3:$O$199,D!S$3:S$199,) | CA399: =_xlfn.XLOOKUP($A399,D!$O$3:$O$199,D!T$3:T$199,) | CB399: =_xlfn.XLOOKUP($A399,D!$O$3:$O$199,D!U$3:U$199,) | CC399: =_xlfn.XLOOKUP($A399,D!$O$3:$O$199,D!V$3:V$199,) | CD399: =_xlfn.XLOOKUP($A399,D!$O$3:$O$199,D!W$3:W$199,) | ... CH399: =_xlfn.XLOOKUP($A399,D!$O$3:$O$199,D!AA$3:AA$199,)
BL408: Ver formulas Depois da 50.6 não importa dados

Sheet DRE
GG2: Orçamento | GI2: Real | JV2: Orçamento | JX2: Real
GE3: =IF(GE4>=$FS$6,GE4-366,GE4-365) | JT3: =IF(JT4<$JH$6,JT4-366,JT4-365)
E4: Forecast | G4: Realizado | T4: Forecast | V4: Realizado | AI4: Forecast | AX4: Budget | BM4: Forecast | CB4: 45170 | CM4: Acumulado | CV4: 1º Trxmestre | DG4: 2T | DR4: 3T | EC4: 4T | EN4: 1S | EZ4: Budget | FO4: Forecast | GE4: 45352 | GN4: 1ºT 2024 | GY4: 2ºT 2024 | HJ4: 3ºT 2024 | HU4: 4ºT 2024 | IF4: ANO 2024 | IO4: Budget | JD4: Forecast | JT4: 45992 | KC4: 1ºT 2025 | KN4: 2ºT 2025 | KY4: 3ºT 2025 | LJ4: 4ºT 2025 | LU4: ANO 2025
CB5: =CB4-365-365 | CD5: =CB4-365 | CE5: =BZ4-365
A6: 1 | E6: 2020 - F | G6: 43831 | H6: 43862 | I6: 43891 | J6: 43922 | K6: 43952 | L6: 43983 | M6: 44013 | N6: 44044 | O6: 44075 | P6: 44105 | Q6: 44136 | R6: 44166 | T6: 2021 - F | V6: 44197 | W6: 44228 | X6: 44256 | Y6: 44287 | Z6: 44317 | AA6: 44348 | AB6: 44378 | AC6: 44409 | AD6: 44440 | AE6: 44470 | AF6: 44501 | AG6: 44531 | AI6: 2022 - F | AK6: 44562 | AL6: 44593 | AM6: 44621 | AN6: 44652 | AO6: 44682 | AP6: 44713 | AQ6: 44743 | AR6: 44774 | AS6: 44805 | AT6: 44835 | AU6: 44866 | AV6: 44896 | AX6: 2023 - B | AZ6: 44927 | BA6: 44958 | BB6: 44986 | BC6: 45017 | BD6: 45047 | BE6: 45078 | BF6: 45108 | BG6: 45139 | BH6: 45170 | BI6: 45200 | BJ6: 45231 | BK6: 45261 | BM6: 2023 - F | BO6: 44927 | BP6: 44958 | BQ6: 44986 | BR6: 45017 | BS6: 45047 | BT6: 45078 | BU6: 45108 | BV6: 45139 | BW6: 45170 | BX6: 45200 | BY6: 45231 | BZ6: 45261 | CB6: 2021 - F | CD6: 2022 - F | CF6: 2023 - B | CH6: 2023 - F | CJ6: Real vs Bdgt | CK6: Var % | CM6: 2020 - R | CO6: 2021 - B | CQ6: 2021 - F | CS6: Real vs Bdgt | CT6: Var % | CV6: 2021 - F | CX6: 2022 - F | CZ6: 2023 - B | DB6: 2023 - F | DD6: Real vs Budget | DE6: Var % | DG6: 2020 - R | DI6: 2021 - R | DK6: 2022 - B | DM6: 2022 - R | DO6: Real vs Budget | DP6: Var % | DR6: 2020 - R | DT6: 2021 - R | DV6: 2022 - B | DX6: 2022 - R | DZ6: Real vs Budget | EA6: Var % | EC6: 2020 - R | EE6: 2021 - R | EG6: 2022 - B | EI6: 2022 - R | EK6: Real vs Budget | EL6: Var % | EN6: 2020 - R | EP6: 2021 - R | ER6: 2022 - B | ET6: 2022 - R | EV6: Real vs Budget | EW6: Var % | EZ6: 2024 - B | FB6: 45292 | FC6: 45323 | FD6: 45352 | FE6: 45383 | FF6: 45413 | FG6: 45444 | FH6: 45474 | FI6: 45505 | FJ6: 45536 | FK6: 45566 | FL6: 45597 | FM6: 45627 | FO6: 2024 - F | FQ6: 45292 | FR6: 45323 | FS6: 45352 | FT6: 45383 | FU6: 45413 | FV6: 45444 | FW6: 45474 | FX6: 45505 | FY6: 45536 | FZ6: 45566 | GA6: 45597 | GB6: 45627 | GE6: 2023 - R | GG6: 2024 - B | GI6: 2024 - F | GK6: Real vs Bdgt | GL6: Var % | GN6: 2022 - R | GP6: 2023 - R | GR6: 2024 - B | GT6: 2024 - R | GV6: Real vs Bdgt | GW6: Var % | GY6: 2022 - R | HA6: 2023 - R | HC6: 2024 - B | HE6: 2024 - R | HG6: Real vs Bdgt | HH6: Var % | HJ6: 2022 - R | HL6: 2023 - R | HN6: 2024 - B | HP6: 2024 - R | HR6: Real vs Bdgt | HS6: Var % | HU6: 2022 - R | HW6: 2023 - R | HY6: 2024 - B | IA6: 2024 - R | IC6: Real vs Bdgt | ID6: Var % | IF6: 2023 - R | IH6: 2024 - B | IJ6: 2024 - F | IL6: Real vs Budget | IM6: Var % | IO6: 2025- B | IQ6: 45658 | IR6: 45689 | IS6: 45717 | IT6: 45748 | IU6: 45778 | IV6: 45809 | IW6: 45839 | IX6: 45870 | IY6: 45901 | IZ6: 45931 | JA6: 45962 | JB6: 45992 | JD6: 2025- F | JF6: 45658 | JG6: 45689 | JH6: 45717 | JI6: 45748 | JJ6: 45778 | JK6: 45809 | JL6: 45839 | JM6: 45870 | JN6: 45901 | JO6: 45931 | JP6: 45962 | JQ6: 45992 | JT6: 2024 - R | JV6: 2025 - B | JX6: 2025 - F | JZ6: Real vs Bdgt | KA6: Var % | KC6: 2023 - R | KE6: 2024 - R | KG6: 2025 - B | KI6: 2025 - R | KK6: Real vs Bdgt | KL6: Var % | KN6: 2023 - R | KP6: 2024 - R | KR6: 2025 - B | KT6: 2025 - R | KV6: Real vs Bdgt | KW6: Var % | KY6: 2023 - R | LA6: 2024 - R | LC6: 2025 - B | LE6: 2025 - R | LG6: Real vs Bdgt | LH6: Var % | LJ6: 2023 - R | LL6: 2024 - R | LN6: 2025 - B | LP6: 2025 - R | LR6: Real vs Bdgt | LS6: Var % | LU6: 2024 - R | LW6: 2025 - B | LY6: 2025 - F | MA6: Real vs Budget | MB6: Var %
A7: 2
A8: 3 | C8: Receita Bruta de Venda | E8: 11168874 | G8: 786539.49 | H8: 722530.67 | I8: 783954.01 | J8: 753524.76 | K8: 968541.38 | L8: 1148073 | M8: 1069053 | N8: 995152 | O8: 1048346 | P8: 996025 | Q8: 810578 | R8: 1086557 | T8: =SUM(V8:AG8) | V8: ='Rec.'!V8 | W8: ='Rec.'!W8 | X8: ='Rec.'!X8 | Y8: ='Rec.'!Y8 | Z8: ='Rec.'!Z8 | AA8: ='Rec.'!AA8 | AB8: ='Rec.'!AB8 | AC8: ='Rec.'!AC8 | ... AG8: ='Rec.'!AG8 | AI8: =SUM(AK8:AV8) | AK8: ='Rec.'!AK8 | AL8: ='Rec.'!AL8 | AM8: ='Rec.'!AM8 | AN8: ='Rec.'!AN8 | AO8: ='Rec.'!AO8 | AP8: ='Rec.'!AP8 | AQ8: ='Rec.'!AQ8 | AR8: ='Rec.'!AR8 | ... AV8: ='Rec.'!AV8 | AX8: =SUM(AZ8:BK8) | AZ8: ='Rec.'!AZ8 | BA8: ='Rec.'!BA8 | BB8: ='Rec.'!BB8 | BC8: ='Rec.'!BC8 | BD8: ='Rec.'!BD8 | BE8: ='Rec.'!BE8 | BF8: ='Rec.'!BF8 | BG8: ='Rec.'!BG8 | ... BK8: ='Rec.'!BK8 | BM8: =SUM(BO8:BZ8) | BO8: ='Rec.'!BO8 | BP8: ='Rec.'!BP8 | BQ8: ='Rec.'!BQ8 | BR8: ='Rec.'!BR8 | BS8: ='Rec.'!BS8 | BT8: ='Rec.'!BT8 | BU8: ='Rec.'!BU8 | BV8: ='Rec.'!BV8 | ... BZ8: ='Rec.'!BZ8 | CB8: =HLOOKUP($CB$5,$V$6:$AG$37,$A8,0) | CD8: =HLOOKUP($CD$5,$AK$6:$AV$37,$A8,0) | CF8: =HLOOKUP($CB$4,$AZ$6:$BK$37,$A8,0) | CH8: =HLOOKUP($CB$4,$BO$6:$BZ$37,$A8,0) | CJ8: =CH8-CF8 | CK8: =CJ8/CF8 | CM8: =SUM(G8:Q8) | CO8: =SUM(AK8:AU8) | CQ8: =SUM(AZ8:BJ8) | CS8: =CQ8-CO8 | CT8: =CS8/CO8 | CV8: =SUM(V8:X8) | CX8: =SUM(AK8:AM8) | CZ8: =SUM(AZ8:BB8) | DB8: =SUM(BO8:BQ8) | DD8: =DB8-CZ8 | DE8: =DD8/CZ8 | DG8: =SUM(J8:L8) | DI8: =SUM(Y8:AA8) | DK8: =SUM(AN8:AP8) | DM8: =SUM(BC8:BE8) | DO8: =DM8-DK8 | DP8: =DO8/DK8 | DR8: =SUM(M8:O8) | DT8: =SUM(AB8:AD8) | DV8: =SUM(AQ8:AS8) | DX8: =SUM(BF8:BH8) | DZ8: =DX8-DV8 | EA8: =DZ8/DV8 | EC8: =SUM(AN8:AP8) | EE8: =SUM(AE8:AG8) | EG8: =SUM(BC8:BE8) | EI8: =SUM(CH8:CJ8) | EK8: =EI8-EG8 | EL8: =EK8/EG8 | EN8: =SUM(G8:L8) | EP8: =SUM(V8:AA8) | ER8: =SUM(AK8:AP8) | ET8: =SUM(AZ8:BE8) | EV8: =ET8-ER8 | EW8: =EV8/ER8 | EZ8: =SUM(FB8:FM8) | FB8: ='Rec.'!CG8 | FC8: ='Rec.'!CH8 | FD8: ='Rec.'!CI8 | FE8: ='Rec.'!CJ8 | FF8: ='Rec.'!CK8 | FG8: ='Rec.'!CL8 | FH8: ='Rec.'!CM8 | FI8: ='Rec.'!CN8 | ... FM8: ='Rec.'!CR8 | FO8: =SUM(FQ8:GB8) | FQ8: ='Rec.'!CV8 | FR8: ='Rec.'!CW8 | FS8: ='Rec.'!CX8 | FT8: ='Rec.'!CY8 | FU8: ='Rec.'!CZ8 | FV8: ='Rec.'!DA8 | FW8: ='Rec.'!DB8 | FX8: ='Rec.'!DC8 | ... GB8: ='Rec.'!DG8 | GE8: =_xlfn.XLOOKUP($GE$3,$BO$6:$BZ$6,$BO8:$BZ8) | GG8: =_xlfn.XLOOKUP($GE$4,$FB$6:$FM$6,$FB8:$FM8) | GI8: =_xlfn.XLOOKUP($GE$4,$FQ$6:$GB$6,$FQ8:$GB8) | GK8: =GI8-GG8 | GL8: =GK8/GG8 | GN8: =SUM(AK8:AM8) | GP8: =SUM(BO8:BQ8) | GR8: =SUM(FB8:FD8) | GT8: =SUM(FQ8:FS8) | GV8: =GT8-GR8 | GW8: =GV8/GR8 | GY8: =SUM(AN8:AP8) | HA8: =SUM(BR8:BT8) | HC8: =SUM(FE8:FG8) | HE8: =SUM(FT8:FV8) | HG8: =HE8-HC8 | HH8: =HG8/HC8 | HJ8: =SUM(AQ8:AS8) | HL8: =SUM(BU8:BW8) | HN8: =SUM(FH8:FJ8) | HP8: =SUM(FW8:FY8) | HR8: =HP8-HN8 | HS8: =HR8/HN8 | HU8: =SUM(BJ8:BL8) | HW8: =SUM(CN8:CP8) | HY8: =SUM(GA8:GC8) | IA8: =SUM(GP8:GR8) | IC8: =IA8-HY8 | ID8: =IC8/HY8 | IF8: =BM8 | IH8: =EZ8 | IJ8: =FO8 | IL8: =IJ8-IH8 | IM8: =IL8/IH8 | IO8: =SUM(IQ8:JB8) | IQ8: ='Rec.'!DN8 | IR8: ='Rec.'!DO8 | IS8: ='Rec.'!DP8 | IT8: ='Rec.'!DQ8 | IU8: ='Rec.'!DR8 | IV8: ='Rec.'!DS8 | IW8: ='Rec.'!DT8 | IX8: ='Rec.'!DU8 | ... JB8: ='Rec.'!DY8 | JD8: =SUM(JF8:JQ8) | JF8: ='Rec.'!EC8 | JG8: ='Rec.'!ED8 | JH8: ='Rec.'!EE8 | JI8: ='Rec.'!EF8 | JJ8: ='Rec.'!EG8 | JK8: ='Rec.'!EH8 | JL8: ='Rec.'!EI8 | JM8: ='Rec.'!EJ8 | ... JQ8: ='Rec.'!EN8 | JT8: =_xlfn.XLOOKUP($JT$3,$FQ$6:$GB$6,$FQ8:$GB8) | JV8: =_xlfn.XLOOKUP($JT$4,$IQ$6:$JB$6,$IQ8:$JB8) | JX8: =_xlfn.XLOOKUP($JT$4,$JF$6:$JQ$6,$JF8:$JQ8) | JZ8: =JX8-JV8 | KA8: =JZ8/JV8 | KC8: =SUM(BO8:BQ8) | KE8: =SUM(FQ8:FS8) | KG8: =SUM(IQ8:IS8) | KI8: =SUM(JF8:JH8) | KK8: =KI8-KG8 | KL8: =KK8/KG8 | KN8: =SUM(BR8:BT8) | KP8: =SUM(FT8:FV8) | KR8: =SUM(IT8:IV8) | KT8: =SUM(JI8:JK8) | KV8: =KT8-KR8 | KW8: =KV8/KR8 | KY8: =SUM(BU8:BW8) | LA8: =SUM(FW8:FY8) | LC8: =SUM(IW8:IY8) | LE8: =SUM(JL8:JN8) | LG8: =LE8-LC8 | LH8: =LG8/LC8 | LJ8: =SUM(BX8:BZ8) | LL8: =SUM(FZ8:GB8) | LN8: =SUM(IZ8:JB8) | LP8: =SUM(JO8:JQ8) | LR8: =LP8-LN8 | LS8: =LR8/LN8 | LU8: =FO8 | LW8: =IO8 | LY8: =JD8 | MA8: =LY8-LW8 | MB8: =MA8/LW8
A9: 4 | JV9: =_xlfn.XLOOKUP($JT$4,$IQ$6:$JB$6,$IQ9:$JB9)
A10: 5 | C10: Deduções da Receita de Vendas | E10: -737127.13 | G10: -52468.59 | H10: -48808.18 | I10: -45753.66 | J10: -53585.83 | K10: -71070.87 | L10: -58896 | M10: -74286 | N10: -89336 | O10: -62671 | P10: -58013 | Q10: -63413 | R10: -58825 | T10: =SUM(V10:AG10) | V10: ='Rec.'!V14 | W10: ='Rec.'!W14 | X10: ='Rec.'!X14 | Y10: ='Rec.'!Y14 | Z10: ='Rec.'!Z14 | AA10: ='Rec.'!AA14 | AB10: ='Rec.'!AB14 | AC10: ='Rec.'!AC14 | ... AG10: ='Rec.'!AG14 | AI10: =SUM(AK10:AV10) | AK10: ='Rec.'!AK14 | AL10: ='Rec.'!AL14 | AM10: ='Rec.'!AM14 | AN10: ='Rec.'!AN14 | AO10: ='Rec.'!AO14 | AP10: ='Rec.'!AP14 | AQ10: ='Rec.'!AQ14 | AR10: ='Rec.'!AR14 | ... AV10: ='Rec.'!AV14 | AX10: =SUM(AZ10:BK10) | AZ10: ='Rec.'!AZ14 | BA10: ='Rec.'!BA14 | BB10: ='Rec.'!BB14 | BC10: ='Rec.'!BC14 | BD10: ='Rec.'!BD14 | BE10: ='Rec.'!BE14 | BF10: ='Rec.'!BF14 | BG10: ='Rec.'!BG14 | ... BK10: ='Rec.'!BK14 | BM10: =SUM(BO10:BZ10) | BO10: ='Rec.'!BO14 | BP10: ='Rec.'!BP14 | BQ10: ='Rec.'!BQ14 | BR10: ='Rec.'!BR14 | BS10: ='Rec.'!BS14 | BT10: ='Rec.'!BT14 | BU10: ='Rec.'!BU14 | BV10: ='Rec.'!BV14 | ... BZ10: ='Rec.'!BZ14 | CB10: =HLOOKUP($CB$5,$V$6:$AG$37,$A10,0) | CD10: =HLOOKUP($CD$5,$AK$6:$AV$37,$A10,0) | CF10: =HLOOKUP($CB$4,$AZ$6:$BK$37,$A10,0) | CH10: =HLOOKUP($CB$4,$BO$6:$BZ$37,$A10,0) | CJ10: =CH10-CF10 | CK10: =-CJ10/CF10 | CM10: =SUM(G10:Q10) | CO10: =SUM(AK10:AU10) | CQ10: =SUM(AZ10:BJ10) | CS10: =CQ10-CO10 | CT10: =-CS10/CO10 | CV10: =SUM(V10:X10) | CX10: =SUM(AK10:AM10) | CZ10: =SUM(AZ10:BB10) | DB10: =SUM(BO10:BQ10) | DD10: =DB10-CZ10 | DE10: =DD10/CZ10 | DG10: =SUM(J10:L10) | DI10: =SUM(Y10:AA10) | DK10: =SUM(AN10:AP10) | DM10: =SUM(BC10:BE10) | DO10: =DM10-DK10 | DP10: =DO10/DK10 | DR10: =SUM(M10:O10) | DT10: =SUM(AB10:AD10) | DV10: =SUM(AQ10:AS10) | DX10: =SUM(BF10:BH10) | DZ10: =DX10-DV10 | EA10: =DZ10/DV10 | EC10: =SUM(AN10:AP10) | EE10: =SUM(AE10:AG10) | EG10: =SUM(BC10:BE10) | EI10: =SUM(CH10:CJ10) | EK10: =EI10-EG10 | EL10: =EK10/EG10 | EN10: =SUM(G10:L10) | EP10: =SUM(V10:AA10) | ER10: =SUM(AK10:AP10) | ET10: =SUM(AZ10:BE10) | EV10: =ET10-ER10 | EW10: =EV10/ER10 | EZ10: =SUM(FB10:FM10) | FB10: ='Rec.'!CG14 | FC10: ='Rec.'!CH14 | FD10: ='Rec.'!CI14 | FE10: ='Rec.'!CJ14 | FF10: ='Rec.'!CK14 | FG10: ='Rec.'!CL14 | FH10: ='Rec.'!CM14 | FI10: ='Rec.'!CN14 | ... FM10: ='Rec.'!CR14 | FO10: =SUM(FQ10:GB10) | FQ10: ='Rec.'!CV14 | FR10: ='Rec.'!CW14 | FS10: ='Rec.'!CX14 | FT10: ='Rec.'!CY14 | FU10: ='Rec.'!CZ14 | FV10: ='Rec.'!DA14 | FW10: ='Rec.'!DB14 | FX10: ='Rec.'!DC14 | ... GB10: ='Rec.'!DG14 | GE10: =_xlfn.XLOOKUP($GE$3,$BO$6:$BZ$6,$BO10:$BZ10) | GG10: =_xlfn.XLOOKUP($GE$4,$FB$6:$FM$6,$FB10:$FM10) | GI10: =_xlfn.XLOOKUP($GE$4,$FQ$6:$GB$6,$FQ10:$GB10) | GK10: =GI10-GG10 | GL10: =-GK10/GG10 | GN10: =SUM(AK10:AM10) | GP10: =SUM(BO10:BQ10) | GR10: =SUM(FB10:FD10) | GT10: =SUM(FQ10:FS10) | GV10: =GT10-GR10 | GW10: =-GV10/GR10 | GY10: =SUM(AN10:AP10) | HA10: =SUM(BR10:BT10) | HC10: =SUM(FE10:FG10) | HE10: =SUM(FT10:FV10) | HG10: =HE10-HC10 | HH10: =-HG10/HC10 | HJ10: =SUM(AQ10:AS10) | HL10: =SUM(BU10:BW10) | HN10: =SUM(FH10:FJ10) | HP10: =SUM(FW10:FY10) | HR10: =HP10-HN10 | HS10: =-HR10/HN10 | HU10: =SUM(BJ10:BL10) | HW10: =SUM(CN10:CP10) | HY10: =SUM(GA10:GC10) | IA10: =SUM(GP10:GR10) | IC10: =IA10-HY10 | ID10: =-IC10/HY10 | IF10: =BM10 | IH10: =EZ10 | IJ10: =FO10 | IL10: =IJ10-IH10 | IM10: =IL10/IH10 | IO10: =SUM(IQ10:JB10) | IQ10: ='Rec.'!DN14 | IR10: ='Rec.'!DO14 | IS10: ='Rec.'!DP14 | IT10: ='Rec.'!DQ14 | IU10: ='Rec.'!DR14 | IV10: ='Rec.'!DS14 | IW10: ='Rec.'!DT14 | IX10: ='Rec.'!DU14 | ... JB10: ='Rec.'!DY14 | JD10: =SUM(JF10:JQ10) | JF10: ='Rec.'!EC14 | JG10: ='Rec.'!ED14 | JH10: ='Rec.'!EE14 | JI10: ='Rec.'!EF14 | JJ10: ='Rec.'!EG14 | JK10: ='Rec.'!EH14 | JL10: ='Rec.'!EI14 | JM10: ='Rec.'!EJ14 | ... JQ10: ='Rec.'!EN14 | JT10: =_xlfn.XLOOKUP($JT$3,$FQ$6:$GB$6,$FQ10:$GB10) | JV10: =_xlfn.XLOOKUP($JT$4,$IQ$6:$JB$6,$IQ10:$JB10) | JX10: =_xlfn.XLOOKUP($JT$4,$JF$6:$JQ$6,$JF10:$JQ10) | JZ10: =JX10-JV10 | KA10: =-JZ10/JV10 | KC10: =SUM(BO10:BQ10) | KE10: =SUM(FQ10:FS10) | KG10: =SUM(IQ10:IS10) | KI10: =SUM(JF10:JH10) | KK10: =KI10-KG10 | KL10: =-KK10/KG10 | KN10: =SUM(BR10:BT10) | KP10: =SUM(FT10:FV10) | KR10: =SUM(IT10:IV10) | KT10: =SUM(JI10:JK10) | KV10: =KT10-KR10 | KW10: =-KV10/KR10 | KY10: =SUM(BU10:BW10) | LA10: =SUM(FW10:FY10) | LC10: =SUM(IW10:IY10) | LE10: =SUM(JL10:JN10) | LG10: =LE10-LC10 | LH10: =-LG10/LC10 | LJ10: =SUM(BX10:BZ10) | LL10: =SUM(FZ10:GB10) | LN10: =SUM(IZ10:JB10) | LP10: =SUM(JO10:JQ10) | LR10: =LP10-LN10 | LS10: =-LR10/LN10 | LU10: =FO10 | LW10: =IO10 | LY10: =JD10 | MA10: =LY10-LW10 | MB10: =MA10/LW10
A11: 6
